{"103rd-st-rosemoor-1b20":{"m":104,"r":"X1|ME","x":1,"legs":[{"mode":"RAIL","line":"X1","from":"Ravinia","to":"Roosevelt","ride":51,"wait":7,"freq":30},{"mode":"RAIL","line":"ME","from":"Museum Campus/11th St.","to":"103rd St. (Rosemoor)","ride":21,"wait":8,"freq":20}]},"103rd-st-beverly-hills-1bbb":{"m":105,"r":"X1|RI","x":1,"legs":[{"mode":"RAIL","line":"X1","from":"Ravinia","to":"Chicago Union Station","ride":47,"wait":7,"freq":30},{"mode":"RAIL","line":"RI","from":"LaSalle Street","to":"103rd St. - Beverly Hills","ride":26,"wait":6,"freq":60}]},"103rd-st-washington-hts-1b8d":{"m":115,"r":"X1|RI","x":1,"legs":[{"mode":"RAIL","line":"X1","from":"Ravinia","to":"Chicago Union Station","ride":47,"wait":7,"freq":30},{"mode":"RAIL","line":"RI","from":"LaSalle Street","to":"103rd St. - Beverly Hills","ride":26,"wait":6,"freq":60}]},"103rd-street-1af9":{"m":108,"r":"X1|Red|RLE","x":2,"legs":[{"mode":"RAIL","line":"X1","from":"Ravinia","to":"Roosevelt","ride":51,"wait":7,"freq":30},{"mode":"SUBWAY","line":"Red","from":"Roosevelt","to":"95th/Dan Ryan","ride":23,"wait":4,"freq":3},{"mode":"SUBWAY","line":"RLE","from":"95th/Dan Ryan","to":"103rd Street","ride":3,"wait":10,"freq":6}]},"107th-st-1bcc":{"m":107,"r":"X1|X3","x":1,"legs":[{"mode":"RAIL","line":"X1","from":"Ravinia","to":"Clybourn","ride":37,"wait":7,"freq":15},{"mode":"RAIL","line":"X3","from":"Clybourn","to":"107th St.","ride":49,"wait":8,"freq":15}]},"107th-st-beverly-hills-1b2e":{"m":107,"r":"X1|RI","x":1,"legs":[{"mode":"RAIL","line":"X1","from":"Ravinia","to":"Chicago Union Station","ride":47,"wait":7,"freq":30},{"mode":"RAIL","line":"RI","from":"LaSalle Street","to":"107th St. - Beverly Hills","ride":28,"wait":6,"freq":60}]},"111th-st-pullman-1b0f":{"m":109,"r":"X1|X3","x":1,"legs":[{"mode":"RAIL","line":"X1","from":"Ravinia","to":"Clybourn","ride":37,"wait":7,"freq":15},{"mode":"RAIL","line":"X3","from":"Clybourn","to":"111th St. (Pullman)","ride":50,"wait":8,"freq":15}]},"111th-st-morgan-park-1b63":{"m":111,"r":"X1|RI","x":1,"legs":[{"mode":"RAIL","line":"X1","from":"Ravinia","to":"Chicago Union Station","ride":47,"wait":7,"freq":30},{"mode":"RAIL","line":"RI","from":"LaSalle Street","to":"111th St. - Morgan Park","ride":30,"wait":6,"freq":60}]},"111th-street-1b3d":{"m":108,"r":"X1|Red|RLE","x":2,"legs":[{"mode":"RAIL","line":"X1","from":"Ravinia","to":"Roosevelt","ride":51,"wait":7,"freq":30},{"mode":"SUBWAY","line":"Red","from":"Roosevelt","to":"95th/Dan Ryan","ride":23,"wait":4,"freq":3},{"mode":"SUBWAY","line":"RLE","from":"95th/Dan Ryan","to":"111th Street","ride":5,"wait":10,"freq":5}]},"115th-st-morgan-park-1b57":{"m":111,"r":"X1|RI","x":1,"legs":[{"mode":"RAIL","line":"X1","from":"Ravinia","to":"Chicago Union Station","ride":47,"wait":7,"freq":30},{"mode":"RAIL","line":"RI","from":"LaSalle Street","to":"115th St. - Morgan Park","ride":32,"wait":6,"freq":60}]},"119th-rlx-1b6d":{"m":115,"r":"X1|X3","x":1,"legs":[{"mode":"RAIL","line":"X1","from":"Ravinia","to":"Clybourn","ride":37,"wait":7,"freq":15},{"mode":"RAIL","line":"X3","from":"Clybourn","to":"119th (RLX)","ride":54,"wait":8,"freq":30}]},"119th-st-1b63":{"m":113,"r":"X1|RI","x":1,"legs":[{"mode":"RAIL","line":"X1","from":"Ravinia","to":"Chicago Union Station","ride":47,"wait":7,"freq":30},{"mode":"RAIL","line":"RI","from":"LaSalle Street","to":"119th St.","ride":34,"wait":6,"freq":60}]},"123rd-st-1b42":{"m":124,"r":"X1|X6","x":1,"legs":[{"mode":"RAIL","line":"X1","from":"Ravinia","to":"Chicago Union Station","ride":47,"wait":7,"freq":30},{"mode":"RAIL","line":"X6","from":"Chicago Union Station","to":"123rd St.","ride":39,"wait":23,"freq":30}]},"130th-street-1b9c":{"m":115,"r":"X1|Red|RLE","x":2,"legs":[{"mode":"RAIL","line":"X1","from":"Ravinia","to":"Roosevelt","ride":51,"wait":7,"freq":30},{"mode":"SUBWAY","line":"Red","from":"Roosevelt","to":"95th/Dan Ryan","ride":23,"wait":4,"freq":3},{"mode":"SUBWAY","line":"RLE","from":"95th/Dan Ryan","to":"130th Street","ride":10,"wait":10,"freq":10}]},"130th-indiana-1ba2":{"m":116,"r":"X1|X3","x":1,"legs":[{"mode":"RAIL","line":"X1","from":"Ravinia","to":"Clybourn","ride":37,"wait":7,"freq":15},{"mode":"RAIL","line":"X3","from":"Clybourn","to":"130th/Indiana","ride":56,"wait":8,"freq":30}]},"147th-st-1b12":{"m":117,"r":"X1|ME","x":1,"legs":[{"mode":"RAIL","line":"X1","from":"Ravinia","to":"Roosevelt","ride":51,"wait":7,"freq":30},{"mode":"RAIL","line":"ME","from":"Museum Campus/11th St.","to":"147th St.","ride":33,"wait":8,"freq":30}]},"18th-1ba5":{"m":75,"r":"X1|Pink","x":1,"legs":[{"mode":"RAIL","line":"X1","from":"Ravinia","to":"Clinton (Green/Pink)","ride":45,"wait":7,"freq":30},{"mode":"SUBWAY","line":"Pink","from":"Clinton (Green/Pink)","to":"18th","ride":8,"wait":4}]},"18th-st-1b2c":{"m":68,"r":"X1","x":0,"legs":[{"mode":"RAIL","line":"X1","from":"Ravinia","to":"18th St.","ride":53,"wait":7,"freq":30}]},"211th-st-1b7d":{"m":134,"r":"X1|ME","x":1,"legs":[{"mode":"RAIL","line":"X1","from":"Ravinia","to":"Roosevelt","ride":51,"wait":7,"freq":30},{"mode":"RAIL","line":"ME","from":"Museum Campus/11th St.","to":"211th St.","ride":50,"wait":8,"freq":30}]},"27th-st-1add":{"m":72,"r":"X1","x":0,"legs":[{"mode":"RAIL","line":"X1","from":"Ravinia","to":"27th St.","ride":57,"wait":7,"freq":30}]},"35th-st-lou-jones-1b2c":{"m":79,"r":"X1|Red","x":1,"legs":[{"mode":"RAIL","line":"X1","from":"Ravinia","to":"Roosevelt","ride":51,"wait":7,"freq":30},{"mode":"SUBWAY","line":"Red","from":"Roosevelt","to":"35th St. - Lou Jones","ride":6,"wait":4,"freq":4}]},"35th-bronzeville-iit-1b65":{"m":78,"r":"X1|G","x":1,"legs":[{"mode":"RAIL","line":"X1","from":"Ravinia","to":"Roosevelt","ride":51,"wait":7,"freq":30},{"mode":"SUBWAY","line":"G","from":"Roosevelt","to":"35th-Bronzeville-IIT","ride":8,"wait":3,"freq":5}]},"35th-archer-1b64":{"m":82,"r":"X1|Org","x":1,"legs":[{"mode":"RAIL","line":"X1","from":"Ravinia","to":"Roosevelt","ride":51,"wait":7,"freq":30},{"mode":"SUBWAY","line":"Org","from":"Roosevelt","to":"35th/Archer","ride":8,"wait":7,"freq":9}]},"43rd-1b19":{"m":83,"r":"X1|G","x":1,"legs":[{"mode":"RAIL","line":"X1","from":"Ravinia","to":"Roosevelt","ride":51,"wait":7,"freq":30},{"mode":"SUBWAY","line":"G","from":"Roosevelt","to":"43rd","ride":13,"wait":3,"freq":9}]},"47th-green-1b82":{"m":84,"r":"X1|G","x":1,"legs":[{"mode":"RAIL","line":"X1","from":"Ravinia","to":"Roosevelt","ride":51,"wait":7,"freq":30},{"mode":"SUBWAY","line":"G","from":"Roosevelt","to":"47th (Green)","ride":14,"wait":3,"freq":9}]},"47th-red-1b0c":{"m":81,"r":"X1|Red","x":1,"legs":[{"mode":"RAIL","line":"X1","from":"Ravinia","to":"Roosevelt","ride":51,"wait":7,"freq":30},{"mode":"SUBWAY","line":"Red","from":"Roosevelt","to":"47th (Red)","ride":10,"wait":4,"freq":4}]},"47th-st-kenwood-1b5f":{"m":76,"r":"X1","x":0,"legs":[{"mode":"RAIL","line":"X1","from":"Ravinia","to":"47th St. (Kenwood)","ride":61,"wait":7,"freq":30}]},"51st-1b21":{"m":86,"r":"X1|G","x":1,"legs":[{"mode":"RAIL","line":"X1","from":"Ravinia","to":"Roosevelt","ride":51,"wait":7,"freq":30},{"mode":"SUBWAY","line":"G","from":"Roosevelt","to":"51st","ride":16,"wait":3,"freq":9}]},"51st-53rd-st-hyde-park-1b85":{"m":76,"r":"X1","x":0,"legs":[{"mode":"RAIL","line":"X1","from":"Ravinia","to":"51st/53rd St. (Hyde Park)","ride":62,"wait":7,"freq":30}]},"54th-cermak-1bac":{"m":90,"r":"X1|Pink","x":1,"legs":[{"mode":"RAIL","line":"X1","from":"Ravinia","to":"Clinton (Green/Pink)","ride":45,"wait":7,"freq":30},{"mode":"SUBWAY","line":"Pink","from":"Clinton (Green/Pink)","to":"54th/Cermak","ride":24,"wait":4}]},"55th-56th-57th-st-1ba4":{"m":79,"r":"X1","x":0,"legs":[{"mode":"RAIL","line":"X1","from":"Ravinia","to":"55th - 56th - 57th St.","ride":64,"wait":7,"freq":30}]},"59th-st-u-of-chicago-1bce":{"m":81,"r":"X1","x":0,"legs":[{"mode":"RAIL","line":"X1","from":"Ravinia","to":"59th St. (U. of Chicago)","ride":66,"wait":7,"freq":30}]},"59th-perry-1b4a":{"m":91,"r":"X1|Red|59","x":2,"legs":[{"mode":"RAIL","line":"X1","from":"Ravinia","to":"Roosevelt","ride":51,"wait":7,"freq":30},{"mode":"SUBWAY","line":"Red","from":"Roosevelt","to":"Garfield (Red)","ride":12,"wait":4,"freq":4},{"mode":"BUS","line":"59","from":"Garfield (Red)","to":"59th/Perry","ride":4,"wait":3,"freq":15}]},"63rd-1ab8":{"m":84,"r":"X1|Red","x":1,"legs":[{"mode":"RAIL","line":"X1","from":"Ravinia","to":"Roosevelt","ride":51,"wait":7,"freq":30},{"mode":"SUBWAY","line":"Red","from":"Roosevelt","to":"63rd","ride":14,"wait":4,"freq":4}]},"63rd-st-1b42":{"m":83,"r":"X1","x":0,"legs":[{"mode":"RAIL","line":"X1","from":"Ravinia","to":"63rd St.","ride":68,"wait":7,"freq":30}]},"67th-1b0d":{"m":84,"r":"X1","x":0,"legs":[{"mode":"RAIL","line":"X1","from":"Ravinia","to":"67th","ride":70,"wait":7,"freq":30}]},"69th-1b75":{"m":87,"r":"X1|Red","x":1,"legs":[{"mode":"RAIL","line":"X1","from":"Ravinia","to":"Roosevelt","ride":51,"wait":7,"freq":30},{"mode":"SUBWAY","line":"Red","from":"Roosevelt","to":"69th","ride":16,"wait":4,"freq":3}]},"75th-st-grand-crossing-1ba8":{"m":94,"r":"X1|X3","x":1,"legs":[{"mode":"RAIL","line":"X1","from":"Ravinia","to":"Clybourn","ride":37,"wait":7,"freq":15},{"mode":"RAIL","line":"X3","from":"Clybourn","to":"75th St. (Grand Crossing)","ride":36,"wait":8,"freq":15}]},"79th-1ae0":{"m":89,"r":"X1|Red","x":1,"legs":[{"mode":"RAIL","line":"X1","from":"Ravinia","to":"Roosevelt","ride":51,"wait":7,"freq":30},{"mode":"SUBWAY","line":"Red","from":"Roosevelt","to":"79th","ride":19,"wait":4,"freq":3}]},"79th-auburn-park-1b76":{"m":100,"r":"X1|Red|79","x":2,"legs":[{"mode":"RAIL","line":"X1","from":"Ravinia","to":"Roosevelt","ride":51,"wait":7,"freq":30},{"mode":"SUBWAY","line":"Red","from":"Roosevelt","to":"79th","ride":19,"wait":4,"freq":3},{"mode":"BUS","line":"79","from":"79th","to":"79th (Auburn Park)","ride":3,"wait":6,"freq":5}]},"79th-st-chatham-1b7f":{"m":97,"r":"X1|X3","x":1,"legs":[{"mode":"RAIL","line":"X1","from":"Ravinia","to":"Clybourn","ride":37,"wait":7,"freq":15},{"mode":"RAIL","line":"X3","from":"Clybourn","to":"79th St. (Chatham)","ride":38,"wait":8,"freq":15}]},"83rd-st-1b1e":{"m":97,"r":"X1","x":0,"legs":[{"mode":"RAIL","line":"X1","from":"Ravinia","to":"83rd St.","ride":81,"wait":7,"freq":30}]},"83rd-st-avalon-park-1bb7":{"m":97,"r":"X1|X3","x":1,"legs":[{"mode":"RAIL","line":"X1","from":"Ravinia","to":"Clybourn","ride":37,"wait":7,"freq":15},{"mode":"RAIL","line":"X3","from":"Clybourn","to":"83rd St. (Avalon Park)","ride":39,"wait":8,"freq":15}]},"87th-1b45":{"m":92,"r":"X1|Red","x":1,"legs":[{"mode":"RAIL","line":"X1","from":"Ravinia","to":"Roosevelt","ride":51,"wait":7,"freq":30},{"mode":"SUBWAY","line":"Red","from":"Roosevelt","to":"87th","ride":21,"wait":4,"freq":3}]},"87th-st-1b78":{"m":98,"r":"X1","x":0,"legs":[{"mode":"RAIL","line":"X1","from":"Ravinia","to":"87th St.","ride":83,"wait":7,"freq":30}]},"87th-st-woodruff-1ad6":{"m":99,"r":"X1|X3","x":1,"legs":[{"mode":"RAIL","line":"X1","from":"Ravinia","to":"Clybourn","ride":37,"wait":7,"freq":15},{"mode":"RAIL","line":"X3","from":"Clybourn","to":"87th St. (Woodruff)","ride":41,"wait":8,"freq":15}]},"91st-st-1b2f":{"m":103,"r":"X1|X3","x":1,"legs":[{"mode":"RAIL","line":"X1","from":"Ravinia","to":"Clybourn","ride":37,"wait":7,"freq":15},{"mode":"RAIL","line":"X3","from":"Clybourn","to":"91st St.","ride":43,"wait":8,"freq":15}]},"91st-st-beverly-hills-1b52":{"m":101,"r":"X1|RI","x":1,"legs":[{"mode":"RAIL","line":"X1","from":"Ravinia","to":"Chicago Union Station","ride":47,"wait":7,"freq":30},{"mode":"RAIL","line":"RI","from":"LaSalle Street","to":"91st St. - Beverly Hills","ride":20,"wait":6,"freq":60}]},"95th-st-1b40":{"m":103,"r":"X1|X3","x":1,"legs":[{"mode":"RAIL","line":"X1","from":"Ravinia","to":"Clybourn","ride":37,"wait":7,"freq":15},{"mode":"RAIL","line":"X3","from":"Clybourn","to":"95th St.","ride":45,"wait":8,"freq":15}]},"95th-st-beverly-hills-1b3d":{"m":100,"r":"X1|RI","x":1,"legs":[{"mode":"RAIL","line":"X1","from":"Ravinia","to":"Chicago Union Station","ride":47,"wait":7,"freq":30},{"mode":"RAIL","line":"RI","from":"LaSalle Street","to":"95th St. - Beverly Hills","ride":22,"wait":6,"freq":60}]},"95th-st-longwood-1ac1":{"m":106,"r":"X1|Red|381","x":2,"legs":[{"mode":"RAIL","line":"X1","from":"Ravinia","to":"Roosevelt","ride":51,"wait":7,"freq":30},{"mode":"SUBWAY","line":"Red","from":"Roosevelt","to":"95th/Dan Ryan","ride":23,"wait":4,"freq":3},{"mode":"BUS","line":"381","from":"95th/Dan Ryan","to":"95th St.-Longwood","ride":8,"wait":4,"freq":4}]},"95th-dan-ryan-1aee":{"m":93,"r":"X1|Red","x":1,"legs":[{"mode":"RAIL","line":"X1","from":"Ravinia","to":"Roosevelt","ride":51,"wait":7,"freq":30},{"mode":"SUBWAY","line":"Red","from":"Roosevelt","to":"95th/Dan Ryan","ride":23,"wait":4,"freq":3}]},"99th-st-beverly-hills-1b82":{"m":103,"r":"X1|RI","x":1,"legs":[{"mode":"RAIL","line":"X1","from":"Ravinia","to":"Chicago Union Station","ride":47,"wait":7,"freq":30},{"mode":"RAIL","line":"RI","from":"LaSalle Street","to":"99th St. - Beverly Hills","ride":24,"wait":6,"freq":60}]},"adams-wabash-1b2a":{"m":75,"r":"X1|G","x":1,"legs":[{"mode":"RAIL","line":"X1","from":"Ravinia","to":"Clinton (Green/Pink)","ride":45,"wait":7,"freq":30},{"mode":"SUBWAY","line":"G","from":"Clinton (Green/Pink)","to":"Adams/Wabash","ride":6,"wait":6,"freq":4}]},"addison-blue-1b81":{"m":68,"r":"X1|152","x":1,"legs":[{"mode":"RAIL","line":"X1","from":"Ravinia","to":"Addison (Brown)","ride":34,"wait":7,"freq":30},{"mode":"BUS","line":"152","from":"Addison (Brown)","to":"Addison (Blue)","ride":14,"wait":4,"freq":9}]},"addison-brown-1b78":{"m":50,"r":"X1","x":0,"legs":[{"mode":"RAIL","line":"X1","from":"Ravinia","to":"Addison (Brown)","ride":34,"wait":7,"freq":30}]},"addison-red-1b62":{"m":60,"r":"X1|152","x":1,"legs":[{"mode":"RAIL","line":"X1","from":"Ravinia","to":"Addison (Brown)","ride":34,"wait":7,"freq":30},{"mode":"BUS","line":"152","from":"Addison (Brown)","to":"Addison (Red)","ride":7,"wait":3,"freq":8}]},"argyle-1b94":{"m":58,"r":"X1|81|Red","x":2,"legs":[{"mode":"RAIL","line":"X1","from":"Ravinia","to":"Ravenswood","ride":32,"wait":7,"freq":15},{"mode":"BUS","line":"81","from":"Ravenswood","to":"Lawrence","ride":6,"wait":2,"freq":8},{"mode":"SUBWAY","line":"Red","from":"Lawrence","to":"Argyle","ride":1,"wait":3,"freq":5}]},"arlington-heights-1b8c":{"m":91,"r":"X1|X3","x":1,"legs":[{"mode":"RAIL","line":"X1","from":"Ravinia","to":"Clybourn","ride":37,"wait":7,"freq":15},{"mode":"RAIL","line":"X3","from":"Clybourn","to":"Arlington Heights","ride":33,"wait":6,"freq":12}]},"arlington-park-1ade":{"m":94,"r":"X1|X3","x":1,"legs":[{"mode":"RAIL","line":"X1","from":"Ravinia","to":"Clybourn","ride":37,"wait":7,"freq":15},{"mode":"RAIL","line":"X3","from":"Clybourn","to":"Arlington Park","ride":36,"wait":6,"freq":12}]},"armitage-brown-purple-1b43":{"m":65,"r":"X1|Brn","x":1,"legs":[{"mode":"RAIL","line":"X1","from":"Ravinia","to":"Addison (Brown)","ride":34,"wait":7,"freq":30},{"mode":"SUBWAY","line":"Brn","from":"Addison (Brown)","to":"Armitage (Brown/Purple)","ride":12,"wait":6,"freq":4}]},"ashburn-1b08":{"m":115,"r":"X1|SWS","x":1,"legs":[{"mode":"RAIL","line":"X1","from":"Ravinia","to":"Chicago Union Station","ride":47,"wait":7,"freq":30},{"mode":"RAIL","line":"SWS","from":"Chicago Union Station","to":"Ashburn","ride":27,"wait":33,"freq":60}]},"ashland-1b54":{"m":126,"r":"X1|RI|X4","x":2,"legs":[{"mode":"RAIL","line":"X1","from":"Ravinia","to":"Chicago Union Station","ride":47,"wait":7,"freq":30},{"mode":"RAIL","line":"RI","from":"LaSalle Street","to":"Blue Island-Vermont","ride":40,"wait":6,"freq":30},{"mode":"RAIL","line":"X4","from":"Blue Island","to":"Ashland","ride":4,"wait":2,"freq":20}]},"ashland-green-pink-1b50":{"m":66,"r":"X1|G","x":1,"legs":[{"mode":"RAIL","line":"X1","from":"Ravinia","to":"Clinton (Green/Pink)","ride":45,"wait":7,"freq":30},{"mode":"SUBWAY","line":"G","from":"Clinton (Green/Pink)","to":"Ashland (Green/Pink)","ride":3,"wait":2,"freq":9}]},"ashland-orange-1b5a":{"m":80,"r":"X1|Org","x":1,"legs":[{"mode":"RAIL","line":"X1","from":"Ravinia","to":"Roosevelt","ride":51,"wait":7,"freq":30},{"mode":"SUBWAY","line":"Org","from":"Roosevelt","to":"Ashland (Orange)","ride":6,"wait":7,"freq":9}]},"ashland-ogden-1bd0":{"m":69,"r":"X1|X9","x":1,"legs":[{"mode":"RAIL","line":"X1","from":"Ravinia","to":"Clybourn","ride":37,"wait":7,"freq":15},{"mode":"BUS","line":"X9","from":"Clybourn","to":"Ashland-Ogden","ride":10,"wait":3}]},"ashland-63rd-1bc7":{"m":103,"r":"X1|Red|63","x":2,"legs":[{"mode":"RAIL","line":"X1","from":"Ravinia","to":"Roosevelt","ride":51,"wait":7,"freq":30},{"mode":"SUBWAY","line":"Red","from":"Roosevelt","to":"63rd","ride":14,"wait":4,"freq":4},{"mode":"BUS","line":"63","from":"63rd","to":"Ashland/63rd","ride":14,"wait":4,"freq":9}]},"aurora-1b16":{"m":159,"r":"X1|BNSF","x":1,"legs":[{"mode":"RAIL","line":"X1","from":"Ravinia","to":"Chicago Union Station","ride":47,"wait":7,"freq":30},{"mode":"RAIL","line":"BNSF","from":"Chicago Union Station","to":"Aurora","ride":78,"wait":24,"freq":60}]},"austin-blue-1be3":{"m":97,"r":"X1|G|315","x":2,"legs":[{"mode":"RAIL","line":"X1","from":"Ravinia","to":"Clinton (Green/Pink)","ride":45,"wait":7,"freq":30},{"mode":"SUBWAY","line":"G","from":"Clinton (Green/Pink)","to":"Austin (Green)","ride":20,"wait":2,"freq":9},{"mode":"BUS","line":"315","from":"Austin (Green)","to":"Austin (Blue)","ride":7,"wait":2}]},"austin-green-1b5a":{"m":84,"r":"X1|G","x":1,"legs":[{"mode":"RAIL","line":"X1","from":"Ravinia","to":"Clinton (Green/Pink)","ride":45,"wait":7,"freq":30},{"mode":"SUBWAY","line":"G","from":"Clinton (Green/Pink)","to":"Austin (Green)","ride":20,"wait":2,"freq":9}]},"barrington-1b0e":{"m":152,"r":"X1|UP-NW","x":1,"legs":[{"mode":"RAIL","line":"X1","from":"Ravinia","to":"Clinton (Green/Pink)","ride":45,"wait":7,"freq":30},{"mode":"RAIL","line":"UP-NW","from":"Chicago OTC","to":"Barrington","ride":62,"wait":24,"freq":60}]},"bartlett-1b7a":{"m":139,"r":"X1|MD-W","x":1,"legs":[{"mode":"RAIL","line":"X1","from":"Ravinia","to":"Chicago Union Station","ride":47,"wait":7,"freq":30},{"mode":"RAIL","line":"MD-W","from":"Chicago Union Station","to":"Bartlett","ride":59,"wait":21,"freq":60}]},"bellwood-1b7f":{"m":114,"r":"X1|X6","x":1,"legs":[{"mode":"RAIL","line":"X1","from":"Ravinia","to":"Chicago Union Station","ride":47,"wait":7,"freq":30},{"mode":"RAIL","line":"X6","from":"Chicago Union Station","to":"Bellwood","ride":24,"wait":31,"freq":30}]},"belmont-1b03":{"m":136,"r":"X1|BNSF","x":1,"legs":[{"mode":"RAIL","line":"X1","from":"Ravinia","to":"Chicago Union Station","ride":47,"wait":7,"freq":30},{"mode":"RAIL","line":"BNSF","from":"Chicago Union Station","to":"Belmont","ride":53,"wait":24,"freq":60}]},"belmont-blue-1af1":{"m":68,"r":"X1|X3","x":1,"legs":[{"mode":"RAIL","line":"X1","from":"Ravinia","to":"Clybourn","ride":37,"wait":7,"freq":15},{"mode":"RAIL","line":"X3","from":"Clybourn","to":"Belmont/Kedzie","ride":4,"wait":6,"freq":15}]},"belmont-red-brown-purple-1b6c":{"m":58,"r":"X1|Brn","x":1,"legs":[{"mode":"RAIL","line":"X1","from":"Ravinia","to":"Addison (Brown)","ride":34,"wait":7,"freq":30},{"mode":"SUBWAY","line":"Brn","from":"Addison (Brown)","to":"Belmont (Red/Brown/Purple)","ride":6,"wait":6,"freq":4}]},"belmont-kedzie-1b51":{"m":62,"r":"X1|X3","x":1,"legs":[{"mode":"RAIL","line":"X1","from":"Ravinia","to":"Clybourn","ride":37,"wait":7,"freq":15},{"mode":"RAIL","line":"X3","from":"Clybourn","to":"Belmont/Kedzie","ride":4,"wait":6,"freq":15}]},"bensenville-1bb6":{"m":117,"r":"X1|MD-W","x":1,"legs":[{"mode":"RAIL","line":"X1","from":"Ravinia","to":"Chicago Union Station","ride":47,"wait":7,"freq":30},{"mode":"RAIL","line":"MD-W","from":"Chicago Union Station","to":"Bensenville","ride":33,"wait":21,"freq":60}]},"berkeley-1b40":{"m":126,"r":"X1|X6|UP-W","x":2,"legs":[{"mode":"RAIL","line":"X1","from":"Ravinia","to":"Chicago Union Station","ride":47,"wait":7,"freq":30},{"mode":"RAIL","line":"X6","from":"Chicago Union Station","to":"Elmhurst","ride":30,"wait":31,"freq":30},{"mode":"RAIL","line":"UP-W","from":"Elmhurst","to":"Berkeley","ride":3,"wait":3,"freq":15}]},"berwyn-1b78":{"m":96,"r":"X1|X5","x":1,"legs":[{"mode":"RAIL","line":"X1","from":"Ravinia","to":"Chicago Union Station","ride":47,"wait":7,"freq":30},{"mode":"RAIL","line":"X5","from":"Chicago Union Station","to":"Berwyn","ride":20,"wait":18,"freq":20}]},"berwyn-1bbd":{"m":58,"r":"X1|Red","x":1,"legs":[{"mode":"RAIL","line":"X1","from":"Ravinia","to":"Howard/Clark","ride":26,"wait":7,"freq":30},{"mode":"SUBWAY","line":"Red","from":"Howard","to":"Berwyn","ride":11,"wait":3,"freq":4}]},"big-timber-1b76":{"m":162,"r":"X1|MD-W","x":1,"legs":[{"mode":"RAIL","line":"X1","from":"Ravinia","to":"Chicago Union Station","ride":47,"wait":7,"freq":30},{"mode":"RAIL","line":"MD-W","from":"Chicago Union Station","to":"Big Timber","ride":82,"wait":21,"freq":60}]},"blue-island-1ba1":{"m":119,"r":"X1|RI","x":1,"legs":[{"mode":"RAIL","line":"X1","from":"Ravinia","to":"Chicago Union Station","ride":47,"wait":7,"freq":30},{"mode":"RAIL","line":"RI","from":"LaSalle Street","to":"Blue Island-Vermont","ride":40,"wait":6,"freq":30}]},"blue-island-vermont-1bdd":{"m":115,"r":"X1|RI","x":1,"legs":[{"mode":"RAIL","line":"X1","from":"Ravinia","to":"Chicago Union Station","ride":47,"wait":7,"freq":30},{"mode":"RAIL","line":"RI","from":"LaSalle Street","to":"Blue Island-Vermont","ride":40,"wait":6,"freq":30}]},"braeside-1b58":{"m":10},"brainerd-1bab":{"m":97,"r":"X1|RI","x":1,"legs":[{"mode":"RAIL","line":"X1","from":"Ravinia","to":"Chicago Union Station","ride":47,"wait":7,"freq":30},{"mode":"RAIL","line":"RI","from":"LaSalle Street","to":"Brainerd","ride":18,"wait":6,"freq":60}]},"brookfield-1b16":{"m":110,"r":"X1|BNSF","x":1,"legs":[{"mode":"RAIL","line":"X1","from":"Ravinia","to":"Chicago Union Station","ride":47,"wait":7,"freq":30},{"mode":"RAIL","line":"BNSF","from":"Chicago Union Station","to":"Brookfield","ride":27,"wait":24,"freq":60}]},"bryn-mawr-1b9c":{"m":88,"r":"X1","x":0,"legs":[{"mode":"RAIL","line":"X1","from":"Ravinia","to":"Bryn Mawr","ride":73,"wait":7,"freq":30}]},"bryn-mawr-1bd7":{"m":57,"r":"X1|Red","x":1,"legs":[{"mode":"RAIL","line":"X1","from":"Ravinia","to":"Howard/Clark","ride":26,"wait":7,"freq":30},{"mode":"SUBWAY","line":"Red","from":"Howard","to":"Bryn Mawr","ride":10,"wait":3,"freq":4}]},"buffalo-grove-1b44":{"m":95,"r":"213|626","x":1,"legs":[{"mode":"BUS","line":"213","from":"Braeside","to":"Ravinia","ride":4,"wait":18,"freq":20},{"mode":"BUS","line":"626","from":"Ravinia Park","to":"Buffalo Grove","ride":35,"wait":14}]},"burr-oak-1bc4":{"m":127,"r":"X1|RI|X4","x":2,"legs":[{"mode":"RAIL","line":"X1","from":"Ravinia","to":"Chicago Union Station","ride":47,"wait":7,"freq":30},{"mode":"RAIL","line":"RI","from":"LaSalle Street","to":"Blue Island-Vermont","ride":40,"wait":6,"freq":30},{"mode":"RAIL","line":"X4","from":"Blue Island","to":"Burr Oak","ride":2,"wait":2,"freq":20}]},"california-blue-1b67":{"m":73,"r":"X1|X3|74","x":2,"legs":[{"mode":"RAIL","line":"X1","from":"Ravinia","to":"Clybourn","ride":37,"wait":7,"freq":15},{"mode":"RAIL","line":"X3","from":"Clybourn","to":"Western/Logan","ride":2,"wait":6,"freq":15},{"mode":"BUS","line":"74","from":"Western/Logan","to":"California (Blue)","ride":2,"wait":2}]},"california-green-1b7e":{"m":71,"r":"X1|G","x":1,"legs":[{"mode":"RAIL","line":"X1","from":"Ravinia","to":"Clinton (Green/Pink)","ride":45,"wait":7,"freq":30},{"mode":"SUBWAY","line":"G","from":"Clinton (Green/Pink)","to":"California (Green)","ride":7,"wait":2,"freq":9}]},"california-pink-1baa":{"m":80,"r":"X1|Pink","x":1,"legs":[{"mode":"RAIL","line":"X1","from":"Ravinia","to":"Clinton (Green/Pink)","ride":45,"wait":7,"freq":30},{"mode":"SUBWAY","line":"Pink","from":"Clinton (Green/Pink)","to":"California (Pink)","ride":14,"wait":4}]},"calumet-1b4d":{"m":124,"r":"X1|ME","x":1,"legs":[{"mode":"RAIL","line":"X1","from":"Ravinia","to":"Roosevelt","ride":51,"wait":7,"freq":30},{"mode":"RAIL","line":"ME","from":"Museum Campus/11th St.","to":"Calumet","ride":40,"wait":8,"freq":30}]},"cary-1aef":{"m":154,"r":"X1|UP-NW","x":1,"legs":[{"mode":"RAIL","line":"X1","from":"Ravinia","to":"Clinton (Green/Pink)","ride":45,"wait":7,"freq":30},{"mode":"RAIL","line":"UP-NW","from":"Chicago OTC","to":"Cary","ride":73,"wait":24,"freq":60}]},"central-green-1bb2":{"m":82,"r":"X1|G","x":1,"legs":[{"mode":"RAIL","line":"X1","from":"Ravinia","to":"Clinton (Green/Pink)","ride":45,"wait":7,"freq":30},{"mode":"SUBWAY","line":"G","from":"Clinton (Green/Pink)","to":"Central (Green)","ride":18,"wait":2,"freq":9}]},"central-purple-1b6b":{"m":43,"r":"X1|P","x":1,"legs":[{"mode":"RAIL","line":"X1","from":"Ravinia","to":"Evanston (Davis St.)","ride":22,"wait":7,"freq":15},{"mode":"SUBWAY","line":"P","from":"Evanston (Davis St.)","to":"Central (Purple)","ride":4,"wait":5,"freq":15}]},"central-park-1b72":{"m":83,"r":"X1|Pink","x":1,"legs":[{"mode":"RAIL","line":"X1","from":"Ravinia","to":"Clinton (Green/Pink)","ride":45,"wait":7,"freq":30},{"mode":"SUBWAY","line":"Pink","from":"Clinton (Green/Pink)","to":"Central Park","ride":16,"wait":4}]},"central-st-1b64":{"m":32,"r":"X1","x":0,"legs":[{"mode":"RAIL","line":"X1","from":"Ravinia","to":"Central St.","ride":20,"wait":7,"freq":15}]},"cermak-chinatown-1aaa":{"m":73,"r":"X1|Red","x":1,"legs":[{"mode":"RAIL","line":"X1","from":"Ravinia","to":"Roosevelt","ride":51,"wait":7,"freq":30},{"mode":"SUBWAY","line":"Red","from":"Roosevelt","to":"Cermak-Chinatown","ride":3,"wait":4,"freq":3}]},"cermak-mccormick-place-1b20":{"m":74,"r":"X1|G","x":1,"legs":[{"mode":"RAIL","line":"X1","from":"Ravinia","to":"Roosevelt","ride":51,"wait":7,"freq":30},{"mode":"SUBWAY","line":"G","from":"Roosevelt","to":"Cermak-McCormick Place","ride":4,"wait":3,"freq":5}]},"cheltenham-79th-st-1b0e":{"m":94,"r":"X1","x":0,"legs":[{"mode":"RAIL","line":"X1","from":"Ravinia","to":"Cheltenham (79th St.)","ride":79,"wait":7,"freq":30}]},"chicago-blue-1b41":{"m":66,"r":"X1","x":0,"legs":[{"mode":"RAIL","line":"X1","from":"Ravinia","to":"Chicago/Halsted (Bally's)","ride":42,"wait":7,"freq":30}]},"chicago-brown-purple-1bc6":{"m":72,"r":"X1|Brn","x":1,"legs":[{"mode":"RAIL","line":"X1","from":"Ravinia","to":"Addison (Brown)","ride":34,"wait":7,"freq":30},{"mode":"SUBWAY","line":"Brn","from":"Addison (Brown)","to":"Chicago (Brown/Purple)","ride":20,"wait":6,"freq":4}]},"chicago-red-1b6e":{"m":76,"r":"X1|Brn|Red","x":2,"legs":[{"mode":"RAIL","line":"X1","from":"Ravinia","to":"Addison (Brown)","ride":34,"wait":7,"freq":30},{"mode":"SUBWAY","line":"Brn","from":"Addison (Brown)","to":"Belmont (Red/Brown/Purple)","ride":6,"wait":6,"freq":4},{"mode":"SUBWAY","line":"Red","from":"Belmont (Red/Brown/Purple)","to":"Chicago (Red)","ride":12,"wait":3,"freq":4}]},"chicago-otc-1b12":{"m":63,"r":"X1|UP-N","x":1,"legs":[{"mode":"RAIL","line":"X1","from":"Braeside","to":"Highland Park","ride":6,"wait":4,"freq":20},{"mode":"RAIL","line":"UP-N","from":"Highland Park","to":"Chicago OTC","ride":46,"wait":2,"freq":15}]},"chicago-ridge-1b08":{"m":123,"r":"X1|SWS","x":1,"legs":[{"mode":"RAIL","line":"X1","from":"Ravinia","to":"Chicago Union Station","ride":47,"wait":7,"freq":30},{"mode":"RAIL","line":"SWS","from":"Chicago Union Station","to":"Chicago Ridge","ride":35,"wait":33,"freq":60}]},"chicago-union-station-1bfc":{"m":62,"r":"X1","x":0,"legs":[{"mode":"RAIL","line":"X1","from":"Ravinia","to":"Chicago Union Station","ride":47,"wait":7,"freq":30}]},"chicago-halsted-bally-s-1b9c":{"m":57,"r":"X1","x":0,"legs":[{"mode":"RAIL","line":"X1","from":"Ravinia","to":"Chicago/Halsted (Bally's)","ride":42,"wait":7,"freq":30}]},"cicero-1b62":{"m":89,"r":"X1|X5","x":1,"legs":[{"mode":"RAIL","line":"X1","from":"Ravinia","to":"Chicago Union Station","ride":47,"wait":7,"freq":30},{"mode":"RAIL","line":"X5","from":"Chicago Union Station","to":"Cicero","ride":13,"wait":18,"freq":20}]},"cicero-blue-1b3b":{"m":90,"r":"X1|G|54","x":2,"legs":[{"mode":"RAIL","line":"X1","from":"Ravinia","to":"Clinton (Green/Pink)","ride":45,"wait":7,"freq":30},{"mode":"SUBWAY","line":"G","from":"Clinton (Green/Pink)","to":"Cicero (Green)","ride":16,"wait":2,"freq":9},{"mode":"BUS","line":"54","from":"Cicero (Green)","to":"Cicero (Blue)","ride":7,"wait":2,"freq":9}]},"cicero-green-1b98":{"m":80,"r":"X1|G","x":1,"legs":[{"mode":"RAIL","line":"X1","from":"Ravinia","to":"Clinton (Green/Pink)","ride":45,"wait":7,"freq":30},{"mode":"SUBWAY","line":"G","from":"Clinton (Green/Pink)","to":"Cicero (Green)","ride":16,"wait":2,"freq":9}]},"cicero-pink-1b4f":{"m":89,"r":"X1|Pink","x":1,"legs":[{"mode":"RAIL","line":"X1","from":"Ravinia","to":"Clinton (Green/Pink)","ride":45,"wait":7,"freq":30},{"mode":"SUBWAY","line":"Pink","from":"Clinton (Green/Pink)","to":"Cicero (Pink)","ride":22,"wait":4}]},"clarendon-hills-1bbe":{"m":120,"r":"X1|X5","x":1,"legs":[{"mode":"RAIL","line":"X1","from":"Ravinia","to":"Chicago Union Station","ride":47,"wait":7,"freq":30},{"mode":"RAIL","line":"X5","from":"Chicago Union Station","to":"Clarendon Hills","ride":44,"wait":18,"freq":20}]},"clark-division-1b06":{"m":73,"r":"X1|Brn|Red","x":2,"legs":[{"mode":"RAIL","line":"X1","from":"Ravinia","to":"Addison (Brown)","ride":34,"wait":7,"freq":30},{"mode":"SUBWAY","line":"Brn","from":"Addison (Brown)","to":"Belmont (Red/Brown/Purple)","ride":6,"wait":6,"freq":4},{"mode":"SUBWAY","line":"Red","from":"Belmont (Red/Brown/Purple)","to":"Clark/Division","ride":10,"wait":3,"freq":4}]},"clark-lake-1b69":{"m":71,"r":"X1|G","x":1,"legs":[{"mode":"RAIL","line":"X1","from":"Ravinia","to":"Clinton (Green/Pink)","ride":45,"wait":7,"freq":30},{"mode":"SUBWAY","line":"G","from":"Clinton (Green/Pink)","to":"Clark/Lake","ride":2,"wait":6,"freq":4}]},"clinton-blue-1ae3":{"m":68,"r":"X1","x":0,"legs":[{"mode":"RAIL","line":"X1","from":"Ravinia","to":"Chicago Union Station","ride":47,"wait":7,"freq":30}]},"clinton-green-pink-1b76":{"m":62,"r":"X1","x":0,"legs":[{"mode":"RAIL","line":"X1","from":"Ravinia","to":"Clinton (Green/Pink)","ride":45,"wait":7,"freq":30}]},"clybourn-1b80":{"m":51,"r":"X1","x":0,"legs":[{"mode":"RAIL","line":"X1","from":"Ravinia","to":"Clybourn","ride":37,"wait":7,"freq":15}]},"congress-park-1bc5":{"m":109,"r":"X1|X5","x":1,"legs":[{"mode":"RAIL","line":"X1","from":"Ravinia","to":"Chicago Union Station","ride":47,"wait":7,"freq":30},{"mode":"RAIL","line":"X5","from":"Chicago Union Station","to":"Congress Park","ride":29,"wait":18,"freq":30}]},"conservatory-central-park-drive-1b7c":{"m":74,"r":"X1|G","x":1,"legs":[{"mode":"RAIL","line":"X1","from":"Ravinia","to":"Clinton (Green/Pink)","ride":45,"wait":7,"freq":30},{"mode":"SUBWAY","line":"G","from":"Clinton (Green/Pink)","to":"Conservatory-Central Park Drive","ride":10,"wait":2,"freq":9}]},"cottage-grove-1b4c":{"m":94,"r":"X1|G","x":1,"legs":[{"mode":"RAIL","line":"X1","from":"Ravinia","to":"Roosevelt","ride":51,"wait":7,"freq":30},{"mode":"SUBWAY","line":"G","from":"Roosevelt","to":"Cottage Grove","ride":24,"wait":3,"freq":15}]},"crystal-lake-1ad7":{"m":165,"r":"X1|UP-NW","x":1,"legs":[{"mode":"RAIL","line":"X1","from":"Ravinia","to":"Clinton (Green/Pink)","ride":45,"wait":7,"freq":30},{"mode":"RAIL","line":"UP-NW","from":"Chicago OTC","to":"Crystal Lake","ride":85,"wait":24,"freq":60}]},"cumberland-1ad5":{"m":84,"r":"X1|X3","x":1,"legs":[{"mode":"RAIL","line":"X1","from":"Ravinia","to":"Clybourn","ride":37,"wait":7,"freq":15},{"mode":"RAIL","line":"X3","from":"Clybourn","to":"Cumberland","ride":26,"wait":6,"freq":12}]},"cumberland-1b46":{"m":89,"r":"X1|X3|Blue","x":2,"legs":[{"mode":"RAIL","line":"X1","from":"Ravinia","to":"Clybourn","ride":37,"wait":7,"freq":15},{"mode":"RAIL","line":"X3","from":"Clybourn","to":"Belmont/Kedzie","ride":4,"wait":6,"freq":15},{"mode":"SUBWAY","line":"Blue","from":"Belmont (Blue)","to":"Cumberland","ride":17,"wait":2,"freq":7}]},"damen-blue-1bc5":{"m":65,"r":"X1|X9|72","x":2,"legs":[{"mode":"RAIL","line":"X1","from":"Ravinia","to":"Clybourn","ride":37,"wait":7,"freq":15},{"mode":"BUS","line":"X9","from":"Clybourn","to":"Clybourn","ride":2,"wait":3},{"mode":"BUS","line":"72","from":"Clybourn","to":"Damen (Blue)","ride":3,"wait":3}]},"damen-brown-1bcd":{"m":52,"r":"X1|UP-N","x":1,"legs":[{"mode":"RAIL","line":"X1","from":"Braeside","to":"Highland Park","ride":6,"wait":4,"freq":20},{"mode":"RAIL","line":"UP-N","from":"Highland Park","to":"Ravenswood","ride":28,"wait":2,"freq":10}]},"damen-green-1bca":{"m":68,"r":"X1|G","x":1,"legs":[{"mode":"RAIL","line":"X1","from":"Ravinia","to":"Clinton (Green/Pink)","ride":45,"wait":7,"freq":30},{"mode":"SUBWAY","line":"G","from":"Clinton (Green/Pink)","to":"Damen (Green)","ride":4,"wait":2,"freq":9}]},"damen-pink-1b48":{"m":78,"r":"X1|Pink","x":1,"legs":[{"mode":"RAIL","line":"X1","from":"Ravinia","to":"Clinton (Green/Pink)","ride":45,"wait":7,"freq":30},{"mode":"SUBWAY","line":"Pink","from":"Clinton (Green/Pink)","to":"Damen (Pink)","ride":11,"wait":4}]},"dee-road-1b14":{"m":78,"r":"X1|X3","x":1,"legs":[{"mode":"RAIL","line":"X1","from":"Ravinia","to":"Clybourn","ride":37,"wait":7,"freq":15},{"mode":"RAIL","line":"X3","from":"Clybourn","to":"Dee Road","ride":20,"wait":6,"freq":12}]},"deerfield-1ad3":{"m":50,"r":"213|471","x":1,"legs":[{"mode":"BUS","line":"213","from":"Braeside","to":"Ravinia","ride":5,"wait":18,"freq":20},{"mode":"BUS","line":"471","from":"Ravinia","to":"Deerfield","ride":8,"wait":3}]},"dempster-1b44":{"m":44,"r":"X1|UP-N","x":1,"legs":[{"mode":"RAIL","line":"X1","from":"Braeside","to":"Highland Park","ride":6,"wait":4,"freq":20},{"mode":"RAIL","line":"UP-N","from":"Highland Park","to":"Evanston (Davis St.)","ride":17,"wait":2,"freq":9}]},"dempster-skokie-1b51":{"m":59,"r":"X1|Y","x":1,"legs":[{"mode":"RAIL","line":"X1","from":"Ravinia","to":"Howard/Clark","ride":26,"wait":7,"freq":30},{"mode":"SUBWAY","line":"Y","from":"Howard","to":"Dempster-Skokie","ride":8,"wait":9,"freq":7}]},"des-plaines-1bba":{"m":84,"r":"X1|X3","x":1,"legs":[{"mode":"RAIL","line":"X1","from":"Ravinia","to":"Clybourn","ride":37,"wait":7,"freq":15},{"mode":"RAIL","line":"X3","from":"Clybourn","to":"Des Plaines","ride":23,"wait":6,"freq":12}]},"des-plaines-river-rd-1bb2":{"m":96,"r":"X1|X5","x":1,"legs":[{"mode":"RAIL","line":"X1","from":"Ravinia","to":"Chicago Union Station","ride":47,"wait":7,"freq":30},{"mode":"RAIL","line":"X5","from":"Chicago Union Station","to":"Des Plaines River Rd","ride":28,"wait":6,"freq":30}]},"diversey-brown-purple-1b0b":{"m":61,"r":"X1|Brn","x":1,"legs":[{"mode":"RAIL","line":"X1","from":"Ravinia","to":"Addison (Brown)","ride":34,"wait":7,"freq":30},{"mode":"SUBWAY","line":"Brn","from":"Addison (Brown)","to":"Diversey (Brown/Purple)","ride":8,"wait":6,"freq":4}]},"division-1b68":{"m":61,"r":"X1","x":0,"legs":[{"mode":"RAIL","line":"X1","from":"Ravinia","to":"Division/Elston","ride":40,"wait":7,"freq":30}]},"division-elston-1aee":{"m":55,"r":"X1","x":0,"legs":[{"mode":"RAIL","line":"X1","from":"Ravinia","to":"Division/Elston","ride":40,"wait":7,"freq":30}]},"downers-grove-1b48":{"m":127,"r":"X1|X5","x":1,"legs":[{"mode":"RAIL","line":"X1","from":"Ravinia","to":"Chicago Union Station","ride":47,"wait":7,"freq":30},{"mode":"RAIL","line":"X5","from":"Chicago Union Station","to":"Downers Grove","ride":51,"wait":18,"freq":20}]},"edgebrook-1bd7":{"m":74,"r":"X1|UP-N|84","x":2,"legs":[{"mode":"RAIL","line":"X1","from":"Braeside","to":"Highland Park","ride":6,"wait":4,"freq":20},{"mode":"RAIL","line":"UP-N","from":"Highland Park","to":"Peterson/Ridge","ride":24,"wait":2,"freq":10},{"mode":"BUS","line":"84","from":"Peterson/Ridge","to":"Edgebrook","ride":24,"wait":4}]},"edison-park-1b15":{"m":74,"r":"X1|X3","x":1,"legs":[{"mode":"RAIL","line":"X1","from":"Ravinia","to":"Clybourn","ride":37,"wait":7,"freq":15},{"mode":"RAIL","line":"X3","from":"Clybourn","to":"Edison Park","ride":16,"wait":6,"freq":12}]},"elgin-1b05":{"m":154,"r":"X1|MD-W","x":1,"legs":[{"mode":"RAIL","line":"X1","from":"Ravinia","to":"Chicago Union Station","ride":47,"wait":7,"freq":30},{"mode":"RAIL","line":"MD-W","from":"Chicago Union Station","to":"Elgin","ride":70,"wait":21,"freq":60}]},"elmhurst-1bab":{"m":121,"r":"X1|X6","x":1,"legs":[{"mode":"RAIL","line":"X1","from":"Ravinia","to":"Chicago Union Station","ride":47,"wait":7,"freq":30},{"mode":"RAIL","line":"X6","from":"Chicago Union Station","to":"Elmhurst","ride":30,"wait":31,"freq":30}]},"elmwood-park-1b63":{"m":99,"r":"X1|X5","x":1,"legs":[{"mode":"RAIL","line":"X1","from":"Ravinia","to":"Chicago Union Station","ride":47,"wait":7,"freq":30},{"mode":"RAIL","line":"X5","from":"Chicago Union Station","to":"Grand/Harlem","ride":22,"wait":6,"freq":30}]},"elmwood-park-conti-cir-1ad3":{"m":92,"r":"X1|X5","x":1,"legs":[{"mode":"RAIL","line":"X1","from":"Ravinia","to":"Chicago Union Station","ride":47,"wait":7,"freq":30},{"mode":"RAIL","line":"X5","from":"Chicago Union Station","to":"Elmwood Park - Conti Cir","ride":24,"wait":6,"freq":30}]},"evanston-davis-st-1b81":{"m":33,"r":"X1|UP-N","x":1,"legs":[{"mode":"RAIL","line":"X1","from":"Braeside","to":"Highland Park","ride":6,"wait":4,"freq":20},{"mode":"RAIL","line":"UP-N","from":"Highland Park","to":"Evanston (Davis St.)","ride":17,"wait":2,"freq":9}]},"fairview-ave-1bc6":{"m":124,"r":"X1|X5","x":1,"legs":[{"mode":"RAIL","line":"X1","from":"Ravinia","to":"Chicago Union Station","ride":47,"wait":7,"freq":30},{"mode":"RAIL","line":"X5","from":"Chicago Union Station","to":"Fairview Ave.","ride":49,"wait":18,"freq":20}]},"flossmoor-1b93":{"m":129,"r":"X1|ME","x":1,"legs":[{"mode":"RAIL","line":"X1","from":"Ravinia","to":"Roosevelt","ride":51,"wait":7,"freq":30},{"mode":"RAIL","line":"ME","from":"Museum Campus/11th St.","to":"Flossmoor","ride":45,"wait":8,"freq":30}]},"forest-glen-1b94":{"m":85,"r":"X1|X3","x":1,"legs":[{"mode":"RAIL","line":"X1","from":"Ravinia","to":"Clybourn","ride":37,"wait":7,"freq":15},{"mode":"RAIL","line":"X3","from":"Clybourn","to":"Jefferson Park","ride":10,"wait":6,"freq":12}]},"forest-park-1b49":{"m":111,"r":"X1|G|318","x":2,"legs":[{"mode":"RAIL","line":"X1","from":"Ravinia","to":"Clinton (Green/Pink)","ride":45,"wait":7,"freq":30},{"mode":"SUBWAY","line":"G","from":"Clinton (Green/Pink)","to":"Harlem/Lake","ride":24,"wait":2,"freq":9},{"mode":"BUS","line":"318","from":"Harlem/Lake","to":"Forest Park","ride":7,"wait":14,"freq":15}]},"fort-sheridan-1b2a":{"m":47,"r":"UP-N","x":0,"legs":[{"mode":"RAIL","line":"UP-N","from":"Braeside","to":"Fort Sheridan","ride":11,"wait":9,"freq":60}]},"foster-1b56":{"m":41,"r":"X1|UP-N|93","x":2,"legs":[{"mode":"RAIL","line":"X1","from":"Braeside","to":"Highland Park","ride":6,"wait":4,"freq":20},{"mode":"RAIL","line":"UP-N","from":"Highland Park","to":"Evanston (Davis St.)","ride":17,"wait":2,"freq":9},{"mode":"BUS","line":"93","from":"Evanston (Davis St.)","to":"Foster","ride":2,"wait":1}]},"fox-lake-1b10":{"m":121,"r":"UP-N|572|570","x":2,"legs":[{"mode":"RAIL","line":"UP-N","from":"Braeside","to":"Waukegan","ride":34,"wait":9,"freq":60},{"mode":"BUS","line":"572","from":"Waukegan","to":"Washington St (Grayslake)","ride":31,"wait":7},{"mode":"BUS","line":"570","from":"Washington St (Grayslake)","to":"Fox Lake","ride":34,"wait":3}]},"fox-river-grove-1b59":{"m":151,"r":"X1|UP-NW","x":1,"legs":[{"mode":"RAIL","line":"X1","from":"Ravinia","to":"Clinton (Green/Pink)","ride":45,"wait":7,"freq":30},{"mode":"RAIL","line":"UP-NW","from":"Chicago OTC","to":"Fox River Grove","ride":70,"wait":24,"freq":60}]},"francisco-1afa":{"m":59,"r":"X1|Brn","x":1,"legs":[{"mode":"RAIL","line":"X1","from":"Ravinia","to":"Addison (Brown)","ride":34,"wait":7,"freq":30},{"mode":"SUBWAY","line":"Brn","from":"Addison (Brown)","to":"Francisco","ride":8,"wait":2,"freq":30}]},"franklin-park-1ba8":{"m":107,"r":"X1|X5","x":1,"legs":[{"mode":"RAIL","line":"X1","from":"Ravinia","to":"Chicago Union Station","ride":47,"wait":7,"freq":30},{"mode":"RAIL","line":"X5","from":"Chicago Union Station","to":"Franklin Pk","ride":30,"wait":6,"freq":30}]},"franklin-pk-1b1b":{"m":98,"r":"X1|X5","x":1,"legs":[{"mode":"RAIL","line":"X1","from":"Ravinia","to":"Chicago Union Station","ride":47,"wait":7,"freq":30},{"mode":"RAIL","line":"X5","from":"Chicago Union Station","to":"Franklin Pk","ride":30,"wait":6,"freq":30}]},"fullerton-1b6d":{"m":64,"r":"X1|Brn","x":1,"legs":[{"mode":"RAIL","line":"X1","from":"Ravinia","to":"Addison (Brown)","ride":34,"wait":7,"freq":30},{"mode":"SUBWAY","line":"Brn","from":"Addison (Brown)","to":"Fullerton","ride":10,"wait":6,"freq":4}]},"galewood-1bc9":{"m":87,"r":"X1|X5","x":1,"legs":[{"mode":"RAIL","line":"X1","from":"Ravinia","to":"Chicago Union Station","ride":47,"wait":7,"freq":30},{"mode":"RAIL","line":"X5","from":"Chicago Union Station","to":"Galewood","ride":19,"wait":6,"freq":20}]},"garfield-green-1b43":{"m":88,"r":"X1|G","x":1,"legs":[{"mode":"RAIL","line":"X1","from":"Ravinia","to":"Roosevelt","ride":51,"wait":7,"freq":30},{"mode":"SUBWAY","line":"G","from":"Roosevelt","to":"Garfield (Green)","ride":18,"wait":3,"freq":9}]},"garfield-red-1af4":{"m":82,"r":"X1|Red","x":1,"legs":[{"mode":"RAIL","line":"X1","from":"Ravinia","to":"Roosevelt","ride":51,"wait":7,"freq":30},{"mode":"SUBWAY","line":"Red","from":"Roosevelt","to":"Garfield (Red)","ride":12,"wait":4,"freq":4}]},"gladstone-park-1bbd":{"m":70,"r":"X1|X3","x":1,"legs":[{"mode":"RAIL","line":"X1","from":"Ravinia","to":"Clybourn","ride":37,"wait":7,"freq":15},{"mode":"RAIL","line":"X3","from":"Clybourn","to":"Gladstone Park","ride":12,"wait":6,"freq":15}]},"glen-n-glenview-1b87":{"m":66,"r":"X1|423","x":1,"legs":[{"mode":"RAIL","line":"X1","from":"Ravinia","to":"Winnetka","ride":12,"wait":7,"freq":15},{"mode":"BUS","line":"423","from":"Winnetka","to":"Glen/N. Glenview","ride":15,"wait":8}]},"glencoe-1b50":{"m":17,"r":"X1","x":0,"legs":[{"mode":"RAIL","line":"X1","from":"Ravinia","to":"Glencoe","ride":6,"wait":7,"freq":15}]},"glenview-1b20":{"m":68,"r":"X1|423","x":1,"legs":[{"mode":"RAIL","line":"X1","from":"Ravinia","to":"Winnetka","ride":12,"wait":7,"freq":15},{"mode":"BUS","line":"423","from":"Winnetka","to":"Glenview","ride":30,"wait":8,"freq":30}]},"golf-1bed":{"m":80,"r":"X1|423","x":1,"legs":[{"mode":"RAIL","line":"X1","from":"Ravinia","to":"Winnetka","ride":12,"wait":7,"freq":15},{"mode":"BUS","line":"423","from":"Winnetka","to":"Golf","ride":33,"wait":8}]},"grand-blue-1b7a":{"m":66,"r":"X1","x":0,"legs":[{"mode":"RAIL","line":"X1","from":"Ravinia","to":"Chicago/Halsted (Bally's)","ride":42,"wait":7,"freq":30}]},"grand-red-1b30":{"m":76,"r":"X1|Red","x":1,"legs":[{"mode":"RAIL","line":"X1","from":"Ravinia","to":"Roosevelt","ride":51,"wait":7,"freq":30},{"mode":"SUBWAY","line":"Red","from":"Roosevelt","to":"Grand (Red)","ride":6,"wait":5,"freq":4}]},"grand-cicero-1b24":{"m":83,"r":"X1|X5","x":1,"legs":[{"mode":"RAIL","line":"X1","from":"Ravinia","to":"Chicago Union Station","ride":47,"wait":7,"freq":30},{"mode":"RAIL","line":"X5","from":"Chicago Union Station","to":"Grand/Cicero","ride":15,"wait":6,"freq":30}]},"grand-harlem-1b75":{"m":90,"r":"X1|X5","x":1,"legs":[{"mode":"RAIL","line":"X1","from":"Ravinia","to":"Chicago Union Station","ride":47,"wait":7,"freq":30},{"mode":"RAIL","line":"X5","from":"Chicago Union Station","to":"Grand/Harlem","ride":22,"wait":6,"freq":30}]},"granville-1b91":{"m":58,"r":"X1|Red","x":1,"legs":[{"mode":"RAIL","line":"X1","from":"Ravinia","to":"Howard/Clark","ride":26,"wait":7,"freq":30},{"mode":"SUBWAY","line":"Red","from":"Howard","to":"Granville","ride":7,"wait":3,"freq":4}]},"grayland-1b34":{"m":80,"r":"X1|152","x":1,"legs":[{"mode":"RAIL","line":"X1","from":"Ravinia","to":"Addison (Brown)","ride":34,"wait":7,"freq":30},{"mode":"BUS","line":"152","from":"Addison (Brown)","to":"Grayland","ride":19,"wait":4}]},"grayslake-1ac3":{"m":101,"r":"UP-N|572|570","x":2,"legs":[{"mode":"RAIL","line":"UP-N","from":"Braeside","to":"Waukegan","ride":34,"wait":9,"freq":60},{"mode":"BUS","line":"572","from":"Waukegan","to":"Washington St (Grayslake)","ride":31,"wait":7},{"mode":"BUS","line":"570","from":"Washington St (Grayslake)","to":"Grayslake","ride":10,"wait":3}]},"great-lakes-1b75":{"m":59,"r":"UP-N","x":0,"legs":[{"mode":"RAIL","line":"UP-N","from":"Braeside","to":"Great Lakes","ride":23,"wait":9,"freq":60}]},"gresham-1b67":{"m":94,"r":"X1|RI","x":1,"legs":[{"mode":"RAIL","line":"X1","from":"Ravinia","to":"Chicago Union Station","ride":47,"wait":7,"freq":30},{"mode":"RAIL","line":"RI","from":"LaSalle Street","to":"Gresham","ride":15,"wait":6,"freq":12}]},"halsted-green-1b5a":{"m":98,"r":"X1|Red|63","x":2,"legs":[{"mode":"RAIL","line":"X1","from":"Ravinia","to":"Roosevelt","ride":51,"wait":7,"freq":30},{"mode":"SUBWAY","line":"Red","from":"Roosevelt","to":"63rd","ride":14,"wait":4,"freq":4},{"mode":"BUS","line":"63","from":"63rd","to":"Halsted (Green)","ride":5,"wait":4,"freq":9}]},"halsted-orange-1b68":{"m":78,"r":"X1|Org","x":1,"legs":[{"mode":"RAIL","line":"X1","from":"Ravinia","to":"Roosevelt","ride":51,"wait":7,"freq":30},{"mode":"SUBWAY","line":"Org","from":"Roosevelt","to":"Halsted (Orange)","ride":4,"wait":7,"freq":9}]},"halsted-street-1b2c":{"m":77,"r":"X1|8","x":1,"legs":[{"mode":"RAIL","line":"X1","from":"Ravinia","to":"Taylor/Clinton","ride":49,"wait":7,"freq":30},{"mode":"BUS","line":"8","from":"Taylor/Clinton","to":"Halsted Street","ride":4,"wait":4}]},"hanover-park-1b44":{"m":137,"r":"X1|MD-W","x":1,"legs":[{"mode":"RAIL","line":"X1","from":"Ravinia","to":"Chicago Union Station","ride":47,"wait":7,"freq":30},{"mode":"RAIL","line":"MD-W","from":"Chicago Union Station","to":"Hanover Park","ride":56,"wait":21,"freq":60}]},"hanson-park-1be1":{"m":85,"r":"X1|X5","x":1,"legs":[{"mode":"RAIL","line":"X1","from":"Ravinia","to":"Chicago Union Station","ride":47,"wait":7,"freq":30},{"mode":"RAIL","line":"X5","from":"Chicago Union Station","to":"Hanson Park","ride":17,"wait":6,"freq":30}]},"harlem-blue-forest-park-branch-1b13":{"m":108,"r":"X1|G|307","x":2,"legs":[{"mode":"RAIL","line":"X1","from":"Ravinia","to":"Clinton (Green/Pink)","ride":45,"wait":7,"freq":30},{"mode":"SUBWAY","line":"G","from":"Clinton (Green/Pink)","to":"Harlem/Lake","ride":24,"wait":2,"freq":9},{"mode":"BUS","line":"307","from":"Harlem/Lake","to":"Harlem (Blue - Forest Park Branch)","ride":5,"wait":10}]},"harlem-blue-o-hare-branch-1ba7":{"m":86,"r":"X1|X3|Blue","x":2,"legs":[{"mode":"RAIL","line":"X1","from":"Ravinia","to":"Clybourn","ride":37,"wait":7,"freq":15},{"mode":"RAIL","line":"X3","from":"Clybourn","to":"Belmont/Kedzie","ride":4,"wait":6,"freq":15},{"mode":"SUBWAY","line":"Blue","from":"Belmont (Blue)","to":"Harlem (Blue - O'Hare Branch)","ride":14,"wait":2,"freq":7}]},"harlem-ave-1b22":{"m":98,"r":"X1|X5","x":1,"legs":[{"mode":"RAIL","line":"X1","from":"Ravinia","to":"Chicago Union Station","ride":47,"wait":7,"freq":30},{"mode":"RAIL","line":"X5","from":"Chicago Union Station","to":"Harlem Ave.","ride":22,"wait":18,"freq":20}]},"harlem-lake-1b23":{"m":88,"r":"X1|G","x":1,"legs":[{"mode":"RAIL","line":"X1","from":"Ravinia","to":"Clinton (Green/Pink)","ride":45,"wait":7,"freq":30},{"mode":"SUBWAY","line":"G","from":"Clinton (Green/Pink)","to":"Harlem/Lake","ride":24,"wait":2,"freq":9}]},"harold-washington-library-state-van-buren-1b72":{"m":75,"r":"X1|Brn","x":1,"legs":[{"mode":"RAIL","line":"X1","from":"Ravinia","to":"Chicago Union Station","ride":47,"wait":7,"freq":30},{"mode":"SUBWAY","line":"Brn","from":"Quincy","to":"Harold Washington Library-State/Van Buren","ride":2,"wait":3,"freq":2}]},"harrison-1b48":{"m":72,"r":"X1|Red","x":1,"legs":[{"mode":"RAIL","line":"X1","from":"Ravinia","to":"Roosevelt","ride":51,"wait":7,"freq":30},{"mode":"SUBWAY","line":"Red","from":"Roosevelt","to":"Harrison","ride":0,"wait":5,"freq":2}]},"harvey-1b6a":{"m":119,"r":"X1|ME","x":1,"legs":[{"mode":"RAIL","line":"X1","from":"Ravinia","to":"Roosevelt","ride":51,"wait":7,"freq":30},{"mode":"RAIL","line":"ME","from":"Museum Campus/11th St.","to":"Harvey","ride":35,"wait":8,"freq":30}]},"harvey-1b23":{"m":122,"r":"X1|ME","x":1,"legs":[{"mode":"RAIL","line":"X1","from":"Ravinia","to":"Roosevelt","ride":51,"wait":7,"freq":30},{"mode":"RAIL","line":"ME","from":"Museum Campus/11th St.","to":"Harvey","ride":35,"wait":8,"freq":30}]},"hazel-crest-1baa":{"m":122,"r":"X1|ME","x":1,"legs":[{"mode":"RAIL","line":"X1","from":"Ravinia","to":"Roosevelt","ride":51,"wait":7,"freq":30},{"mode":"RAIL","line":"ME","from":"Museum Campus/11th St.","to":"Hazel Crest","ride":38,"wait":8,"freq":30}]},"healy-1ba1":{"m":81,"r":"X1|X3|74","x":2,"legs":[{"mode":"RAIL","line":"X1","from":"Ravinia","to":"Clybourn","ride":37,"wait":7,"freq":15},{"mode":"RAIL","line":"X3","from":"Clybourn","to":"Western/Logan","ride":2,"wait":6,"freq":15},{"mode":"BUS","line":"74","from":"Western/Logan","to":"Healy","ride":12,"wait":2}]},"hickory-creek-1b97":{"m":148,"r":"X1|RI","x":1,"legs":[{"mode":"RAIL","line":"X1","from":"Ravinia","to":"Chicago Union Station","ride":47,"wait":7,"freq":30},{"mode":"RAIL","line":"RI","from":"LaSalle Street","to":"Hickory Creek","ride":48,"wait":36,"freq":60}]},"highland-park-1bb1":{"m":22,"r":"X1","x":0,"legs":[{"mode":"RAIL","line":"X1","from":"Braeside","to":"Highland Park","ride":6,"wait":4,"freq":20}]},"highlands-1b33":{"m":118,"r":"X1|X5","x":1,"legs":[{"mode":"RAIL","line":"X1","from":"Ravinia","to":"Chicago Union Station","ride":47,"wait":7,"freq":30},{"mode":"RAIL","line":"X5","from":"Chicago Union Station","to":"Highlands","ride":38,"wait":18,"freq":30}]},"highwood-1ad1":{"m":43,"r":"UP-N","x":0,"legs":[{"mode":"RAIL","line":"UP-N","from":"Braeside","to":"Highwood","ride":9,"wait":9,"freq":60}]},"hinsdale-1b67":{"m":116,"r":"X1|X5","x":1,"legs":[{"mode":"RAIL","line":"X1","from":"Ravinia","to":"Chicago Union Station","ride":47,"wait":7,"freq":30},{"mode":"RAIL","line":"X5","from":"Chicago Union Station","to":"Hinsdale","ride":40,"wait":18,"freq":20}]},"hollywood-1b77":{"m":103,"r":"X1|X5","x":1,"legs":[{"mode":"RAIL","line":"X1","from":"Ravinia","to":"Chicago Union Station","ride":47,"wait":7,"freq":30},{"mode":"RAIL","line":"X5","from":"Chicago Union Station","to":"Hollywood","ride":27,"wait":18,"freq":20}]},"homewood-1b90":{"m":129,"r":"X1|ME","x":1,"legs":[{"mode":"RAIL","line":"X1","from":"Ravinia","to":"Roosevelt","ride":51,"wait":7,"freq":30},{"mode":"RAIL","line":"ME","from":"Museum Campus/11th St.","to":"Homewood","ride":42,"wait":8,"freq":30}]},"howard-1b6c":{"m":45,"r":"X1","x":0,"legs":[{"mode":"RAIL","line":"X1","from":"Ravinia","to":"Howard/Clark","ride":26,"wait":7,"freq":30}]},"howard-clark-1b2e":{"m":41,"r":"X1","x":0,"legs":[{"mode":"RAIL","line":"X1","from":"Ravinia","to":"Howard/Clark","ride":26,"wait":7,"freq":30}]},"hubbard-woods-1b2c":{"m":20,"r":"X1","x":0,"legs":[{"mode":"RAIL","line":"X1","from":"Ravinia","to":"Hubbard Woods","ride":9,"wait":7,"freq":15}]},"humboldt-park-1b5a":{"m":78,"r":"X1|X5","x":1,"legs":[{"mode":"RAIL","line":"X1","from":"Ravinia","to":"Chicago Union Station","ride":47,"wait":7,"freq":30},{"mode":"RAIL","line":"X5","from":"Chicago Union Station","to":"Humboldt Park","ride":10,"wait":6,"freq":30}]},"illinois-medical-district-1bc9":{"m":79,"r":"X1|X9","x":1,"legs":[{"mode":"RAIL","line":"X1","from":"Ravinia","to":"Clybourn","ride":37,"wait":7,"freq":15},{"mode":"BUS","line":"X9","from":"Clybourn","to":"Illinois Medical District","ride":15,"wait":3}]},"indian-hill-1b61":{"m":25,"r":"X1","x":0,"legs":[{"mode":"RAIL","line":"X1","from":"Ravinia","to":"Indian Hill","ride":14,"wait":7,"freq":15}]},"indiana-1ae4":{"m":81,"r":"X1|G","x":1,"legs":[{"mode":"RAIL","line":"X1","from":"Ravinia","to":"Roosevelt","ride":51,"wait":7,"freq":30},{"mode":"SUBWAY","line":"G","from":"Roosevelt","to":"Indiana","ride":11,"wait":3,"freq":9}]},"ingleside-1b3c":{"m":114,"r":"X1|423|MD-N","x":2,"legs":[{"mode":"RAIL","line":"X1","from":"Ravinia","to":"Winnetka","ride":12,"wait":7,"freq":15},{"mode":"BUS","line":"423","from":"Winnetka","to":"Glen/N. Glenview","ride":20,"wait":8},{"mode":"RAIL","line":"MD-N","from":"Glen/N. Glenview","to":"Ingleside","ride":51,"wait":1}]},"irving-park-1ba4":{"m":65,"r":"X1|X3","x":1,"legs":[{"mode":"RAIL","line":"X1","from":"Ravinia","to":"Clybourn","ride":37,"wait":7,"freq":15},{"mode":"RAIL","line":"X3","from":"Clybourn","to":"Irving Park","ride":6,"wait":6,"freq":12}]},"irving-park-brown-1bbe":{"m":52,"r":"X1|Brn","x":1,"legs":[{"mode":"RAIL","line":"X1","from":"Ravinia","to":"Addison (Brown)","ride":34,"wait":7,"freq":30},{"mode":"SUBWAY","line":"Brn","from":"Addison (Brown)","to":"Irving Park (Brown)","ride":1,"wait":2,"freq":30}]},"itasca-1aa8":{"m":125,"r":"X1|MD-W","x":1,"legs":[{"mode":"RAIL","line":"X1","from":"Ravinia","to":"Chicago Union Station","ride":47,"wait":7,"freq":30},{"mode":"RAIL","line":"MD-W","from":"Chicago Union Station","to":"Itasca","ride":41,"wait":21,"freq":60}]},"ivanhoe-1ac0":{"m":115,"r":"X1|ME","x":1,"legs":[{"mode":"RAIL","line":"X1","from":"Ravinia","to":"Roosevelt","ride":51,"wait":7,"freq":30},{"mode":"RAIL","line":"ME","from":"Museum Campus/11th St.","to":"Ivanhoe","ride":31,"wait":8,"freq":30}]},"jackson-blue-1b6c":{"m":73,"r":"X1|28","x":1,"legs":[{"mode":"RAIL","line":"X1","from":"Ravinia","to":"Chicago Union Station","ride":47,"wait":7,"freq":30},{"mode":"BUS","line":"28","from":"Chicago Union Station","to":"Jackson (Blue)","ride":6,"wait":3,"freq":2}]},"jarvis-1b4e":{"m":50,"r":"X1|Red","x":1,"legs":[{"mode":"RAIL","line":"X1","from":"Ravinia","to":"Howard/Clark","ride":26,"wait":7,"freq":30},{"mode":"SUBWAY","line":"Red","from":"Howard","to":"Jarvis","ride":2,"wait":3,"freq":4}]},"jefferson-park-1b3f":{"m":69,"r":"X1|X3","x":1,"legs":[{"mode":"RAIL","line":"X1","from":"Ravinia","to":"Clybourn","ride":37,"wait":7,"freq":15},{"mode":"RAIL","line":"X3","from":"Clybourn","to":"Jefferson Park","ride":10,"wait":6,"freq":12}]},"jefferson-park-transit-center-1b3d":{"m":72,"r":"X1|X3","x":1,"legs":[{"mode":"RAIL","line":"X1","from":"Ravinia","to":"Clybourn","ride":37,"wait":7,"freq":15},{"mode":"RAIL","line":"X3","from":"Clybourn","to":"Jefferson Park","ride":10,"wait":6,"freq":12}]},"kedzie-1b9c":{"m":80,"r":"X1|G","x":1,"legs":[{"mode":"RAIL","line":"X1","from":"Ravinia","to":"Clinton (Green/Pink)","ride":45,"wait":7,"freq":30},{"mode":"SUBWAY","line":"G","from":"Clinton (Green/Pink)","to":"Kedzie (Green)","ride":9,"wait":2,"freq":9}]},"kedzie-brown-1b83":{"m":61,"r":"X1|Brn","x":1,"legs":[{"mode":"RAIL","line":"X1","from":"Ravinia","to":"Addison (Brown)","ride":34,"wait":7,"freq":30},{"mode":"SUBWAY","line":"Brn","from":"Addison (Brown)","to":"Kedzie (Brown)","ride":10,"wait":2,"freq":30}]},"kedzie-green-1b14":{"m":73,"r":"X1|G","x":1,"legs":[{"mode":"RAIL","line":"X1","from":"Ravinia","to":"Clinton (Green/Pink)","ride":45,"wait":7,"freq":30},{"mode":"SUBWAY","line":"G","from":"Clinton (Green/Pink)","to":"Kedzie (Green)","ride":9,"wait":2,"freq":9}]},"kedzie-orange-1ae7":{"m":89,"r":"X1|Org","x":1,"legs":[{"mode":"RAIL","line":"X1","from":"Ravinia","to":"Roosevelt","ride":51,"wait":7,"freq":30},{"mode":"SUBWAY","line":"Org","from":"Roosevelt","to":"Kedzie (Orange)","ride":15,"wait":7,"freq":30}]},"kedzie-pink-1b01":{"m":82,"r":"X1|Pink","x":1,"legs":[{"mode":"RAIL","line":"X1","from":"Ravinia","to":"Clinton (Green/Pink)","ride":45,"wait":7,"freq":30},{"mode":"SUBWAY","line":"Pink","from":"Clinton (Green/Pink)","to":"Kedzie (Pink)","ride":15,"wait":4}]},"kedzie-homan-1aef":{"m":88,"r":"X1|G","x":1,"legs":[{"mode":"RAIL","line":"X1","from":"Ravinia","to":"Clinton (Green/Pink)","ride":45,"wait":7,"freq":30},{"mode":"SUBWAY","line":"G","from":"Clinton (Green/Pink)","to":"Kedzie (Green)","ride":9,"wait":2,"freq":9}]},"kenilworth-1b67":{"m":27,"r":"X1","x":0,"legs":[{"mode":"RAIL","line":"X1","from":"Ravinia","to":"Kenilworth","ride":16,"wait":7,"freq":15}]},"kensington-1afa":{"m":108,"r":"X1|ME","x":1,"legs":[{"mode":"RAIL","line":"X1","from":"Ravinia","to":"Roosevelt","ride":51,"wait":7,"freq":30},{"mode":"RAIL","line":"ME","from":"Museum Campus/11th St.","to":"Kensington","ride":24,"wait":8,"freq":20}]},"kimball-1b1b":{"m":62,"r":"X1|Brn","x":1,"legs":[{"mode":"RAIL","line":"X1","from":"Ravinia","to":"Addison (Brown)","ride":34,"wait":7,"freq":30},{"mode":"SUBWAY","line":"Brn","from":"Addison (Brown)","to":"Kimball","ride":12,"wait":2,"freq":30}]},"king-drive-1b0c":{"m":92,"r":"X1|G","x":1,"legs":[{"mode":"RAIL","line":"X1","from":"Ravinia","to":"Roosevelt","ride":51,"wait":7,"freq":30},{"mode":"SUBWAY","line":"G","from":"Roosevelt","to":"King Drive","ride":22,"wait":3,"freq":15}]},"kostner-1b2f":{"m":88,"r":"X1|Pink","x":1,"legs":[{"mode":"RAIL","line":"X1","from":"Ravinia","to":"Clinton (Green/Pink)","ride":45,"wait":7,"freq":30},{"mode":"SUBWAY","line":"Pink","from":"Clinton (Green/Pink)","to":"Kostner","ride":20,"wait":4}]},"lagrange-road-1b2e":{"m":107,"r":"X1|X5","x":1,"legs":[{"mode":"RAIL","line":"X1","from":"Ravinia","to":"Chicago Union Station","ride":47,"wait":7,"freq":30},{"mode":"RAIL","line":"X5","from":"Chicago Union Station","to":"LaGrange Road","ride":31,"wait":18,"freq":20}]},"lasalle-street-1b03":{"m":72,"r":"X1","x":0,"legs":[{"mode":"RAIL","line":"X1","from":"Ravinia","to":"Chicago Union Station","ride":47,"wait":7,"freq":30}]},"lake-subway-1bb5":{"m":75,"r":"X1|56","x":1,"legs":[{"mode":"RAIL","line":"X1","from":"Ravinia","to":"Clinton (Green/Pink)","ride":45,"wait":7,"freq":30},{"mode":"BUS","line":"56","from":"Chicago OTC","to":"Washington/Wabash","ride":7,"wait":2,"freq":2}]},"lake-bluff-1bc8":{"m":55,"r":"UP-N","x":0,"legs":[{"mode":"RAIL","line":"UP-N","from":"Braeside","to":"Lake Bluff","ride":19,"wait":9,"freq":60}]},"lake-forest-1b90":{"m":80,"r":"X1|423|MD-N","x":2,"legs":[{"mode":"RAIL","line":"X1","from":"Ravinia","to":"Winnetka","ride":12,"wait":7,"freq":15},{"mode":"BUS","line":"423","from":"Winnetka","to":"Glen/N. Glenview","ride":20,"wait":8},{"mode":"RAIL","line":"MD-N","from":"Glen/N. Glenview","to":"Lake Forest","ride":17,"wait":1,"freq":30}]},"lake-forest-1ba5":{"m":51,"r":"UP-N","x":0,"legs":[{"mode":"RAIL","line":"UP-N","from":"Braeside","to":"Lake Forest.","ride":15,"wait":9,"freq":60}]},"lake-cook-1b0f":{"m":59,"r":"213|471","x":1,"legs":[{"mode":"BUS","line":"213","from":"Braeside","to":"Ravinia","ride":5,"wait":18,"freq":20},{"mode":"BUS","line":"471","from":"Ravinia","to":"Lake-Cook","ride":4,"wait":3}]},"laramie-1b36":{"m":81,"r":"X1|G","x":1,"legs":[{"mode":"RAIL","line":"X1","from":"Ravinia","to":"Clinton (Green/Pink)","ride":45,"wait":7,"freq":30},{"mode":"SUBWAY","line":"G","from":"Clinton (Green/Pink)","to":"Laramie","ride":18,"wait":2,"freq":9}]},"lavergne-1b69":{"m":98,"r":"X1|X5","x":1,"legs":[{"mode":"RAIL","line":"X1","from":"Ravinia","to":"Chicago Union Station","ride":47,"wait":7,"freq":30},{"mode":"RAIL","line":"X5","from":"Chicago Union Station","to":"Lavergne","ride":18,"wait":18,"freq":30}]},"lawrence-1b9e":{"m":55,"r":"X1|81","x":1,"legs":[{"mode":"RAIL","line":"X1","from":"Ravinia","to":"Ravenswood","ride":32,"wait":7,"freq":15},{"mode":"BUS","line":"81","from":"Ravenswood","to":"Lawrence","ride":6,"wait":2,"freq":8}]},"lawrence-ruby-1bac":{"m":102,"r":"X1|X5","x":1,"legs":[{"mode":"RAIL","line":"X1","from":"Ravinia","to":"Chicago Union Station","ride":47,"wait":7,"freq":30},{"mode":"RAIL","line":"X5","from":"Chicago Union Station","to":"Lawrence/Ruby","ride":34,"wait":6,"freq":30}]},"libertyville-1b63":{"m":91,"r":"X1|423|MD-N","x":2,"legs":[{"mode":"RAIL","line":"X1","from":"Ravinia","to":"Winnetka","ride":12,"wait":7,"freq":15},{"mode":"BUS","line":"423","from":"Winnetka","to":"Glen/N. Glenview","ride":20,"wait":8},{"mode":"RAIL","line":"MD-N","from":"Glen/N. Glenview","to":"Libertyville","ride":28,"wait":1,"freq":60}]},"linden-1b4b":{"m":43,"r":"X1|422","x":1,"legs":[{"mode":"RAIL","line":"X1","from":"Ravinia","to":"Wilmette","ride":18,"wait":7,"freq":15},{"mode":"BUS","line":"422","from":"Wilmette","to":"Linden","ride":4,"wait":1,"freq":20}]},"lisle-1b81":{"m":137,"r":"X1|BNSF","x":1,"legs":[{"mode":"RAIL","line":"X1","from":"Ravinia","to":"Chicago Union Station","ride":47,"wait":7,"freq":30},{"mode":"RAIL","line":"BNSF","from":"Chicago Union Station","to":"Lisle","ride":56,"wait":24,"freq":60}]},"logan-square-1b85":{"m":75,"r":"X1|X3|76","x":2,"legs":[{"mode":"RAIL","line":"X1","from":"Ravinia","to":"Clybourn","ride":37,"wait":7,"freq":15},{"mode":"RAIL","line":"X3","from":"Clybourn","to":"Western/Logan","ride":2,"wait":6,"freq":15},{"mode":"BUS","line":"76","from":"Western/Logan","to":"Logan Square","ride":7,"wait":3}]},"long-lake-1ae9":{"m":111,"r":"X1|423|MD-N","x":2,"legs":[{"mode":"RAIL","line":"X1","from":"Ravinia","to":"Winnetka","ride":12,"wait":7,"freq":15},{"mode":"BUS","line":"423","from":"Winnetka","to":"Glen/N. Glenview","ride":20,"wait":8},{"mode":"RAIL","line":"MD-N","from":"Glen/N. Glenview","to":"Long Lake","ride":48,"wait":1}]},"loyola-1a9a":{"m":53,"r":"X1|Red","x":1,"legs":[{"mode":"RAIL","line":"X1","from":"Ravinia","to":"Howard/Clark","ride":26,"wait":7,"freq":30},{"mode":"SUBWAY","line":"Red","from":"Howard","to":"Loyola","ride":5,"wait":3,"freq":3}]},"main-st-1ac0":{"m":36,"r":"X1","x":0,"legs":[{"mode":"RAIL","line":"X1","from":"Ravinia","to":"Main St.","ride":24,"wait":7,"freq":15}]},"mannheim-1b6e":{"m":143,"r":"X1|X6|330","x":2,"legs":[{"mode":"RAIL","line":"X1","from":"Ravinia","to":"Chicago Union Station","ride":47,"wait":7,"freq":30},{"mode":"RAIL","line":"X6","from":"Chicago Union Station","to":"Bellwood","ride":24,"wait":31,"freq":30},{"mode":"BUS","line":"330","from":"Bellwood","to":"Mannheim","ride":13,"wait":1}]},"mars-1b8c":{"m":88,"r":"X1|X5","x":1,"legs":[{"mode":"RAIL","line":"X1","from":"Ravinia","to":"Chicago Union Station","ride":47,"wait":7,"freq":30},{"mode":"RAIL","line":"X5","from":"Chicago Union Station","to":"Mars","ride":20,"wait":6,"freq":30}]},"matteson-1afa":{"m":136,"r":"X1|ME","x":1,"legs":[{"mode":"RAIL","line":"X1","from":"Ravinia","to":"Roosevelt","ride":51,"wait":7,"freq":30},{"mode":"RAIL","line":"ME","from":"Museum Campus/11th St.","to":"Matteson","ride":52,"wait":8,"freq":30}]},"mayfair-1bcc":{"m":69,"r":"X1|X3","x":1,"legs":[{"mode":"RAIL","line":"X1","from":"Ravinia","to":"Clybourn","ride":37,"wait":7,"freq":15},{"mode":"RAIL","line":"X3","from":"Clybourn","to":"Montrose (Blue)","ride":8,"wait":6,"freq":15}]},"maywood-1bc1":{"m":108,"r":"X1|X6","x":1,"legs":[{"mode":"RAIL","line":"X1","from":"Ravinia","to":"Chicago Union Station","ride":47,"wait":7,"freq":30},{"mode":"RAIL","line":"X6","from":"Chicago Union Station","to":"Maywood","ride":19,"wait":31,"freq":30}]},"mccormick-place-1b1b":{"m":70,"r":"X1","x":0,"legs":[{"mode":"RAIL","line":"X1","from":"Ravinia","to":"McCormick Place","ride":55,"wait":7,"freq":30}]},"medinah-1b19":{"m":129,"r":"X1|MD-W","x":1,"legs":[{"mode":"RAIL","line":"X1","from":"Ravinia","to":"Chicago Union Station","ride":47,"wait":7,"freq":30},{"mode":"RAIL","line":"MD-W","from":"Chicago Union Station","to":"Medinah","ride":45,"wait":21,"freq":60}]},"melrose-park-1b85":{"m":110,"r":"X1|X6","x":1,"legs":[{"mode":"RAIL","line":"X1","from":"Ravinia","to":"Chicago Union Station","ride":47,"wait":7,"freq":30},{"mode":"RAIL","line":"X6","from":"Chicago Union Station","to":"Melrose Park","ride":21,"wait":31,"freq":30}]},"merchandise-mart-brown-purple-1b7d":{"m":72,"r":"X1","x":0,"legs":[{"mode":"RAIL","line":"X1","from":"Ravinia","to":"Clinton (Green/Pink)","ride":45,"wait":7,"freq":30}]},"michigan-116th-1b06":{"m":110,"r":"X1|Red|RLE","x":2,"legs":[{"mode":"RAIL","line":"X1","from":"Ravinia","to":"Roosevelt","ride":51,"wait":7,"freq":30},{"mode":"SUBWAY","line":"Red","from":"Roosevelt","to":"95th/Dan Ryan","ride":23,"wait":4,"freq":3},{"mode":"SUBWAY","line":"RLE","from":"95th/Dan Ryan","to":"Michigan (116th)","ride":7,"wait":10,"freq":3}]},"midlothian-1b14":{"m":132,"r":"X1|RI","x":1,"legs":[{"mode":"RAIL","line":"X1","from":"Ravinia","to":"Chicago Union Station","ride":47,"wait":7,"freq":30},{"mode":"RAIL","line":"RI","from":"LaSalle Street","to":"Midlothian","ride":32,"wait":36,"freq":60}]},"midway-1bda":{"m":94,"r":"X1|Org","x":1,"legs":[{"mode":"RAIL","line":"X1","from":"Ravinia","to":"Roosevelt","ride":51,"wait":7,"freq":30},{"mode":"SUBWAY","line":"Org","from":"Roosevelt","to":"Midway","ride":20,"wait":7,"freq":30}]},"millennium-station-1adf":{"m":78,"r":"X1|56","x":1,"legs":[{"mode":"RAIL","line":"X1","from":"Ravinia","to":"Clinton (Green/Pink)","ride":45,"wait":7,"freq":30},{"mode":"BUS","line":"56","from":"Chicago OTC","to":"Washington/Wabash","ride":8,"wait":2,"freq":2}]},"mokena-1bc7":{"m":153,"r":"X1|RI","x":1,"legs":[{"mode":"RAIL","line":"X1","from":"Ravinia","to":"Chicago Union Station","ride":47,"wait":7,"freq":30},{"mode":"RAIL","line":"RI","from":"LaSalle Street","to":"Mokena","ride":52,"wait":36,"freq":60}]},"monroe-blue-1b74":{"m":74,"r":"X1|Blue","x":1,"legs":[{"mode":"RAIL","line":"X1","from":"Ravinia","to":"Chicago Union Station","ride":47,"wait":7,"freq":30},{"mode":"SUBWAY","line":"Blue","from":"Clinton (Blue)","to":"Monroe (Blue)","ride":4,"wait":2,"freq":5}]},"mont-clare-1b16":{"m":99,"r":"X1|X5","x":1,"legs":[{"mode":"RAIL","line":"X1","from":"Ravinia","to":"Chicago Union Station","ride":47,"wait":7,"freq":30},{"mode":"RAIL","line":"X5","from":"Chicago Union Station","to":"Grand/Harlem","ride":22,"wait":6,"freq":30}]},"montrose-blue-1b8c":{"m":68,"r":"X1|X3","x":1,"legs":[{"mode":"RAIL","line":"X1","from":"Ravinia","to":"Clybourn","ride":37,"wait":7,"freq":15},{"mode":"RAIL","line":"X3","from":"Clybourn","to":"Montrose (Blue)","ride":8,"wait":6,"freq":15}]},"montrose-brown-1b45":{"m":54,"r":"X1|Brn","x":1,"legs":[{"mode":"RAIL","line":"X1","from":"Ravinia","to":"Addison (Brown)","ride":34,"wait":7,"freq":30},{"mode":"SUBWAY","line":"Brn","from":"Addison (Brown)","to":"Montrose (Brown)","ride":2,"wait":2,"freq":30}]},"morgan-green-pink-1b1c":{"m":65,"r":"X1|G","x":1,"legs":[{"mode":"RAIL","line":"X1","from":"Ravinia","to":"Clinton (Green/Pink)","ride":45,"wait":7,"freq":30},{"mode":"SUBWAY","line":"G","from":"Clinton (Green/Pink)","to":"Morgan (Green/Pink)","ride":2,"wait":2,"freq":9}]},"morse-1b95":{"m":48,"r":"X1|UP-N|96","x":2,"legs":[{"mode":"RAIL","line":"X1","from":"Braeside","to":"Highland Park","ride":6,"wait":4,"freq":20},{"mode":"RAIL","line":"UP-N","from":"Highland Park","to":"Rogers Park","ride":21,"wait":2,"freq":10},{"mode":"BUS","line":"96","from":"Rogers Park","to":"Morse","ride":4,"wait":2,"freq":15}]},"morton-grove-1b3f":{"m":79,"r":"X1|Y|210","x":2,"legs":[{"mode":"RAIL","line":"X1","from":"Ravinia","to":"Howard/Clark","ride":26,"wait":7,"freq":30},{"mode":"SUBWAY","line":"Y","from":"Howard","to":"Oakton-Skokie","ride":6,"wait":9,"freq":7},{"mode":"BUS","line":"210","from":"Oakton-Skokie","to":"Morton Grove","ride":10,"wait":6,"freq":30}]},"mt-prospect-1b0c":{"m":87,"r":"X1|X3","x":1,"legs":[{"mode":"RAIL","line":"X1","from":"Ravinia","to":"Clybourn","ride":37,"wait":7,"freq":15},{"mode":"RAIL","line":"X3","from":"Clybourn","to":"Mt. Prospect","ride":29,"wait":6,"freq":12}]},"mundelein-1bd0":{"m":169,"r":"UP-N|572|574","x":2,"legs":[{"mode":"RAIL","line":"UP-N","from":"Braeside","to":"Waukegan","ride":34,"wait":9,"freq":60},{"mode":"BUS","line":"572","from":"Waukegan","to":"Washington St (Grayslake)","ride":31,"wait":7},{"mode":"BUS","line":"574","from":"Washington St (Grayslake)","to":"Mundelein","ride":18,"wait":37,"freq":60}]},"museum-campus-11th-st-1b1b":{"m":75,"r":"X1","x":0,"legs":[{"mode":"RAIL","line":"X1","from":"Ravinia","to":"Roosevelt","ride":51,"wait":7,"freq":30}]},"naperville-1b6b":{"m":150,"r":"X1|BNSF","x":1,"legs":[{"mode":"RAIL","line":"X1","from":"Ravinia","to":"Chicago Union Station","ride":47,"wait":7,"freq":30},{"mode":"RAIL","line":"BNSF","from":"Chicago Union Station","to":"Naperville","ride":62,"wait":24,"freq":60}]},"national-st-1ba5":{"m":148,"r":"X1|MD-W","x":1,"legs":[{"mode":"RAIL","line":"X1","from":"Ravinia","to":"Chicago Union Station","ride":47,"wait":7,"freq":30},{"mode":"RAIL","line":"MD-W","from":"Chicago Union Station","to":"National St","ride":68,"wait":21,"freq":60}]},"new-lenox-1b5b":{"m":158,"r":"X1|RI","x":1,"legs":[{"mode":"RAIL","line":"X1","from":"Ravinia","to":"Chicago Union Station","ride":47,"wait":7,"freq":30},{"mode":"RAIL","line":"RI","from":"LaSalle Street","to":"New Lenox","ride":58,"wait":36,"freq":60}]},"north-chicago-1bb8":{"m":65,"r":"UP-N","x":0,"legs":[{"mode":"RAIL","line":"UP-N","from":"Braeside","to":"North Chicago","ride":28,"wait":9,"freq":60}]},"north-clybourn-1b51":{"m":69,"r":"X1|X9|72","x":2,"legs":[{"mode":"RAIL","line":"X1","from":"Ravinia","to":"Clybourn","ride":37,"wait":7,"freq":15},{"mode":"BUS","line":"X9","from":"Clybourn","to":"Clybourn","ride":2,"wait":3},{"mode":"BUS","line":"72","from":"Clybourn","to":"North/Clybourn","ride":9,"wait":2}]},"north-ridgeway-1b74":{"m":80,"r":"X1|X5","x":1,"legs":[{"mode":"RAIL","line":"X1","from":"Ravinia","to":"Chicago Union Station","ride":47,"wait":7,"freq":30},{"mode":"RAIL","line":"X5","from":"Chicago Union Station","to":"North/Ridgeway","ride":12,"wait":6,"freq":30}]},"northbrook-1baa":{"m":66,"r":"X1|423|422","x":2,"legs":[{"mode":"RAIL","line":"X1","from":"Ravinia","to":"Winnetka","ride":12,"wait":7,"freq":15},{"mode":"BUS","line":"423","from":"Winnetka","to":"Glen/N. Glenview","ride":10,"wait":8},{"mode":"BUS","line":"422","from":"Glen/N. Glenview","to":"Northbrook","ride":12,"wait":5,"freq":30}]},"norwood-park-1c33":{"m":72,"r":"X1|X3","x":1,"legs":[{"mode":"RAIL","line":"X1","from":"Ravinia","to":"Clybourn","ride":37,"wait":7,"freq":15},{"mode":"RAIL","line":"X3","from":"Clybourn","to":"Norwood Park","ride":14,"wait":6,"freq":12}]},"noyes-1b45":{"m":42,"r":"X1|P","x":1,"legs":[{"mode":"RAIL","line":"X1","from":"Ravinia","to":"Evanston (Davis St.)","ride":22,"wait":7,"freq":15},{"mode":"SUBWAY","line":"P","from":"Evanston (Davis St.)","to":"Noyes","ride":2,"wait":5}]},"o-hare-1b3d":{"m":96,"r":"X1|X3|Blue","x":2,"legs":[{"mode":"RAIL","line":"X1","from":"Ravinia","to":"Clybourn","ride":37,"wait":7,"freq":15},{"mode":"RAIL","line":"X3","from":"Clybourn","to":"Belmont/Kedzie","ride":4,"wait":6,"freq":15},{"mode":"SUBWAY","line":"Blue","from":"Belmont (Blue)","to":"O'Hare","ride":26,"wait":2,"freq":7}]},"o-hare-transfer-1b71":{"m":105,"r":"X1|X5","x":1,"legs":[{"mode":"RAIL","line":"X1","from":"Ravinia","to":"Chicago Union Station","ride":47,"wait":7,"freq":30},{"mode":"RAIL","line":"X5","from":"Chicago Union Station","to":"O'Hare Transfer","ride":39,"wait":6,"freq":30}]},"oak-forest-1b43":{"m":137,"r":"X1|RI","x":1,"legs":[{"mode":"RAIL","line":"X1","from":"Ravinia","to":"Chicago Union Station","ride":47,"wait":7,"freq":30},{"mode":"RAIL","line":"RI","from":"LaSalle Street","to":"Oak Forest","ride":36,"wait":36,"freq":60}]},"oak-lawn-patriot-1ba8":{"m":119,"r":"X1|SWS","x":1,"legs":[{"mode":"RAIL","line":"X1","from":"Ravinia","to":"Chicago Union Station","ride":47,"wait":7,"freq":30},{"mode":"RAIL","line":"SWS","from":"Chicago Union Station","to":"Oak Lawn Patriot","ride":31,"wait":33,"freq":60}]},"oak-park-1afc":{"m":92,"r":"X1|G","x":1,"legs":[{"mode":"RAIL","line":"X1","from":"Ravinia","to":"Clinton (Green/Pink)","ride":45,"wait":7,"freq":30},{"mode":"SUBWAY","line":"G","from":"Clinton (Green/Pink)","to":"Harlem/Lake","ride":24,"wait":2,"freq":9}]},"oak-park-blue-1b68":{"m":111,"r":"X1|Blue","x":1,"legs":[{"mode":"RAIL","line":"X1","from":"Ravinia","to":"Division/Elston","ride":40,"wait":7,"freq":30},{"mode":"SUBWAY","line":"Blue","from":"Division","to":"Oak Park (Blue)","ride":42,"wait":6,"freq":5}]},"oak-park-green-1bc2":{"m":86,"r":"X1|G","x":1,"legs":[{"mode":"RAIL","line":"X1","from":"Ravinia","to":"Clinton (Green/Pink)","ride":45,"wait":7,"freq":30},{"mode":"SUBWAY","line":"G","from":"Clinton (Green/Pink)","to":"Oak Park (Green)","ride":22,"wait":2,"freq":9}]},"oakton-skokie-1b24":{"m":59,"r":"X1|Y","x":1,"legs":[{"mode":"RAIL","line":"X1","from":"Ravinia","to":"Howard/Clark","ride":26,"wait":7,"freq":30},{"mode":"SUBWAY","line":"Y","from":"Howard","to":"Oakton-Skokie","ride":6,"wait":9,"freq":7}]},"oakwood-blvd-1ad9":{"m":74,"r":"X1","x":0,"legs":[{"mode":"RAIL","line":"X1","from":"Ravinia","to":"Oakwood Blvd","ride":59,"wait":7,"freq":30}]},"olympia-fields-1ad6":{"m":132,"r":"X1|ME","x":1,"legs":[{"mode":"RAIL","line":"X1","from":"Ravinia","to":"Roosevelt","ride":51,"wait":7,"freq":30},{"mode":"RAIL","line":"ME","from":"Museum Campus/11th St.","to":"Olympia Fields","ride":48,"wait":8,"freq":30}]},"orland-park-143rd-1b70":{"m":136,"r":"X1|SWS","x":1,"legs":[{"mode":"RAIL","line":"X1","from":"Ravinia","to":"Chicago Union Station","ride":47,"wait":7,"freq":30},{"mode":"RAIL","line":"SWS","from":"Chicago Union Station","to":"Orland Park 143rd","ride":48,"wait":33,"freq":60}]},"orland-park-153rd-1b5b":{"m":139,"r":"X1|SWS","x":1,"legs":[{"mode":"RAIL","line":"X1","from":"Ravinia","to":"Chicago Union Station","ride":47,"wait":7,"freq":30},{"mode":"RAIL","line":"SWS","from":"Chicago Union Station","to":"Orland Park 153rd","ride":51,"wait":33,"freq":60}]},"orland-park-179th-1b30":{"m":148,"r":"X1|SWS","x":1,"legs":[{"mode":"RAIL","line":"X1","from":"Ravinia","to":"Chicago Union Station","ride":47,"wait":7,"freq":30},{"mode":"RAIL","line":"SWS","from":"Chicago Union Station","to":"Orland Park 179th","ride":60,"wait":33,"freq":60}]},"palatine-1ad9":{"m":115,"r":"X1|X2","x":1,"legs":[{"mode":"RAIL","line":"X1","from":"Ravinia","to":"Taylor/Clinton","ride":49,"wait":7,"freq":30},{"mode":"RAIL","line":"X2","from":"Taylor/Clinton","to":"Palatine","ride":51,"wait":4,"freq":30}]},"palos-heights-1ba1":{"m":128,"r":"X1|SWS","x":1,"legs":[{"mode":"RAIL","line":"X1","from":"Ravinia","to":"Chicago Union Station","ride":47,"wait":7,"freq":30},{"mode":"RAIL","line":"SWS","from":"Chicago Union Station","to":"Palos Heights","ride":40,"wait":33,"freq":60}]},"palos-park-1b23":{"m":131,"r":"X1|SWS","x":1,"legs":[{"mode":"RAIL","line":"X1","from":"Ravinia","to":"Chicago Union Station","ride":47,"wait":7,"freq":30},{"mode":"RAIL","line":"SWS","from":"Chicago Union Station","to":"Palos Park","ride":43,"wait":33,"freq":60}]},"park-ridge-1af7":{"m":76,"r":"X1|X3","x":1,"legs":[{"mode":"RAIL","line":"X1","from":"Ravinia","to":"Clybourn","ride":37,"wait":7,"freq":15},{"mode":"RAIL","line":"X3","from":"Clybourn","to":"Park Ridge","ride":18,"wait":6,"freq":12}]},"paulina-1b7e":{"m":55,"r":"X1","x":0,"legs":[{"mode":"RAIL","line":"X1","from":"Ravinia","to":"Addison (Brown)","ride":34,"wait":7,"freq":30}]},"peterson-ridge-1b23":{"m":41,"r":"X1|UP-N","x":1,"legs":[{"mode":"RAIL","line":"X1","from":"Braeside","to":"Highland Park","ride":6,"wait":4,"freq":20},{"mode":"RAIL","line":"UP-N","from":"Highland Park","to":"Peterson/Ridge","ride":24,"wait":2,"freq":10}]},"pingree-road-1b34":{"m":159,"r":"X1|UP-NW","x":1,"legs":[{"mode":"RAIL","line":"X1","from":"Ravinia","to":"Clinton (Green/Pink)","ride":45,"wait":7,"freq":30},{"mode":"RAIL","line":"UP-NW","from":"Chicago OTC","to":"Pingree Road","ride":78,"wait":24,"freq":60}]},"polk-1bb6":{"m":74,"r":"X1|Pink","x":1,"legs":[{"mode":"RAIL","line":"X1","from":"Ravinia","to":"Clinton (Green/Pink)","ride":45,"wait":7,"freq":30},{"mode":"SUBWAY","line":"Pink","from":"Clinton (Green/Pink)","to":"Polk","ride":6,"wait":4}]},"prairie-crossing-1aae":{"m":97,"r":"X1|423|MD-N","x":2,"legs":[{"mode":"RAIL","line":"X1","from":"Ravinia","to":"Winnetka","ride":12,"wait":7,"freq":15},{"mode":"BUS","line":"423","from":"Winnetka","to":"Glen/N. Glenview","ride":20,"wait":8},{"mode":"RAIL","line":"MD-N","from":"Glen/N. Glenview","to":"Prairie Crossing","ride":34,"wait":1,"freq":60}]},"prairie-crossing-1ab6":{"m":103,"r":"X1|423|MD-N","x":2,"legs":[{"mode":"RAIL","line":"X1","from":"Ravinia","to":"Winnetka","ride":12,"wait":7,"freq":15},{"mode":"BUS","line":"423","from":"Winnetka","to":"Glen/N. Glenview","ride":20,"wait":8},{"mode":"RAIL","line":"MD-N","from":"Glen/N. Glenview","to":"Prairie Crossing","ride":34,"wait":1,"freq":60}]},"prairie-st-1b2a":{"m":126,"r":"X1|X6","x":1,"legs":[{"mode":"RAIL","line":"X1","from":"Ravinia","to":"Chicago Union Station","ride":47,"wait":7,"freq":30},{"mode":"RAIL","line":"X6","from":"Chicago Union Station","to":"Prairie St.","ride":41,"wait":23,"freq":30}]},"prospect-hts-1b10":{"m":109,"r":"213|626|NCS","x":2,"legs":[{"mode":"BUS","line":"213","from":"Braeside","to":"Ravinia","ride":4,"wait":18,"freq":20},{"mode":"BUS","line":"626","from":"Ravinia Park","to":"Buffalo Grove","ride":35,"wait":14},{"mode":"RAIL","line":"NCS","from":"Buffalo Grove","to":"Prospect Hts","ride":10,"wait":6,"freq":60}]},"pulaski-blue-1b89":{"m":86,"r":"X1|G|53","x":2,"legs":[{"mode":"RAIL","line":"X1","from":"Ravinia","to":"Clinton (Green/Pink)","ride":45,"wait":7,"freq":30},{"mode":"SUBWAY","line":"G","from":"Clinton (Green/Pink)","to":"Pulaski (Green)","ride":12,"wait":2,"freq":9},{"mode":"BUS","line":"53","from":"Pulaski (Green)","to":"Pulaski (Blue)","ride":6,"wait":3,"freq":9}]},"pulaski-green-1b4e":{"m":76,"r":"X1|G","x":1,"legs":[{"mode":"RAIL","line":"X1","from":"Ravinia","to":"Clinton (Green/Pink)","ride":45,"wait":7,"freq":30},{"mode":"SUBWAY","line":"G","from":"Clinton (Green/Pink)","to":"Pulaski (Green)","ride":12,"wait":2,"freq":9}]},"pulaski-orange-1b84":{"m":91,"r":"X1|Org","x":1,"legs":[{"mode":"RAIL","line":"X1","from":"Ravinia","to":"Roosevelt","ride":51,"wait":7,"freq":30},{"mode":"SUBWAY","line":"Org","from":"Roosevelt","to":"Pulaski (Orange)","ride":18,"wait":7,"freq":9}]},"pulaski-pink-1b29":{"m":86,"r":"X1|Pink","x":1,"legs":[{"mode":"RAIL","line":"X1","from":"Ravinia","to":"Clinton (Green/Pink)","ride":45,"wait":7,"freq":30},{"mode":"SUBWAY","line":"Pink","from":"Clinton (Green/Pink)","to":"Pulaski (Pink)","ride":18,"wait":4}]},"quincy-1b83":{"m":69,"r":"X1","x":0,"legs":[{"mode":"RAIL","line":"X1","from":"Ravinia","to":"Chicago Union Station","ride":47,"wait":7,"freq":30}]},"racine-1b5e":{"m":126,"r":"X1|RI|119","x":2,"legs":[{"mode":"RAIL","line":"X1","from":"Ravinia","to":"Chicago Union Station","ride":47,"wait":7,"freq":30},{"mode":"RAIL","line":"RI","from":"LaSalle Street","to":"119th St.","ride":34,"wait":6,"freq":60},{"mode":"BUS","line":"119","from":"119th St.","to":"Racine","ride":3,"wait":2}]},"racine-1bd5":{"m":79,"r":"X1|X9|126","x":2,"legs":[{"mode":"RAIL","line":"X1","from":"Ravinia","to":"Clybourn","ride":37,"wait":7,"freq":15},{"mode":"BUS","line":"X9","from":"Clybourn","to":"Illinois Medical District","ride":15,"wait":3},{"mode":"BUS","line":"126","from":"Illinois Medical District","to":"Racine","ride":2,"wait":3,"freq":5}]},"ravenswood-1b7d":{"m":47,"r":"X1","x":0,"legs":[{"mode":"RAIL","line":"X1","from":"Ravinia","to":"Ravenswood","ride":32,"wait":7,"freq":15}]},"ravinia-1b75":{"m":13,"r":"X1","x":0,"legs":[{"mode":"RAIL","line":"X1","from":"Braeside","to":"Ravinia","ride":3,"wait":4,"freq":20}]},"ravinia-park-1bc7":{"m":0},"richton-park-1b6c":{"m":137,"r":"X1|ME","x":1,"legs":[{"mode":"RAIL","line":"X1","from":"Ravinia","to":"Roosevelt","ride":51,"wait":7,"freq":30},{"mode":"RAIL","line":"ME","from":"Museum Campus/11th St.","to":"Richton Park","ride":55,"wait":8,"freq":30}]},"ridgeland-1bb2":{"m":85,"r":"X1|G","x":1,"legs":[{"mode":"RAIL","line":"X1","from":"Ravinia","to":"Clinton (Green/Pink)","ride":45,"wait":7,"freq":30},{"mode":"SUBWAY","line":"G","from":"Clinton (Green/Pink)","to":"Ridgeland","ride":22,"wait":2,"freq":9}]},"river-forest-1b44":{"m":106,"r":"X1|X6","x":1,"legs":[{"mode":"RAIL","line":"X1","from":"Ravinia","to":"Chicago Union Station","ride":47,"wait":7,"freq":30},{"mode":"RAIL","line":"X6","from":"Chicago Union Station","to":"River Forest","ride":17,"wait":31,"freq":30}]},"river-grove-1b06":{"m":96,"r":"X1|X5","x":1,"legs":[{"mode":"RAIL","line":"X1","from":"Ravinia","to":"Chicago Union Station","ride":47,"wait":7,"freq":30},{"mode":"RAIL","line":"X5","from":"Chicago Union Station","to":"River Grove","ride":26,"wait":6,"freq":20}]},"riverdale-1b12":{"m":114,"r":"X1|ME","x":1,"legs":[{"mode":"RAIL","line":"X1","from":"Ravinia","to":"Roosevelt","ride":51,"wait":7,"freq":30},{"mode":"RAIL","line":"ME","from":"Museum Campus/11th St.","to":"Riverdale","ride":29,"wait":8,"freq":30}]},"riverside-1ab0":{"m":101,"r":"X1|X5","x":1,"legs":[{"mode":"RAIL","line":"X1","from":"Ravinia","to":"Chicago Union Station","ride":47,"wait":7,"freq":30},{"mode":"RAIL","line":"X5","from":"Chicago Union Station","to":"Riverside","ride":25,"wait":18,"freq":20}]},"robbins-1b76":{"m":130,"r":"X1|RI","x":1,"legs":[{"mode":"RAIL","line":"X1","from":"Ravinia","to":"Chicago Union Station","ride":47,"wait":7,"freq":30},{"mode":"RAIL","line":"RI","from":"LaSalle Street","to":"Robbins","ride":29,"wait":36,"freq":60}]},"rockwell-1b4f":{"m":57,"r":"X1|Brn","x":1,"legs":[{"mode":"RAIL","line":"X1","from":"Ravinia","to":"Addison (Brown)","ride":34,"wait":7,"freq":30},{"mode":"SUBWAY","line":"Brn","from":"Addison (Brown)","to":"Rockwell","ride":7,"wait":2,"freq":30}]},"rogers-park-1b79":{"m":40,"r":"X1|UP-N","x":1,"legs":[{"mode":"RAIL","line":"X1","from":"Braeside","to":"Highland Park","ride":6,"wait":4,"freq":20},{"mode":"RAIL","line":"UP-N","from":"Highland Park","to":"Rogers Park","ride":21,"wait":2,"freq":10}]},"roosevelt-1b21":{"m":66,"r":"X1","x":0,"legs":[{"mode":"RAIL","line":"X1","from":"Ravinia","to":"Roosevelt","ride":51,"wait":7,"freq":30}]},"roselle-1b20":{"m":131,"r":"X1|MD-W","x":1,"legs":[{"mode":"RAIL","line":"X1","from":"Ravinia","to":"Chicago Union Station","ride":47,"wait":7,"freq":30},{"mode":"RAIL","line":"MD-W","from":"Chicago Union Station","to":"Roselle","ride":47,"wait":21,"freq":60}]},"rosemont-1bc3":{"m":104,"r":"X1|X5","x":1,"legs":[{"mode":"RAIL","line":"X1","from":"Ravinia","to":"Chicago Union Station","ride":47,"wait":7,"freq":30},{"mode":"RAIL","line":"X5","from":"Chicago Union Station","to":"Rosemont","ride":36,"wait":6,"freq":30}]},"rosemont-1bc0":{"m":92,"r":"X1|X3|Blue","x":2,"legs":[{"mode":"RAIL","line":"X1","from":"Ravinia","to":"Clybourn","ride":37,"wait":7,"freq":15},{"mode":"RAIL","line":"X3","from":"Clybourn","to":"Belmont/Kedzie","ride":4,"wait":6,"freq":15},{"mode":"SUBWAY","line":"Blue","from":"Belmont (Blue)","to":"Rosemont","ride":20,"wait":2,"freq":7}]},"round-lake-1b0a":{"m":108,"r":"UP-N|572|570","x":2,"legs":[{"mode":"RAIL","line":"UP-N","from":"Braeside","to":"Waukegan","ride":34,"wait":9,"freq":60},{"mode":"BUS","line":"572","from":"Waukegan","to":"Washington St (Grayslake)","ride":31,"wait":7},{"mode":"BUS","line":"570","from":"Washington St (Grayslake)","to":"Round Lake","ride":19,"wait":3}]},"route-59-1b68":{"m":148,"r":"X1|BNSF","x":1,"legs":[{"mode":"RAIL","line":"X1","from":"Ravinia","to":"Chicago Union Station","ride":47,"wait":7,"freq":30},{"mode":"RAIL","line":"BNSF","from":"Chicago Union Station","to":"Route 59","ride":66,"wait":24,"freq":60}]},"schiller-park-1b7a":{"m":107,"r":"X1|X5","x":1,"legs":[{"mode":"RAIL","line":"X1","from":"Ravinia","to":"Chicago Union Station","ride":47,"wait":7,"freq":30},{"mode":"RAIL","line":"X5","from":"Chicago Union Station","to":"Lawrence/Ruby","ride":34,"wait":6,"freq":30}]},"schiller-park-irving-park-rd-1bc4":{"m":100,"r":"X1|X5","x":1,"legs":[{"mode":"RAIL","line":"X1","from":"Ravinia","to":"Chicago Union Station","ride":47,"wait":7,"freq":30},{"mode":"RAIL","line":"X5","from":"Chicago Union Station","to":"Schiller Park - Irving Park Rd","ride":32,"wait":6,"freq":30}]},"sedgwick-brown-purple-1b3e":{"m":68,"r":"X1|Brn","x":1,"legs":[{"mode":"RAIL","line":"X1","from":"Ravinia","to":"Addison (Brown)","ride":34,"wait":7,"freq":30},{"mode":"SUBWAY","line":"Brn","from":"Addison (Brown)","to":"Sedgwick (Brown/Purple)","ride":16,"wait":6,"freq":4}]},"sheridan-1b98":{"m":62,"r":"X1|Red","x":1,"legs":[{"mode":"RAIL","line":"X1","from":"Ravinia","to":"Howard/Clark","ride":26,"wait":7,"freq":30},{"mode":"SUBWAY","line":"Red","from":"Howard","to":"Sheridan","ride":17,"wait":3,"freq":4}]},"south-boulevard-1b82":{"m":45,"r":"X1","x":0,"legs":[{"mode":"RAIL","line":"X1","from":"Ravinia","to":"Main St.","ride":24,"wait":7,"freq":15}]},"south-chicago-93rd-1ba7":{"m":101,"r":"X1","x":0,"legs":[{"mode":"RAIL","line":"X1","from":"Ravinia","to":"South Chicago (93rd)","ride":86,"wait":7,"freq":30}]},"south-shore-1b97":{"m":90,"r":"X1","x":0,"legs":[{"mode":"RAIL","line":"X1","from":"Ravinia","to":"South Shore","ride":75,"wait":7,"freq":30}]},"southport-1b74":{"m":59,"r":"X1|Brn","x":1,"legs":[{"mode":"RAIL","line":"X1","from":"Ravinia","to":"Addison (Brown)","ride":34,"wait":7,"freq":30},{"mode":"SUBWAY","line":"Brn","from":"Addison (Brown)","to":"Southport","ride":4,"wait":6,"freq":4}]},"state-st-1b42":{"m":116,"r":"X1|Red|34","x":2,"legs":[{"mode":"RAIL","line":"X1","from":"Ravinia","to":"Roosevelt","ride":51,"wait":7,"freq":30},{"mode":"SUBWAY","line":"Red","from":"Roosevelt","to":"95th/Dan Ryan","ride":23,"wait":4,"freq":3},{"mode":"BUS","line":"34","from":"95th/Dan Ryan","to":"State St.","ride":14,"wait":7,"freq":9}]},"stewart-ridge-1b30":{"m":126,"r":"X1|Red|119","x":2,"legs":[{"mode":"RAIL","line":"X1","from":"Ravinia","to":"Roosevelt","ride":51,"wait":7,"freq":30},{"mode":"SUBWAY","line":"Red","from":"Roosevelt","to":"95th/Dan Ryan","ride":23,"wait":4,"freq":3},{"mode":"BUS","line":"119","from":"95th/Dan Ryan","to":"Stewart Ridge","ride":16,"wait":13}]},"stone-ave-1b87":{"m":110,"r":"X1|X5","x":1,"legs":[{"mode":"RAIL","line":"X1","from":"Ravinia","to":"Chicago Union Station","ride":47,"wait":7,"freq":30},{"mode":"RAIL","line":"X5","from":"Chicago Union Station","to":"Stone Ave.","ride":33,"wait":18,"freq":30}]},"stony-island-1bca":{"m":86,"r":"X1","x":0,"legs":[{"mode":"RAIL","line":"X1","from":"Ravinia","to":"Stony Island","ride":71,"wait":7,"freq":30}]},"summit-1b90":{"m":125,"r":"X1|X5|307","x":2,"legs":[{"mode":"RAIL","line":"X1","from":"Ravinia","to":"Chicago Union Station","ride":47,"wait":7,"freq":30},{"mode":"RAIL","line":"X5","from":"Chicago Union Station","to":"Harlem Ave.","ride":22,"wait":18,"freq":20},{"mode":"BUS","line":"307","from":"Harlem Ave.","to":"Summit","ride":8,"wait":2}]},"taylor-clinton-1b7c":{"m":64,"r":"X1","x":0,"legs":[{"mode":"RAIL","line":"X1","from":"Ravinia","to":"Taylor/Clinton","ride":49,"wait":7,"freq":30}]},"thorndale-1b4d":{"m":56,"r":"X1|Red","x":1,"legs":[{"mode":"RAIL","line":"X1","from":"Ravinia","to":"Howard/Clark","ride":26,"wait":7,"freq":30},{"mode":"SUBWAY","line":"Red","from":"Howard","to":"Thorndale","ride":8,"wait":3,"freq":4}]},"tinley-park-1bc0":{"m":142,"r":"X1|RI","x":1,"legs":[{"mode":"RAIL","line":"X1","from":"Ravinia","to":"Chicago Union Station","ride":47,"wait":7,"freq":30},{"mode":"RAIL","line":"RI","from":"LaSalle Street","to":"Tinley Park","ride":41,"wait":36,"freq":60}]},"tinley-80th-1b5f":{"m":145,"r":"X1|RI","x":1,"legs":[{"mode":"RAIL","line":"X1","from":"Ravinia","to":"Chicago Union Station","ride":47,"wait":7,"freq":30},{"mode":"RAIL","line":"RI","from":"LaSalle Street","to":"Tinley-80th","ride":44,"wait":36,"freq":60}]},"uic-halsted-1bcb":{"m":75,"r":"X1|Blue","x":1,"legs":[{"mode":"RAIL","line":"X1","from":"Ravinia","to":"Chicago Union Station","ride":47,"wait":7,"freq":30},{"mode":"SUBWAY","line":"Blue","from":"Clinton (Blue)","to":"UIC-Halsted","ride":2,"wait":6,"freq":2}]},"university-park-1b19":{"m":139,"r":"X1|ME","x":1,"legs":[{"mode":"RAIL","line":"X1","from":"Ravinia","to":"Roosevelt","ride":51,"wait":7,"freq":30},{"mode":"RAIL","line":"ME","from":"Museum Campus/11th St.","to":"University Park","ride":59,"wait":8,"freq":30}]},"van-buren-st-1b17":{"m":79,"r":"X1|Red","x":1,"legs":[{"mode":"RAIL","line":"X1","from":"Ravinia","to":"Roosevelt","ride":51,"wait":7,"freq":30},{"mode":"SUBWAY","line":"Red","from":"Roosevelt","to":"Jackson (Blue)","ride":2,"wait":5,"freq":2}]},"washington-1b63":{"m":71,"r":"X1|56","x":1,"legs":[{"mode":"RAIL","line":"X1","from":"Ravinia","to":"Clinton (Green/Pink)","ride":45,"wait":7,"freq":30},{"mode":"BUS","line":"56","from":"Chicago OTC","to":"Washington","ride":5,"wait":2,"freq":2}]},"washington-wabash-1b16":{"m":74,"r":"X1|G","x":1,"legs":[{"mode":"RAIL","line":"X1","from":"Ravinia","to":"Clinton (Green/Pink)","ride":45,"wait":7,"freq":30},{"mode":"SUBWAY","line":"G","from":"Clinton (Green/Pink)","to":"Washington/Wabash","ride":5,"wait":6,"freq":4}]},"washington-wells-1b74":{"m":70,"r":"X1|56","x":1,"legs":[{"mode":"RAIL","line":"X1","from":"Ravinia","to":"Clinton (Green/Pink)","ride":45,"wait":7,"freq":30},{"mode":"BUS","line":"56","from":"Chicago OTC","to":"Washington/Wells","ride":2,"wait":2,"freq":2}]},"waukegan-1b4c":{"m":70,"r":"UP-N","x":0,"legs":[{"mode":"RAIL","line":"UP-N","from":"Braeside","to":"Waukegan","ride":34,"wait":9,"freq":60}]},"wellington-brown-purple-1b12":{"m":60,"r":"X1|Brn","x":1,"legs":[{"mode":"RAIL","line":"X1","from":"Ravinia","to":"Addison (Brown)","ride":34,"wait":7,"freq":30},{"mode":"SUBWAY","line":"Brn","from":"Addison (Brown)","to":"Wellington (Brown/Purple)","ride":7,"wait":6,"freq":4}]},"west-hinsdale-1baa":{"m":122,"r":"X1|X5","x":1,"legs":[{"mode":"RAIL","line":"X1","from":"Ravinia","to":"Chicago Union Station","ride":47,"wait":7,"freq":30},{"mode":"RAIL","line":"X5","from":"Chicago Union Station","to":"West Hinsdale","ride":42,"wait":18,"freq":30}]},"west-pullman-1aef":{"m":119,"r":"X1|Red|352","x":2,"legs":[{"mode":"RAIL","line":"X1","from":"Ravinia","to":"Roosevelt","ride":51,"wait":7,"freq":30},{"mode":"SUBWAY","line":"Red","from":"Roosevelt","to":"95th/Dan Ryan","ride":23,"wait":4,"freq":3},{"mode":"BUS","line":"352","from":"95th/Dan Ryan","to":"West Pullman","ride":18,"wait":9,"freq":5}]},"western-blue-forest-park-branch-1bc4":{"m":87,"r":"X1|G|94","x":2,"legs":[{"mode":"RAIL","line":"X1","from":"Ravinia","to":"Clinton (Green/Pink)","ride":45,"wait":7,"freq":30},{"mode":"SUBWAY","line":"G","from":"Clinton (Green/Pink)","to":"California (Green)","ride":7,"wait":2,"freq":9},{"mode":"BUS","line":"94","from":"California (Green)","to":"Western (Blue - Forest Park Branch)","ride":2,"wait":1}]},"western-blue-o-hare-branch-1b8c":{"m":67,"r":"X1|73","x":1,"legs":[{"mode":"RAIL","line":"X1","from":"Ravinia","to":"Clybourn","ride":37,"wait":7,"freq":15},{"mode":"BUS","line":"73","from":"Clybourn","to":"Western (Blue - O'Hare Branch)","ride":7,"wait":3,"freq":12}]},"western-brown-1bc4":{"m":56,"r":"X1|Brn","x":1,"legs":[{"mode":"RAIL","line":"X1","from":"Ravinia","to":"Addison (Brown)","ride":34,"wait":7,"freq":30},{"mode":"SUBWAY","line":"Brn","from":"Addison (Brown)","to":"Western (Brown)","ride":6,"wait":2,"freq":30}]},"western-orange-1b1f":{"m":88,"r":"X1|Org","x":1,"legs":[{"mode":"RAIL","line":"X1","from":"Ravinia","to":"Roosevelt","ride":51,"wait":7,"freq":30},{"mode":"SUBWAY","line":"Org","from":"Roosevelt","to":"Western (Orange)","ride":13,"wait":7,"freq":30}]},"western-pink-1b42":{"m":78,"r":"X1|Pink","x":1,"legs":[{"mode":"RAIL","line":"X1","from":"Ravinia","to":"Clinton (Green/Pink)","ride":45,"wait":7,"freq":30},{"mode":"SUBWAY","line":"Pink","from":"Clinton (Green/Pink)","to":"Western (Pink)","ride":12,"wait":4}]},"western-ave-1b9c":{"m":76,"r":"X1|X5","x":1,"legs":[{"mode":"RAIL","line":"X1","from":"Ravinia","to":"Chicago Union Station","ride":47,"wait":7,"freq":30},{"mode":"RAIL","line":"X5","from":"Chicago Union Station","to":"Western Ave","ride":8,"wait":6,"freq":15}]},"western-avenue-1b9e":{"m":82,"r":"X1|Pink","x":1,"legs":[{"mode":"RAIL","line":"X1","from":"Ravinia","to":"Clinton (Green/Pink)","ride":45,"wait":7,"freq":30},{"mode":"SUBWAY","line":"Pink","from":"Clinton (Green/Pink)","to":"Western (Pink)","ride":12,"wait":4}]},"western-springs-1aed":{"m":112,"r":"X1|X5","x":1,"legs":[{"mode":"RAIL","line":"X1","from":"Ravinia","to":"Chicago Union Station","ride":47,"wait":7,"freq":30},{"mode":"RAIL","line":"X5","from":"Chicago Union Station","to":"Western Springs","ride":36,"wait":18,"freq":20}]},"western-logan-1c00":{"m":60,"r":"X1|X3","x":1,"legs":[{"mode":"RAIL","line":"X1","from":"Ravinia","to":"Clybourn","ride":37,"wait":7,"freq":15},{"mode":"RAIL","line":"X3","from":"Clybourn","to":"Western/Logan","ride":2,"wait":6,"freq":15}]},"westmont-1bcc":{"m":127,"r":"X1|X5","x":1,"legs":[{"mode":"RAIL","line":"X1","from":"Ravinia","to":"Chicago Union Station","ride":47,"wait":7,"freq":30},{"mode":"RAIL","line":"X5","from":"Chicago Union Station","to":"Westmont","ride":47,"wait":18,"freq":20}]},"wheeling-1b39":{"m":110,"r":"213|626|NCS","x":2,"legs":[{"mode":"BUS","line":"213","from":"Braeside","to":"Ravinia","ride":4,"wait":18,"freq":20},{"mode":"BUS","line":"626","from":"Ravinia Park","to":"Buffalo Grove","ride":35,"wait":14},{"mode":"RAIL","line":"NCS","from":"Buffalo Grove","to":"Wheeling","ride":6,"wait":6,"freq":60}]},"wilmette-1b29":{"m":28,"r":"X1|UP-N","x":1,"legs":[{"mode":"RAIL","line":"X1","from":"Braeside","to":"Highland Park","ride":6,"wait":4,"freq":20},{"mode":"RAIL","line":"UP-N","from":"Highland Park","to":"Wilmette","ride":13,"wait":2,"freq":9}]},"wilson-1bda":{"m":58,"r":"X1|81","x":1,"legs":[{"mode":"RAIL","line":"X1","from":"Ravinia","to":"Ravenswood","ride":32,"wait":7,"freq":15},{"mode":"BUS","line":"81","from":"Ravenswood","to":"Lawrence","ride":5,"wait":2,"freq":8}]},"windsor-park-1ba7":{"m":92,"r":"X1","x":0,"legs":[{"mode":"RAIL","line":"X1","from":"Ravinia","to":"Windsor Park","ride":77,"wait":7,"freq":30}]},"winnetka-1b26":{"m":23,"r":"X1|UP-N","x":1,"legs":[{"mode":"RAIL","line":"X1","from":"Braeside","to":"Highland Park","ride":6,"wait":4,"freq":20},{"mode":"RAIL","line":"UP-N","from":"Highland Park","to":"Winnetka","ride":9,"wait":2,"freq":9}]},"wood-dale-1b8d":{"m":121,"r":"X1|MD-W","x":1,"legs":[{"mode":"RAIL","line":"X1","from":"Ravinia","to":"Chicago Union Station","ride":47,"wait":7,"freq":30},{"mode":"RAIL","line":"MD-W","from":"Chicago Union Station","to":"Wood Dale","ride":37,"wait":21,"freq":60}]},"worth-1bd5":{"m":126,"r":"X1|SWS","x":1,"legs":[{"mode":"RAIL","line":"X1","from":"Ravinia","to":"Chicago Union Station","ride":47,"wait":7,"freq":30},{"mode":"RAIL","line":"SWS","from":"Chicago Union Station","to":"Worth","ride":38,"wait":33,"freq":60}]},"wrightwood-1b51":{"m":113,"r":"X1|SWS","x":1,"legs":[{"mode":"RAIL","line":"X1","from":"Ravinia","to":"Chicago Union Station","ride":47,"wait":7,"freq":30},{"mode":"RAIL","line":"SWS","from":"Chicago Union Station","to":"Wrightwood","ride":25,"wait":33,"freq":60}]},"zion-1b32":{"m":106,"r":"UP-N|571","x":1,"legs":[{"mode":"RAIL","line":"UP-N","from":"Braeside","to":"Waukegan","ride":34,"wait":9,"freq":60},{"mode":"BUS","line":"571","from":"Waukegan","to":"Zion","ride":15,"wait":4}]}}