[{"id":"103rd-st-rosemoor-1b20","name":"103rd St. (Rosemoor)","lat":41.7069,"lon":-87.6072,"on_metra":true,"on_cta_rail":false,"on_crosstowner":true,"on_rle":false,"exists_today":true,"wheelchair":0},{"id":"103rd-st-beverly-hills-1bbb","name":"103rd St. - Beverly Hills","lat":41.7061,"lon":-87.6689,"on_metra":true,"on_cta_rail":false,"on_crosstowner":true,"on_rle":false,"exists_today":true,"wheelchair":1},{"id":"103rd-st-washington-hts-1b8d","name":"103rd St.-Washington Hts.","lat":41.7056,"lon":-87.6558,"on_metra":true,"on_cta_rail":false,"on_crosstowner":false,"on_rle":false,"exists_today":true,"wheelchair":1},{"id":"103rd-street-1af9","name":"103rd Street","lat":41.7066,"lon":-87.6332,"on_metra":false,"on_cta_rail":false,"on_crosstowner":false,"on_rle":true,"exists_today":false},{"id":"107th-st-1bcc","name":"107th St.","lat":41.6997,"lon":-87.6089,"on_metra":true,"on_cta_rail":false,"on_crosstowner":true,"on_rle":false,"exists_today":true,"wheelchair":0},{"id":"107th-st-beverly-hills-1b2e","name":"107th St. - Beverly Hills","lat":41.6989,"lon":-87.67,"on_metra":true,"on_cta_rail":false,"on_crosstowner":true,"on_rle":false,"exists_today":true,"wheelchair":1},{"id":"111th-st-pullman-1b0f","name":"111th St. (Pullman)","lat":41.6928,"lon":-87.6106,"on_metra":true,"on_cta_rail":false,"on_crosstowner":true,"on_rle":false,"exists_today":true,"wheelchair":0},{"id":"111th-st-morgan-park-1b63","name":"111th St. - Morgan Park","lat":41.6928,"lon":-87.6706,"on_metra":true,"on_cta_rail":false,"on_crosstowner":true,"on_rle":false,"exists_today":true,"wheelchair":1},{"id":"111th-street-1b3d","name":"111th Street","lat":41.6924,"lon":-87.6327,"on_metra":false,"on_cta_rail":false,"on_crosstowner":false,"on_rle":true,"exists_today":false},{"id":"115th-st-morgan-park-1b57","name":"115th St. - Morgan Park","lat":41.685,"lon":-87.6717,"on_metra":true,"on_cta_rail":false,"on_crosstowner":true,"on_rle":false,"exists_today":true,"wheelchair":1},{"id":"119th-rlx-1b6d","name":"119th (RLX)","lat":41.6789,"lon":-87.6137,"on_metra":false,"on_cta_rail":false,"on_crosstowner":true,"on_rle":false,"exists_today":false},{"id":"119th-st-1b63","name":"119th St.","lat":41.6764,"lon":-87.6725,"on_metra":true,"on_cta_rail":false,"on_crosstowner":true,"on_rle":false,"exists_today":true,"wheelchair":1},{"id":"123rd-st-1b42","name":"123rd St.","lat":41.67,"lon":-87.6736,"on_metra":true,"on_cta_rail":false,"on_crosstowner":true,"on_rle":false,"exists_today":true,"wheelchair":0},{"id":"130th-street-1b9c","name":"130th Street","lat":41.6585,"lon":-87.5918,"on_metra":false,"on_cta_rail":false,"on_crosstowner":false,"on_rle":true,"exists_today":false},{"id":"130th-indiana-1ba2","name":"130th/Indiana","lat":41.6594,"lon":-87.6179,"on_metra":false,"on_cta_rail":false,"on_crosstowner":true,"on_rle":false,"exists_today":false},{"id":"147th-st-1b12","name":"147th St.","lat":41.6228,"lon":-87.6361,"on_metra":true,"on_cta_rail":false,"on_crosstowner":true,"on_rle":false,"exists_today":true,"wheelchair":0},{"id":"18th-1ba5","name":"18th","lat":41.8579,"lon":-87.6691,"on_metra":false,"on_cta_rail":true,"on_crosstowner":false,"on_rle":false,"exists_today":true,"wheelchair":1},{"id":"18th-st-1b2c","name":"18th St.","lat":41.8583,"lon":-87.6181,"on_metra":true,"on_cta_rail":false,"on_crosstowner":true,"on_rle":false,"exists_today":true,"wheelchair":0},{"id":"211th-st-1b7d","name":"211th St.","lat":41.5061,"lon":-87.6983,"on_metra":true,"on_cta_rail":false,"on_crosstowner":false,"on_rle":false,"exists_today":true,"wheelchair":1},{"id":"27th-st-1add","name":"27th St.","lat":41.8442,"lon":-87.6133,"on_metra":true,"on_cta_rail":false,"on_crosstowner":true,"on_rle":false,"exists_today":true,"wheelchair":0},{"id":"35th-st-lou-jones-1b2c","name":"35th St. - Lou Jones","lat":41.8314,"lon":-87.6292,"on_metra":true,"on_cta_rail":true,"on_crosstowner":true,"on_rle":false,"exists_today":true,"wheelchair":1},{"id":"35th-bronzeville-iit-1b65","name":"35th-Bronzeville-IIT","lat":41.8317,"lon":-87.6258,"on_metra":false,"on_cta_rail":true,"on_crosstowner":false,"on_rle":false,"exists_today":true,"wheelchair":1},{"id":"35th-archer-1b64","name":"35th/Archer","lat":41.8294,"lon":-87.6806,"on_metra":false,"on_cta_rail":true,"on_crosstowner":false,"on_rle":false,"exists_today":true,"wheelchair":1},{"id":"43rd-1b19","name":"43rd","lat":41.8165,"lon":-87.619,"on_metra":false,"on_cta_rail":true,"on_crosstowner":false,"on_rle":false,"exists_today":true,"wheelchair":1},{"id":"47th-green-1b82","name":"47th (Green)","lat":41.8092,"lon":-87.6188,"on_metra":false,"on_cta_rail":true,"on_crosstowner":false,"on_rle":false,"exists_today":true,"wheelchair":1},{"id":"47th-red-1b0c","name":"47th (Red)","lat":41.8103,"lon":-87.6309,"on_metra":false,"on_cta_rail":true,"on_crosstowner":false,"on_rle":false,"exists_today":true,"wheelchair":1},{"id":"47th-st-kenwood-1b5f","name":"47th St. (Kenwood)","lat":41.8097,"lon":-87.5914,"on_metra":true,"on_cta_rail":false,"on_crosstowner":true,"on_rle":false,"exists_today":true,"wheelchair":0},{"id":"51st-1b21","name":"51st","lat":41.8021,"lon":-87.6185,"on_metra":false,"on_cta_rail":true,"on_crosstowner":false,"on_rle":false,"exists_today":true,"wheelchair":1},{"id":"51st-53rd-st-hyde-park-1b85","name":"51st/53rd St. (Hyde Park)","lat":41.8,"lon":-87.5869,"on_metra":true,"on_cta_rail":false,"on_crosstowner":true,"on_rle":false,"exists_today":true,"wheelchair":1},{"id":"54th-cermak-1bac","name":"54th/Cermak","lat":41.8518,"lon":-87.7567,"on_metra":false,"on_cta_rail":true,"on_crosstowner":false,"on_rle":false,"exists_today":true,"wheelchair":1},{"id":"55th-56th-57th-st-1ba4","name":"55th - 56th - 57th St.","lat":41.7933,"lon":-87.5875,"on_metra":true,"on_cta_rail":false,"on_crosstowner":true,"on_rle":false,"exists_today":true,"wheelchair":1},{"id":"59th-st-u-of-chicago-1bce","name":"59th St. (U. of Chicago)","lat":41.7881,"lon":-87.5886,"on_metra":true,"on_cta_rail":false,"on_crosstowner":true,"on_rle":false,"exists_today":true,"wheelchair":0},{"id":"59th-perry-1b4a","name":"59th/Perry","lat":41.787,"lon":-87.6283,"on_metra":false,"on_cta_rail":false,"on_crosstowner":true,"on_rle":false,"exists_today":false},{"id":"63rd-1ab8","name":"63rd","lat":41.7805,"lon":-87.631,"on_metra":false,"on_cta_rail":true,"on_crosstowner":false,"on_rle":false,"exists_today":true,"wheelchair":1},{"id":"63rd-st-1b42","name":"63rd St.","lat":41.7803,"lon":-87.5906,"on_metra":true,"on_cta_rail":false,"on_crosstowner":true,"on_rle":false,"exists_today":true,"wheelchair":0},{"id":"67th-1b0d","name":"67th","lat":41.7733,"lon":-87.592,"on_metra":false,"on_cta_rail":false,"on_crosstowner":true,"on_rle":false,"exists_today":false},{"id":"69th-1b75","name":"69th","lat":41.7684,"lon":-87.6257,"on_metra":false,"on_cta_rail":true,"on_crosstowner":false,"on_rle":false,"exists_today":true,"wheelchair":1},{"id":"75th-st-grand-crossing-1ba8","name":"75th St. (Grand Crossing)","lat":41.7589,"lon":-87.5953,"on_metra":true,"on_cta_rail":false,"on_crosstowner":true,"on_rle":false,"exists_today":true,"wheelchair":0},{"id":"79th-1ae0","name":"79th","lat":41.7504,"lon":-87.6251,"on_metra":false,"on_cta_rail":true,"on_crosstowner":false,"on_rle":false,"exists_today":true,"wheelchair":1},{"id":"79th-auburn-park-1b76","name":"79th (Auburn Park)","lat":41.7508,"lon":-87.6394,"on_metra":false,"on_cta_rail":false,"on_crosstowner":true,"on_rle":false,"exists_today":false},{"id":"79th-st-chatham-1b7f","name":"79th St. (Chatham)","lat":41.7508,"lon":-87.5972,"on_metra":true,"on_cta_rail":false,"on_crosstowner":true,"on_rle":false,"exists_today":true,"wheelchair":1},{"id":"83rd-st-1b1e","name":"83rd St.","lat":41.745,"lon":-87.5517,"on_metra":true,"on_cta_rail":false,"on_crosstowner":true,"on_rle":false,"exists_today":true,"wheelchair":1},{"id":"83rd-st-avalon-park-1bb7","name":"83rd St. (Avalon Park)","lat":41.7442,"lon":-87.5986,"on_metra":true,"on_cta_rail":false,"on_crosstowner":true,"on_rle":false,"exists_today":true,"wheelchair":0},{"id":"87th-1b45","name":"87th","lat":41.7354,"lon":-87.6247,"on_metra":false,"on_cta_rail":true,"on_crosstowner":false,"on_rle":false,"exists_today":true,"wheelchair":1},{"id":"87th-st-1b78","name":"87th St.","lat":41.7378,"lon":-87.5483,"on_metra":true,"on_cta_rail":false,"on_crosstowner":true,"on_rle":false,"exists_today":true,"wheelchair":1},{"id":"87th-st-woodruff-1ad6","name":"87th St. (Woodruff)","lat":41.7369,"lon":-87.6003,"on_metra":true,"on_cta_rail":false,"on_crosstowner":true,"on_rle":false,"exists_today":true,"wheelchair":0},{"id":"91st-st-1b2f","name":"91st St.","lat":41.7294,"lon":-87.6019,"on_metra":true,"on_cta_rail":false,"on_crosstowner":true,"on_rle":false,"exists_today":true,"wheelchair":0},{"id":"91st-st-beverly-hills-1b52","name":"91st St. - Beverly Hills","lat":41.7281,"lon":-87.6672,"on_metra":true,"on_cta_rail":false,"on_crosstowner":true,"on_rle":false,"exists_today":true,"wheelchair":1},{"id":"95th-st-1b40","name":"95th St.","lat":41.7219,"lon":-87.6039,"on_metra":true,"on_cta_rail":false,"on_crosstowner":true,"on_rle":false,"exists_today":true,"wheelchair":0},{"id":"95th-st-beverly-hills-1b3d","name":"95th St. - Beverly Hills","lat":41.7214,"lon":-87.6672,"on_metra":true,"on_cta_rail":false,"on_crosstowner":true,"on_rle":false,"exists_today":true,"wheelchair":1},{"id":"95th-st-longwood-1ac1","name":"95th St.-Longwood","lat":41.7211,"lon":-87.6503,"on_metra":true,"on_cta_rail":false,"on_crosstowner":false,"on_rle":false,"exists_today":true,"wheelchair":1},{"id":"95th-dan-ryan-1aee","name":"95th/Dan Ryan","lat":41.7224,"lon":-87.6243,"on_metra":false,"on_cta_rail":true,"on_crosstowner":false,"on_rle":true,"exists_today":true,"wheelchair":1},{"id":"99th-st-beverly-hills-1b82","name":"99th St. - Beverly Hills","lat":41.7136,"lon":-87.6675,"on_metra":true,"on_cta_rail":false,"on_crosstowner":true,"on_rle":false,"exists_today":true,"wheelchair":1},{"id":"adams-wabash-1b2a","name":"Adams/Wabash","lat":41.8795,"lon":-87.626,"on_metra":false,"on_cta_rail":true,"on_crosstowner":false,"on_rle":false,"exists_today":true,"wheelchair":0},{"id":"addison-blue-1b81","name":"Addison (Blue)","lat":41.9466,"lon":-87.7185,"on_metra":false,"on_cta_rail":true,"on_crosstowner":false,"on_rle":false,"exists_today":true,"wheelchair":1},{"id":"addison-brown-1b78","name":"Addison (Brown)","lat":41.947,"lon":-87.6746,"on_metra":false,"on_cta_rail":true,"on_crosstowner":true,"on_rle":false,"exists_today":true,"wheelchair":1},{"id":"addison-red-1b62","name":"Addison (Red)","lat":41.9473,"lon":-87.6536,"on_metra":false,"on_cta_rail":true,"on_crosstowner":false,"on_rle":false,"exists_today":true,"wheelchair":1},{"id":"antioch-1b08","name":"Antioch","lat":42.4811,"lon":-88.0925,"on_metra":true,"on_cta_rail":false,"on_crosstowner":false,"on_rle":false,"exists_today":true,"wheelchair":1},{"id":"argyle-1b94","name":"Argyle","lat":41.9733,"lon":-87.6585,"on_metra":false,"on_cta_rail":true,"on_crosstowner":false,"on_rle":false,"exists_today":true,"wheelchair":1},{"id":"arlington-heights-1b8c","name":"Arlington Heights","lat":42.0842,"lon":-87.9836,"on_metra":true,"on_cta_rail":false,"on_crosstowner":true,"on_rle":false,"exists_today":true,"wheelchair":1},{"id":"arlington-park-1ade","name":"Arlington Park","lat":42.0953,"lon":-88.0092,"on_metra":true,"on_cta_rail":false,"on_crosstowner":true,"on_rle":false,"exists_today":true,"wheelchair":1},{"id":"armitage-brown-purple-1b43","name":"Armitage (Brown/Purple)","lat":41.9182,"lon":-87.6526,"on_metra":false,"on_cta_rail":true,"on_crosstowner":false,"on_rle":false,"exists_today":true,"wheelchair":1},{"id":"ashburn-1b08","name":"Ashburn","lat":41.7417,"lon":-87.7125,"on_metra":true,"on_cta_rail":false,"on_crosstowner":false,"on_rle":false,"exists_today":true,"wheelchair":1},{"id":"ashland-1b54","name":"Ashland","lat":41.6694,"lon":-87.6606,"on_metra":true,"on_cta_rail":false,"on_crosstowner":true,"on_rle":false,"exists_today":true,"wheelchair":0},{"id":"ashland-green-pink-1b50","name":"Ashland (Green/Pink)","lat":41.8853,"lon":-87.667,"on_metra":false,"on_cta_rail":true,"on_crosstowner":false,"on_rle":false,"exists_today":true,"wheelchair":1},{"id":"ashland-orange-1b5a","name":"Ashland (Orange)","lat":41.8392,"lon":-87.6653,"on_metra":false,"on_cta_rail":true,"on_crosstowner":false,"on_rle":false,"exists_today":true,"wheelchair":1},{"id":"ashland-ogden-1bd0","name":"Ashland-Ogden","lat":41.8887,"lon":-87.6657,"on_metra":false,"on_cta_rail":false,"on_crosstowner":true,"on_rle":false,"exists_today":false},{"id":"ashland-63rd-1bc7","name":"Ashland/63rd","lat":41.7789,"lon":-87.6638,"on_metra":false,"on_cta_rail":true,"on_crosstowner":false,"on_rle":false,"exists_today":true,"wheelchair":1},{"id":"aurora-1b16","name":"Aurora","lat":41.7608,"lon":-88.3083,"on_metra":true,"on_cta_rail":false,"on_crosstowner":false,"on_rle":false,"exists_today":true,"wheelchair":1},{"id":"austin-blue-1be3","name":"Austin (Blue)","lat":41.8709,"lon":-87.7768,"on_metra":false,"on_cta_rail":true,"on_crosstowner":false,"on_rle":false,"exists_today":true,"wheelchair":0},{"id":"austin-green-1b5a","name":"Austin (Green)","lat":41.8873,"lon":-87.7741,"on_metra":false,"on_cta_rail":true,"on_crosstowner":false,"on_rle":false,"exists_today":true,"wheelchair":0},{"id":"barrington-1b0e","name":"Barrington","lat":42.1528,"lon":-88.1319,"on_metra":true,"on_cta_rail":false,"on_crosstowner":false,"on_rle":false,"exists_today":true,"wheelchair":1},{"id":"bartlett-1b7a","name":"Bartlett","lat":41.9922,"lon":-88.1839,"on_metra":true,"on_cta_rail":false,"on_crosstowner":false,"on_rle":false,"exists_today":true,"wheelchair":1},{"id":"bellwood-1b7f","name":"Bellwood","lat":41.8914,"lon":-87.8825,"on_metra":true,"on_cta_rail":false,"on_crosstowner":true,"on_rle":false,"exists_today":true,"wheelchair":1},{"id":"belmont-1b03","name":"Belmont","lat":41.7953,"lon":-88.0381,"on_metra":true,"on_cta_rail":false,"on_crosstowner":false,"on_rle":false,"exists_today":true,"wheelchair":1},{"id":"belmont-blue-1af1","name":"Belmont (Blue)","lat":41.9391,"lon":-87.7123,"on_metra":false,"on_cta_rail":true,"on_crosstowner":false,"on_rle":false,"exists_today":true,"wheelchair":0},{"id":"belmont-red-brown-purple-1b6c","name":"Belmont (Red/Brown/Purple)","lat":41.9398,"lon":-87.6534,"on_metra":false,"on_cta_rail":true,"on_crosstowner":false,"on_rle":false,"exists_today":true,"wheelchair":1},{"id":"belmont-kedzie-1b51","name":"Belmont/Kedzie","lat":41.9396,"lon":-87.7073,"on_metra":false,"on_cta_rail":false,"on_crosstowner":true,"on_rle":false,"exists_today":false},{"id":"bensenville-1bb6","name":"Bensenville","lat":41.9569,"lon":-87.9419,"on_metra":true,"on_cta_rail":false,"on_crosstowner":false,"on_rle":false,"exists_today":true,"wheelchair":1},{"id":"berkeley-1b40","name":"Berkeley","lat":41.8961,"lon":-87.9153,"on_metra":true,"on_cta_rail":false,"on_crosstowner":true,"on_rle":false,"exists_today":true,"wheelchair":1},{"id":"berwyn-1b78","name":"Berwyn","lat":41.8331,"lon":-87.7936,"on_metra":true,"on_cta_rail":false,"on_crosstowner":true,"on_rle":false,"exists_today":true,"wheelchair":1},{"id":"berwyn-1bbd","name":"Berwyn","lat":41.978,"lon":-87.6587,"on_metra":false,"on_cta_rail":true,"on_crosstowner":false,"on_rle":false,"exists_today":true,"wheelchair":1},{"id":"big-timber-1b76","name":"Big Timber","lat":42.0586,"lon":-88.3278,"on_metra":true,"on_cta_rail":false,"on_crosstowner":false,"on_rle":false,"exists_today":true,"wheelchair":1},{"id":"blue-island-1ba1","name":"Blue Island","lat":41.6561,"lon":-87.6758,"on_metra":true,"on_cta_rail":false,"on_crosstowner":false,"on_rle":false,"exists_today":true,"wheelchair":1},{"id":"blue-island-vermont-1bdd","name":"Blue Island-Vermont","lat":41.6547,"lon":-87.6778,"on_metra":true,"on_cta_rail":false,"on_crosstowner":true,"on_rle":false,"exists_today":true,"wheelchair":1},{"id":"braeside-1b58","name":"Braeside","lat":42.1528,"lon":-87.7725,"on_metra":true,"on_cta_rail":false,"on_crosstowner":true,"on_rle":false,"exists_today":true,"wheelchair":1},{"id":"brainerd-1bab","name":"Brainerd","lat":41.7322,"lon":-87.6589,"on_metra":true,"on_cta_rail":false,"on_crosstowner":true,"on_rle":false,"exists_today":true,"wheelchair":1},{"id":"brookfield-1b16","name":"Brookfield","lat":41.8219,"lon":-87.8431,"on_metra":true,"on_cta_rail":false,"on_crosstowner":false,"on_rle":false,"exists_today":true,"wheelchair":1},{"id":"bryn-mawr-1b9c","name":"Bryn Mawr","lat":41.7661,"lon":-87.5767,"on_metra":true,"on_cta_rail":false,"on_crosstowner":true,"on_rle":false,"exists_today":true,"wheelchair":1},{"id":"bryn-mawr-1bd7","name":"Bryn Mawr","lat":41.9835,"lon":-87.6588,"on_metra":false,"on_cta_rail":true,"on_crosstowner":false,"on_rle":false,"exists_today":true,"wheelchair":1},{"id":"buffalo-grove-1b44","name":"Buffalo Grove","lat":42.1686,"lon":-87.9414,"on_metra":true,"on_cta_rail":false,"on_crosstowner":false,"on_rle":false,"exists_today":true,"wheelchair":1},{"id":"burr-oak-1bc4","name":"Burr Oak","lat":41.6622,"lon":-87.6689,"on_metra":true,"on_cta_rail":false,"on_crosstowner":true,"on_rle":false,"exists_today":true,"wheelchair":0},{"id":"california-blue-1b67","name":"California (Blue)","lat":41.9222,"lon":-87.6972,"on_metra":false,"on_cta_rail":true,"on_crosstowner":false,"on_rle":false,"exists_today":true,"wheelchair":0},{"id":"california-green-1b7e","name":"California (Green)","lat":41.8842,"lon":-87.6962,"on_metra":false,"on_cta_rail":true,"on_crosstowner":false,"on_rle":false,"exists_today":true,"wheelchair":1},{"id":"california-pink-1baa","name":"California (Pink)","lat":41.8541,"lon":-87.6948,"on_metra":false,"on_cta_rail":true,"on_crosstowner":false,"on_rle":false,"exists_today":true,"wheelchair":1},{"id":"calumet-1b4d","name":"Calumet","lat":41.5736,"lon":-87.6625,"on_metra":true,"on_cta_rail":false,"on_crosstowner":false,"on_rle":false,"exists_today":true,"wheelchair":1},{"id":"cary-1aef","name":"Cary","lat":42.2089,"lon":-88.2414,"on_metra":true,"on_cta_rail":false,"on_crosstowner":false,"on_rle":false,"exists_today":true,"wheelchair":1},{"id":"central-green-1bb2","name":"Central (Green)","lat":41.8874,"lon":-87.7656,"on_metra":false,"on_cta_rail":true,"on_crosstowner":false,"on_rle":false,"exists_today":true,"wheelchair":1},{"id":"central-purple-1b6b","name":"Central (Purple)","lat":42.064,"lon":-87.6856,"on_metra":false,"on_cta_rail":true,"on_crosstowner":false,"on_rle":false,"exists_today":true,"wheelchair":0},{"id":"central-park-1b72","name":"Central Park","lat":41.8538,"lon":-87.7148,"on_metra":false,"on_cta_rail":true,"on_crosstowner":false,"on_rle":false,"exists_today":true,"wheelchair":1},{"id":"central-st-1b64","name":"Central St.","lat":42.0642,"lon":-87.6981,"on_metra":true,"on_cta_rail":false,"on_crosstowner":true,"on_rle":false,"exists_today":true,"wheelchair":1},{"id":"cermak-chinatown-1aaa","name":"Cermak-Chinatown","lat":41.8532,"lon":-87.631,"on_metra":false,"on_cta_rail":true,"on_crosstowner":false,"on_rle":false,"exists_today":true,"wheelchair":1},{"id":"cermak-mccormick-place-1b20","name":"Cermak-McCormick Place","lat":41.8531,"lon":-87.6264,"on_metra":false,"on_cta_rail":true,"on_crosstowner":false,"on_rle":false,"exists_today":true,"wheelchair":1},{"id":"cheltenham-79th-st-1b0e","name":"Cheltenham (79th St.)","lat":41.7522,"lon":-87.5525,"on_metra":true,"on_cta_rail":false,"on_crosstowner":true,"on_rle":false,"exists_today":true,"wheelchair":1},{"id":"chicago-blue-1b41","name":"Chicago (Blue)","lat":41.8961,"lon":-87.6552,"on_metra":false,"on_cta_rail":true,"on_crosstowner":false,"on_rle":false,"exists_today":true,"wheelchair":0},{"id":"chicago-brown-purple-1bc6","name":"Chicago (Brown/Purple)","lat":41.8968,"lon":-87.6359,"on_metra":false,"on_cta_rail":true,"on_crosstowner":false,"on_rle":false,"exists_today":true,"wheelchair":1},{"id":"chicago-red-1b6e","name":"Chicago (Red)","lat":41.8967,"lon":-87.6282,"on_metra":false,"on_cta_rail":true,"on_crosstowner":false,"on_rle":false,"exists_today":true,"wheelchair":1},{"id":"chicago-otc-1b12","name":"Chicago OTC","lat":41.8822,"lon":-87.6406,"on_metra":true,"on_cta_rail":false,"on_crosstowner":false,"on_rle":false,"exists_today":true,"wheelchair":1},{"id":"chicago-ridge-1b08","name":"Chicago Ridge","lat":41.7033,"lon":-87.7803,"on_metra":true,"on_cta_rail":false,"on_crosstowner":false,"on_rle":false,"exists_today":true,"wheelchair":1},{"id":"chicago-union-station-1bfc","name":"Chicago Union Station","lat":41.8789,"lon":-87.6389,"on_metra":true,"on_cta_rail":false,"on_crosstowner":true,"on_rle":false,"exists_today":true,"wheelchair":1},{"id":"chicago-halsted-bally-s-1b9c","name":"Chicago/Halsted (Bally's)","lat":41.8958,"lon":-87.6474,"on_metra":false,"on_cta_rail":false,"on_crosstowner":true,"on_rle":false,"exists_today":false},{"id":"cicero-1b62","name":"Cicero","lat":41.8442,"lon":-87.7456,"on_metra":true,"on_cta_rail":false,"on_crosstowner":true,"on_rle":false,"exists_today":true,"wheelchair":0},{"id":"cicero-blue-1b3b","name":"Cicero (Blue)","lat":41.8716,"lon":-87.7452,"on_metra":false,"on_cta_rail":true,"on_crosstowner":false,"on_rle":false,"exists_today":true,"wheelchair":0},{"id":"cicero-green-1b98","name":"Cicero (Green)","lat":41.8865,"lon":-87.7447,"on_metra":false,"on_cta_rail":true,"on_crosstowner":true,"on_rle":false,"exists_today":true,"wheelchair":1},{"id":"cicero-pink-1b4f","name":"Cicero (Pink)","lat":41.8518,"lon":-87.7453,"on_metra":false,"on_cta_rail":true,"on_crosstowner":false,"on_rle":false,"exists_today":true,"wheelchair":1},{"id":"clarendon-hills-1bbe","name":"Clarendon Hills","lat":41.7969,"lon":-87.9536,"on_metra":true,"on_cta_rail":false,"on_crosstowner":true,"on_rle":false,"exists_today":true,"wheelchair":1},{"id":"clark-division-1b06","name":"Clark/Division","lat":41.9039,"lon":-87.6314,"on_metra":false,"on_cta_rail":true,"on_crosstowner":false,"on_rle":false,"exists_today":true,"wheelchair":1},{"id":"clark-lake-1b69","name":"Clark/Lake","lat":41.8857,"lon":-87.6309,"on_metra":false,"on_cta_rail":true,"on_crosstowner":false,"on_rle":false,"exists_today":true,"wheelchair":1},{"id":"clinton-blue-1ae3","name":"Clinton (Blue)","lat":41.8755,"lon":-87.641,"on_metra":false,"on_cta_rail":true,"on_crosstowner":false,"on_rle":false,"exists_today":true,"wheelchair":0},{"id":"clinton-green-pink-1b76","name":"Clinton (Green/Pink)","lat":41.8857,"lon":-87.6418,"on_metra":false,"on_cta_rail":true,"on_crosstowner":true,"on_rle":false,"exists_today":true,"wheelchair":1},{"id":"clybourn-1b80","name":"Clybourn","lat":41.9169,"lon":-87.6681,"on_metra":true,"on_cta_rail":false,"on_crosstowner":true,"on_rle":false,"exists_today":true,"wheelchair":0},{"id":"college-ave-1b06","name":"College Ave","lat":41.8683,"lon":-88.0903,"on_metra":true,"on_cta_rail":false,"on_crosstowner":false,"on_rle":false,"exists_today":true,"wheelchair":1},{"id":"congress-park-1bc5","name":"Congress Park","lat":41.8189,"lon":-87.8575,"on_metra":true,"on_cta_rail":false,"on_crosstowner":true,"on_rle":false,"exists_today":true,"wheelchair":0},{"id":"conservatory-central-park-drive-1b7c","name":"Conservatory-Central Park Drive","lat":41.8849,"lon":-87.7165,"on_metra":false,"on_cta_rail":true,"on_crosstowner":false,"on_rle":false,"exists_today":true,"wheelchair":1},{"id":"cottage-grove-1b4c","name":"Cottage Grove","lat":41.7803,"lon":-87.6059,"on_metra":false,"on_cta_rail":true,"on_crosstowner":false,"on_rle":false,"exists_today":true,"wheelchair":1},{"id":"crystal-lake-1ad7","name":"Crystal Lake","lat":42.2442,"lon":-88.3172,"on_metra":true,"on_cta_rail":false,"on_crosstowner":false,"on_rle":false,"exists_today":true,"wheelchair":1},{"id":"cumberland-1ad5","name":"Cumberland","lat":42.0525,"lon":-87.9122,"on_metra":true,"on_cta_rail":false,"on_crosstowner":true,"on_rle":false,"exists_today":true,"wheelchair":0},{"id":"cumberland-1b46","name":"Cumberland","lat":41.9842,"lon":-87.838,"on_metra":false,"on_cta_rail":true,"on_crosstowner":false,"on_rle":false,"exists_today":true,"wheelchair":1},{"id":"damen-blue-1bc5","name":"Damen (Blue)","lat":41.9098,"lon":-87.6775,"on_metra":false,"on_cta_rail":true,"on_crosstowner":false,"on_rle":false,"exists_today":true,"wheelchair":0},{"id":"damen-brown-1bcd","name":"Damen (Brown)","lat":41.9663,"lon":-87.6786,"on_metra":false,"on_cta_rail":true,"on_crosstowner":false,"on_rle":false,"exists_today":true,"wheelchair":1},{"id":"damen-green-1bca","name":"Damen (Green)","lat":41.885,"lon":-87.6769,"on_metra":false,"on_cta_rail":true,"on_crosstowner":false,"on_rle":false,"exists_today":true,"wheelchair":1},{"id":"damen-pink-1b48","name":"Damen (Pink)","lat":41.8545,"lon":-87.676,"on_metra":false,"on_cta_rail":true,"on_crosstowner":false,"on_rle":false,"exists_today":true,"wheelchair":1},{"id":"dee-road-1b14","name":"Dee Road","lat":42.0242,"lon":-87.8561,"on_metra":true,"on_cta_rail":false,"on_crosstowner":true,"on_rle":false,"exists_today":true,"wheelchair":1},{"id":"deerfield-1ad3","name":"Deerfield","lat":42.1681,"lon":-87.85,"on_metra":true,"on_cta_rail":false,"on_crosstowner":false,"on_rle":false,"exists_today":true,"wheelchair":1},{"id":"dempster-1b44","name":"Dempster","lat":42.0417,"lon":-87.6816,"on_metra":false,"on_cta_rail":true,"on_crosstowner":false,"on_rle":false,"exists_today":true,"wheelchair":0},{"id":"dempster-skokie-1b51","name":"Dempster-Skokie","lat":42.039,"lon":-87.7519,"on_metra":false,"on_cta_rail":true,"on_crosstowner":false,"on_rle":false,"exists_today":true,"wheelchair":1},{"id":"des-plaines-1bba","name":"Des Plaines","lat":42.0408,"lon":-87.8867,"on_metra":true,"on_cta_rail":false,"on_crosstowner":true,"on_rle":false,"exists_today":true,"wheelchair":1},{"id":"des-plaines-river-rd-1bb2","name":"Des Plaines River Rd","lat":41.9334,"lon":-87.8496,"on_metra":false,"on_cta_rail":false,"on_crosstowner":true,"on_rle":false,"exists_today":false},{"id":"diversey-brown-purple-1b0b","name":"Diversey (Brown/Purple)","lat":41.9327,"lon":-87.6531,"on_metra":false,"on_cta_rail":true,"on_crosstowner":false,"on_rle":false,"exists_today":true,"wheelchair":1},{"id":"division-1b68","name":"Division","lat":41.9034,"lon":-87.6665,"on_metra":false,"on_cta_rail":true,"on_crosstowner":false,"on_rle":false,"exists_today":true,"wheelchair":0},{"id":"division-elston-1aee","name":"Division/Elston","lat":41.9034,"lon":-87.6603,"on_metra":false,"on_cta_rail":false,"on_crosstowner":true,"on_rle":false,"exists_today":false},{"id":"downers-grove-1b48","name":"Downers Grove","lat":41.7953,"lon":-88.0097,"on_metra":true,"on_cta_rail":false,"on_crosstowner":true,"on_rle":false,"exists_today":true,"wheelchair":1},{"id":"edgebrook-1bd7","name":"Edgebrook","lat":41.9978,"lon":-87.7656,"on_metra":true,"on_cta_rail":false,"on_crosstowner":false,"on_rle":false,"exists_today":true,"wheelchair":1},{"id":"edison-park-1b15","name":"Edison Park","lat":42.0022,"lon":-87.8175,"on_metra":true,"on_cta_rail":false,"on_crosstowner":true,"on_rle":false,"exists_today":true,"wheelchair":1},{"id":"elburn-1b91","name":"Elburn","lat":41.8906,"lon":-88.4639,"on_metra":true,"on_cta_rail":false,"on_crosstowner":false,"on_rle":false,"exists_today":true,"wheelchair":1},{"id":"elgin-1b05","name":"Elgin","lat":42.0361,"lon":-88.2861,"on_metra":true,"on_cta_rail":false,"on_crosstowner":false,"on_rle":false,"exists_today":true,"wheelchair":1},{"id":"elmhurst-1bab","name":"Elmhurst","lat":41.8997,"lon":-87.9408,"on_metra":true,"on_cta_rail":false,"on_crosstowner":true,"on_rle":false,"exists_today":true,"wheelchair":1},{"id":"elmwood-park-1b63","name":"Elmwood Park","lat":41.9247,"lon":-87.8147,"on_metra":true,"on_cta_rail":false,"on_crosstowner":false,"on_rle":false,"exists_today":true,"wheelchair":1},{"id":"elmwood-park-conti-cir-1ad3","name":"Elmwood Park - Conti Cir","lat":41.9265,"lon":-87.8201,"on_metra":false,"on_cta_rail":false,"on_crosstowner":true,"on_rle":false,"exists_today":false},{"id":"evanston-davis-st-1b81","name":"Evanston (Davis St.)","lat":42.0481,"lon":-87.6847,"on_metra":true,"on_cta_rail":true,"on_crosstowner":true,"on_rle":false,"exists_today":true,"wheelchair":1},{"id":"fairview-ave-1bc6","name":"Fairview Ave.","lat":41.7953,"lon":-87.9936,"on_metra":true,"on_cta_rail":false,"on_crosstowner":true,"on_rle":false,"exists_today":true,"wheelchair":1},{"id":"flossmoor-1b93","name":"Flossmoor","lat":41.5431,"lon":-87.6786,"on_metra":true,"on_cta_rail":false,"on_crosstowner":false,"on_rle":false,"exists_today":true,"wheelchair":1},{"id":"forest-glen-1b94","name":"Forest Glen","lat":41.9781,"lon":-87.7556,"on_metra":true,"on_cta_rail":false,"on_crosstowner":false,"on_rle":false,"exists_today":true,"wheelchair":0},{"id":"forest-park-1b49","name":"Forest Park","lat":41.8743,"lon":-87.8173,"on_metra":false,"on_cta_rail":true,"on_crosstowner":false,"on_rle":false,"exists_today":true,"wheelchair":1},{"id":"fort-sheridan-1b2a","name":"Fort Sheridan","lat":42.2175,"lon":-87.8208,"on_metra":true,"on_cta_rail":false,"on_crosstowner":false,"on_rle":false,"exists_today":true,"wheelchair":1},{"id":"foster-1b56","name":"Foster","lat":42.0542,"lon":-87.6836,"on_metra":false,"on_cta_rail":true,"on_crosstowner":false,"on_rle":false,"exists_today":true,"wheelchair":0},{"id":"fox-lake-1b10","name":"Fox Lake","lat":42.3983,"lon":-88.1822,"on_metra":true,"on_cta_rail":false,"on_crosstowner":false,"on_rle":false,"exists_today":true,"wheelchair":1},{"id":"fox-river-grove-1b59","name":"Fox River Grove","lat":42.1978,"lon":-88.2194,"on_metra":true,"on_cta_rail":false,"on_crosstowner":false,"on_rle":false,"exists_today":true,"wheelchair":1},{"id":"francisco-1afa","name":"Francisco","lat":41.966,"lon":-87.7016,"on_metra":false,"on_cta_rail":true,"on_crosstowner":false,"on_rle":false,"exists_today":true,"wheelchair":1},{"id":"franklin-park-1ba8","name":"Franklin Park","lat":41.9367,"lon":-87.8664,"on_metra":true,"on_cta_rail":false,"on_crosstowner":false,"on_rle":false,"exists_today":true,"wheelchair":1},{"id":"franklin-pk-1b1b","name":"Franklin Pk","lat":41.9378,"lon":-87.86,"on_metra":true,"on_cta_rail":false,"on_crosstowner":true,"on_rle":false,"exists_today":true,"wheelchair":1},{"id":"fullerton-1b6d","name":"Fullerton","lat":41.9253,"lon":-87.6529,"on_metra":false,"on_cta_rail":true,"on_crosstowner":false,"on_rle":false,"exists_today":true,"wheelchair":1},{"id":"galewood-1bc9","name":"Galewood","lat":41.9164,"lon":-87.7858,"on_metra":true,"on_cta_rail":false,"on_crosstowner":true,"on_rle":false,"exists_today":true,"wheelchair":1},{"id":"garfield-green-1b43","name":"Garfield (Green)","lat":41.7952,"lon":-87.6183,"on_metra":false,"on_cta_rail":true,"on_crosstowner":false,"on_rle":false,"exists_today":true,"wheelchair":1},{"id":"garfield-red-1af4","name":"Garfield (Red)","lat":41.7954,"lon":-87.6312,"on_metra":false,"on_cta_rail":true,"on_crosstowner":false,"on_rle":false,"exists_today":true,"wheelchair":1},{"id":"geneva-1a89","name":"Geneva","lat":41.8817,"lon":-88.31,"on_metra":true,"on_cta_rail":false,"on_crosstowner":false,"on_rle":false,"exists_today":true,"wheelchair":1},{"id":"gladstone-park-1bbd","name":"Gladstone Park","lat":41.9797,"lon":-87.7781,"on_metra":true,"on_cta_rail":false,"on_crosstowner":true,"on_rle":false,"exists_today":true,"wheelchair":0},{"id":"glen-ellyn-1b6d","name":"Glen Ellyn","lat":41.8767,"lon":-88.0647,"on_metra":true,"on_cta_rail":false,"on_crosstowner":false,"on_rle":false,"exists_today":true,"wheelchair":1},{"id":"glen-n-glenview-1b87","name":"Glen/N. Glenview","lat":42.0975,"lon":-87.8158,"on_metra":true,"on_cta_rail":false,"on_crosstowner":false,"on_rle":false,"exists_today":true,"wheelchair":1},{"id":"glencoe-1b50","name":"Glencoe","lat":42.1356,"lon":-87.7581,"on_metra":true,"on_cta_rail":false,"on_crosstowner":true,"on_rle":false,"exists_today":true,"wheelchair":1},{"id":"glenview-1b20","name":"Glenview","lat":42.075,"lon":-87.8056,"on_metra":true,"on_cta_rail":false,"on_crosstowner":false,"on_rle":false,"exists_today":true,"wheelchair":1},{"id":"golf-1bed","name":"Golf","lat":42.0583,"lon":-87.7969,"on_metra":true,"on_cta_rail":false,"on_crosstowner":false,"on_rle":false,"exists_today":true,"wheelchair":1},{"id":"grand-blue-1b7a","name":"Grand (Blue)","lat":41.8912,"lon":-87.6476,"on_metra":false,"on_cta_rail":true,"on_crosstowner":false,"on_rle":false,"exists_today":true,"wheelchair":0},{"id":"grand-red-1b30","name":"Grand (Red)","lat":41.8917,"lon":-87.628,"on_metra":false,"on_cta_rail":true,"on_crosstowner":false,"on_rle":false,"exists_today":true,"wheelchair":1},{"id":"grand-cicero-1b24","name":"Grand/Cicero","lat":41.9144,"lon":-87.7461,"on_metra":true,"on_cta_rail":false,"on_crosstowner":true,"on_rle":false,"exists_today":true,"wheelchair":0},{"id":"grand-harlem-1b75","name":"Grand/Harlem","lat":41.9236,"lon":-87.8077,"on_metra":false,"on_cta_rail":false,"on_crosstowner":true,"on_rle":false,"exists_today":false},{"id":"granville-1b91","name":"Granville","lat":41.9945,"lon":-87.6592,"on_metra":false,"on_cta_rail":true,"on_crosstowner":false,"on_rle":false,"exists_today":true,"wheelchair":1},{"id":"grayland-1b34","name":"Grayland","lat":41.9489,"lon":-87.7403,"on_metra":true,"on_cta_rail":false,"on_crosstowner":false,"on_rle":false,"exists_today":true,"wheelchair":0},{"id":"grayslake-1ac3","name":"Grayslake","lat":42.3336,"lon":-88.0433,"on_metra":true,"on_cta_rail":false,"on_crosstowner":false,"on_rle":false,"exists_today":true,"wheelchair":1},{"id":"great-lakes-1b75","name":"Great Lakes","lat":42.3069,"lon":-87.8464,"on_metra":true,"on_cta_rail":false,"on_crosstowner":false,"on_rle":false,"exists_today":true,"wheelchair":1},{"id":"gresham-1b67","name":"Gresham","lat":41.7364,"lon":-87.6447,"on_metra":true,"on_cta_rail":false,"on_crosstowner":true,"on_rle":false,"exists_today":true,"wheelchair":0},{"id":"halsted-green-1b5a","name":"Halsted (Green)","lat":41.7789,"lon":-87.6442,"on_metra":false,"on_cta_rail":true,"on_crosstowner":false,"on_rle":false,"exists_today":true,"wheelchair":1},{"id":"halsted-orange-1b68","name":"Halsted (Orange)","lat":41.8468,"lon":-87.6481,"on_metra":false,"on_cta_rail":true,"on_crosstowner":false,"on_rle":false,"exists_today":true,"wheelchair":1},{"id":"halsted-street-1b2c","name":"Halsted Street","lat":41.8603,"lon":-87.6472,"on_metra":true,"on_cta_rail":false,"on_crosstowner":true,"on_rle":false,"exists_today":true,"wheelchair":0},{"id":"hanover-park-1b44","name":"Hanover Park","lat":41.9881,"lon":-88.1492,"on_metra":true,"on_cta_rail":false,"on_crosstowner":false,"on_rle":false,"exists_today":true,"wheelchair":1},{"id":"hanson-park-1be1","name":"Hanson Park","lat":41.9167,"lon":-87.7669,"on_metra":true,"on_cta_rail":false,"on_crosstowner":true,"on_rle":false,"exists_today":true,"wheelchair":0},{"id":"harlem-blue-forest-park-branch-1b13","name":"Harlem (Blue - Forest Park Branch)","lat":41.8735,"lon":-87.807,"on_metra":false,"on_cta_rail":true,"on_crosstowner":false,"on_rle":false,"exists_today":true,"wheelchair":0},{"id":"harlem-blue-o-hare-branch-1ba7","name":"Harlem (Blue - O'Hare Branch)","lat":41.9823,"lon":-87.8089,"on_metra":false,"on_cta_rail":true,"on_crosstowner":false,"on_rle":false,"exists_today":true,"wheelchair":1},{"id":"harlem-ave-1b22","name":"Harlem Ave.","lat":41.8314,"lon":-87.8019,"on_metra":true,"on_cta_rail":false,"on_crosstowner":true,"on_rle":false,"exists_today":true,"wheelchair":1},{"id":"harlem-lake-1b23","name":"Harlem/Lake","lat":41.8868,"lon":-87.8032,"on_metra":false,"on_cta_rail":true,"on_crosstowner":false,"on_rle":false,"exists_today":true,"wheelchair":1},{"id":"harold-washington-library-state-van-buren-1b72","name":"Harold Washington Library-State/Van Buren","lat":41.8769,"lon":-87.6282,"on_metra":false,"on_cta_rail":true,"on_crosstowner":false,"on_rle":false,"exists_today":true,"wheelchair":1},{"id":"harrison-1b48","name":"Harrison","lat":41.874,"lon":-87.6275,"on_metra":false,"on_cta_rail":true,"on_crosstowner":false,"on_rle":false,"exists_today":true,"wheelchair":0},{"id":"harvard-1b68","name":"Harvard","lat":42.4197,"lon":-88.6175,"on_metra":true,"on_cta_rail":false,"on_crosstowner":false,"on_rle":false,"exists_today":true,"wheelchair":1},{"id":"harvey-1b6a","name":"Harvey","lat":41.6083,"lon":-87.6439,"on_metra":true,"on_cta_rail":false,"on_crosstowner":false,"on_rle":false,"exists_today":true,"wheelchair":1},{"id":"harvey-1b23","name":"Harvey","lat":41.6098,"lon":-87.6432,"on_metra":false,"on_cta_rail":false,"on_crosstowner":true,"on_rle":false,"exists_today":false},{"id":"hazel-crest-1baa","name":"Hazel Crest","lat":41.5808,"lon":-87.6586,"on_metra":true,"on_cta_rail":false,"on_crosstowner":false,"on_rle":false,"exists_today":true,"wheelchair":0},{"id":"healy-1ba1","name":"Healy","lat":41.9247,"lon":-87.7278,"on_metra":true,"on_cta_rail":false,"on_crosstowner":false,"on_rle":false,"exists_today":true,"wheelchair":1},{"id":"hickory-creek-1b97","name":"Hickory Creek","lat":41.5486,"lon":-87.8456,"on_metra":true,"on_cta_rail":false,"on_crosstowner":false,"on_rle":false,"exists_today":true,"wheelchair":1},{"id":"highland-park-1bb1","name":"Highland Park","lat":42.1833,"lon":-87.7975,"on_metra":true,"on_cta_rail":false,"on_crosstowner":true,"on_rle":false,"exists_today":true,"wheelchair":1},{"id":"highlands-1b33","name":"Highlands","lat":41.805,"lon":-87.9183,"on_metra":true,"on_cta_rail":false,"on_crosstowner":true,"on_rle":false,"exists_today":true,"wheelchair":0},{"id":"highwood-1ad1","name":"Highwood","lat":42.2033,"lon":-87.8106,"on_metra":true,"on_cta_rail":false,"on_crosstowner":false,"on_rle":false,"exists_today":true,"wheelchair":1},{"id":"hinsdale-1b67","name":"Hinsdale","lat":41.8028,"lon":-87.9283,"on_metra":true,"on_cta_rail":false,"on_crosstowner":true,"on_rle":false,"exists_today":true,"wheelchair":1},{"id":"hollywood-1b77","name":"Hollywood","lat":41.8244,"lon":-87.8339,"on_metra":true,"on_cta_rail":false,"on_crosstowner":true,"on_rle":false,"exists_today":true,"wheelchair":1},{"id":"homewood-1b90","name":"Homewood","lat":41.5622,"lon":-87.6686,"on_metra":true,"on_cta_rail":false,"on_crosstowner":false,"on_rle":false,"exists_today":true,"wheelchair":1},{"id":"howard-1b6c","name":"Howard","lat":42.0191,"lon":-87.6729,"on_metra":false,"on_cta_rail":true,"on_crosstowner":false,"on_rle":false,"exists_today":true,"wheelchair":1},{"id":"howard-clark-1b2e","name":"Howard/Clark","lat":42.0192,"lon":-87.677,"on_metra":false,"on_cta_rail":false,"on_crosstowner":true,"on_rle":false,"exists_today":false},{"id":"hubbard-woods-1b2c","name":"Hubbard Woods","lat":42.1181,"lon":-87.7436,"on_metra":true,"on_cta_rail":false,"on_crosstowner":true,"on_rle":false,"exists_today":true,"wheelchair":0},{"id":"humboldt-park-1b5a","name":"Humboldt Park","lat":41.898,"lon":-87.7084,"on_metra":false,"on_cta_rail":false,"on_crosstowner":true,"on_rle":false,"exists_today":false},{"id":"illinois-medical-district-1bc9","name":"Illinois Medical District","lat":41.8757,"lon":-87.6739,"on_metra":false,"on_cta_rail":true,"on_crosstowner":false,"on_rle":false,"exists_today":true,"wheelchair":1},{"id":"indian-hill-1b61","name":"Indian Hill","lat":42.0944,"lon":-87.7239,"on_metra":true,"on_cta_rail":false,"on_crosstowner":true,"on_rle":false,"exists_today":true,"wheelchair":0},{"id":"indiana-1ae4","name":"Indiana","lat":41.8217,"lon":-87.6214,"on_metra":false,"on_cta_rail":true,"on_crosstowner":false,"on_rle":false,"exists_today":true,"wheelchair":1},{"id":"ingleside-1b3c","name":"Ingleside","lat":42.3839,"lon":-88.1536,"on_metra":true,"on_cta_rail":false,"on_crosstowner":false,"on_rle":false,"exists_today":true,"wheelchair":1},{"id":"irving-park-1ba4","name":"Irving Park","lat":41.9525,"lon":-87.7297,"on_metra":true,"on_cta_rail":true,"on_crosstowner":true,"on_rle":false,"exists_today":true,"wheelchair":1},{"id":"irving-park-brown-1bbe","name":"Irving Park (Brown)","lat":41.9545,"lon":-87.6749,"on_metra":false,"on_cta_rail":true,"on_crosstowner":false,"on_rle":false,"exists_today":true,"wheelchair":1},{"id":"itasca-1aa8","name":"Itasca","lat":41.9714,"lon":-88.0142,"on_metra":true,"on_cta_rail":false,"on_crosstowner":false,"on_rle":false,"exists_today":true,"wheelchair":1},{"id":"ivanhoe-1ac0","name":"Ivanhoe","lat":41.6333,"lon":-87.6303,"on_metra":true,"on_cta_rail":false,"on_crosstowner":true,"on_rle":false,"exists_today":true,"wheelchair":1},{"id":"jackson-blue-1b6c","name":"Jackson (Blue)","lat":41.8782,"lon":-87.6293,"on_metra":false,"on_cta_rail":true,"on_crosstowner":false,"on_rle":false,"exists_today":true,"wheelchair":1},{"id":"jarvis-1b4e","name":"Jarvis","lat":42.016,"lon":-87.6693,"on_metra":false,"on_cta_rail":true,"on_crosstowner":false,"on_rle":false,"exists_today":true,"wheelchair":0},{"id":"jefferson-park-1b3f","name":"Jefferson Park","lat":41.9714,"lon":-87.7633,"on_metra":true,"on_cta_rail":false,"on_crosstowner":true,"on_rle":false,"exists_today":true,"wheelchair":1},{"id":"jefferson-park-transit-center-1b3d","name":"Jefferson Park Transit Center","lat":41.9702,"lon":-87.7616,"on_metra":false,"on_cta_rail":true,"on_crosstowner":false,"on_rle":false,"exists_today":true,"wheelchair":1},{"id":"joliet-1b80","name":"Joliet","lat":41.5244,"lon":-88.0797,"on_metra":true,"on_cta_rail":false,"on_crosstowner":false,"on_rle":false,"exists_today":true,"wheelchair":1},{"id":"kedzie-1b9c","name":"Kedzie","lat":41.8883,"lon":-87.7069,"on_metra":true,"on_cta_rail":false,"on_crosstowner":true,"on_rle":false,"exists_today":true,"wheelchair":0},{"id":"kedzie-brown-1b83","name":"Kedzie (Brown)","lat":41.966,"lon":-87.7088,"on_metra":false,"on_cta_rail":true,"on_crosstowner":false,"on_rle":false,"exists_today":true,"wheelchair":1},{"id":"kedzie-green-1b14","name":"Kedzie (Green)","lat":41.8843,"lon":-87.7062,"on_metra":false,"on_cta_rail":true,"on_crosstowner":false,"on_rle":false,"exists_today":true,"wheelchair":1},{"id":"kedzie-orange-1ae7","name":"Kedzie (Orange)","lat":41.8042,"lon":-87.7044,"on_metra":false,"on_cta_rail":true,"on_crosstowner":false,"on_rle":false,"exists_today":true,"wheelchair":1},{"id":"kedzie-pink-1b01","name":"Kedzie (Pink)","lat":41.854,"lon":-87.7054,"on_metra":false,"on_cta_rail":true,"on_crosstowner":false,"on_rle":false,"exists_today":true,"wheelchair":1},{"id":"kedzie-homan-1aef","name":"Kedzie-Homan","lat":41.8743,"lon":-87.706,"on_metra":false,"on_cta_rail":true,"on_crosstowner":false,"on_rle":false,"exists_today":true,"wheelchair":1},{"id":"kenilworth-1b67","name":"Kenilworth","lat":42.0864,"lon":-87.7167,"on_metra":true,"on_cta_rail":false,"on_crosstowner":true,"on_rle":false,"exists_today":true,"wheelchair":1},{"id":"kenosha-1bad","name":"Kenosha","lat":42.5858,"lon":-87.8258,"on_metra":true,"on_cta_rail":false,"on_crosstowner":false,"on_rle":false,"exists_today":true,"wheelchair":1},{"id":"kensington-1afa","name":"Kensington","lat":41.6858,"lon":-87.6122,"on_metra":true,"on_cta_rail":false,"on_crosstowner":true,"on_rle":false,"exists_today":true,"wheelchair":1},{"id":"kimball-1b1b","name":"Kimball","lat":41.9679,"lon":-87.7131,"on_metra":false,"on_cta_rail":true,"on_crosstowner":false,"on_rle":false,"exists_today":true,"wheelchair":1},{"id":"king-drive-1b0c","name":"King Drive","lat":41.7801,"lon":-87.6155,"on_metra":false,"on_cta_rail":true,"on_crosstowner":false,"on_rle":false,"exists_today":true,"wheelchair":1},{"id":"kostner-1b2f","name":"Kostner","lat":41.8538,"lon":-87.7333,"on_metra":false,"on_cta_rail":true,"on_crosstowner":false,"on_rle":false,"exists_today":true,"wheelchair":1},{"id":"la-fox-1af2","name":"La Fox","lat":41.8867,"lon":-88.4122,"on_metra":true,"on_cta_rail":false,"on_crosstowner":false,"on_rle":false,"exists_today":true,"wheelchair":1},{"id":"lagrange-road-1b2e","name":"LaGrange Road","lat":41.8158,"lon":-87.8711,"on_metra":true,"on_cta_rail":false,"on_crosstowner":true,"on_rle":false,"exists_today":true,"wheelchair":1},{"id":"lasalle-street-1b03","name":"LaSalle Street","lat":41.8764,"lon":-87.6322,"on_metra":true,"on_cta_rail":true,"on_crosstowner":false,"on_rle":false,"exists_today":true,"wheelchair":1},{"id":"lake-subway-1bb5","name":"Lake (Subway)","lat":41.8848,"lon":-87.6278,"on_metra":false,"on_cta_rail":true,"on_crosstowner":false,"on_rle":false,"exists_today":true,"wheelchair":1},{"id":"lake-bluff-1bc8","name":"Lake Bluff","lat":42.2797,"lon":-87.8467,"on_metra":true,"on_cta_rail":false,"on_crosstowner":false,"on_rle":false,"exists_today":true,"wheelchair":1},{"id":"lake-forest-1b90","name":"Lake Forest","lat":42.2236,"lon":-87.8747,"on_metra":true,"on_cta_rail":false,"on_crosstowner":false,"on_rle":false,"exists_today":true,"wheelchair":1},{"id":"lake-forest-1ba5","name":"Lake Forest.","lat":42.2525,"lon":-87.8397,"on_metra":true,"on_cta_rail":false,"on_crosstowner":false,"on_rle":false,"exists_today":true,"wheelchair":1},{"id":"lake-villa-1b62","name":"Lake Villa","lat":42.4175,"lon":-88.0794,"on_metra":true,"on_cta_rail":false,"on_crosstowner":false,"on_rle":false,"exists_today":true,"wheelchair":1},{"id":"lake-cook-1b0f","name":"Lake-Cook","lat":42.1517,"lon":-87.8414,"on_metra":true,"on_cta_rail":false,"on_crosstowner":false,"on_rle":false,"exists_today":true,"wheelchair":1},{"id":"laramie-1b36","name":"Laramie","lat":41.8872,"lon":-87.755,"on_metra":false,"on_cta_rail":true,"on_crosstowner":false,"on_rle":false,"exists_today":true,"wheelchair":1},{"id":"laraway-road-1bfd","name":"Laraway Road","lat":41.4847,"lon":-87.9597,"on_metra":true,"on_cta_rail":false,"on_crosstowner":false,"on_rle":false,"exists_today":true,"wheelchair":1},{"id":"lavergne-1b69","name":"Lavergne","lat":41.8356,"lon":-87.7833,"on_metra":true,"on_cta_rail":false,"on_crosstowner":true,"on_rle":false,"exists_today":true,"wheelchair":1},{"id":"lawrence-1b9e","name":"Lawrence","lat":41.969,"lon":-87.6585,"on_metra":false,"on_cta_rail":true,"on_crosstowner":false,"on_rle":false,"exists_today":true,"wheelchair":1},{"id":"lawrence-ruby-1bac","name":"Lawrence/Ruby","lat":41.9658,"lon":-87.8708,"on_metra":false,"on_cta_rail":false,"on_crosstowner":true,"on_rle":false,"exists_today":false},{"id":"lemont-1aba","name":"Lemont","lat":41.6736,"lon":-88.0025,"on_metra":true,"on_cta_rail":false,"on_crosstowner":false,"on_rle":false,"exists_today":true,"wheelchair":1},{"id":"libertyville-1b63","name":"Libertyville","lat":42.2911,"lon":-87.9564,"on_metra":true,"on_cta_rail":false,"on_crosstowner":false,"on_rle":false,"exists_today":true,"wheelchair":1},{"id":"linden-1b4b","name":"Linden","lat":42.0732,"lon":-87.6907,"on_metra":false,"on_cta_rail":true,"on_crosstowner":false,"on_rle":false,"exists_today":true,"wheelchair":1},{"id":"lisle-1b81","name":"Lisle","lat":41.7978,"lon":-88.0719,"on_metra":true,"on_cta_rail":false,"on_crosstowner":false,"on_rle":false,"exists_today":true,"wheelchair":1},{"id":"lockport-1ab3","name":"Lockport","lat":41.585,"lon":-88.0603,"on_metra":true,"on_cta_rail":false,"on_crosstowner":false,"on_rle":false,"exists_today":true,"wheelchair":1},{"id":"logan-square-1b85","name":"Logan Square","lat":41.9295,"lon":-87.7077,"on_metra":false,"on_cta_rail":true,"on_crosstowner":false,"on_rle":false,"exists_today":true,"wheelchair":1},{"id":"lombard-1b58","name":"Lombard","lat":41.8867,"lon":-88.0186,"on_metra":true,"on_cta_rail":false,"on_crosstowner":false,"on_rle":false,"exists_today":true,"wheelchair":1},{"id":"long-lake-1ae9","name":"Long Lake","lat":42.3681,"lon":-88.1281,"on_metra":true,"on_cta_rail":false,"on_crosstowner":false,"on_rle":false,"exists_today":true,"wheelchair":1},{"id":"loyola-1a9a","name":"Loyola","lat":42.0011,"lon":-87.6611,"on_metra":false,"on_cta_rail":true,"on_crosstowner":false,"on_rle":false,"exists_today":true,"wheelchair":1},{"id":"main-st-1ac0","name":"Main St.","lat":42.0333,"lon":-87.68,"on_metra":true,"on_cta_rail":true,"on_crosstowner":true,"on_rle":false,"exists_today":true,"wheelchair":1},{"id":"manhattan-1bb0","name":"Manhattan","lat":41.4183,"lon":-87.9892,"on_metra":true,"on_cta_rail":false,"on_crosstowner":false,"on_rle":false,"exists_today":true,"wheelchair":1},{"id":"mannheim-1b6e","name":"Mannheim","lat":41.9417,"lon":-87.8833,"on_metra":true,"on_cta_rail":false,"on_crosstowner":false,"on_rle":false,"exists_today":true,"wheelchair":0},{"id":"mars-1b8c","name":"Mars","lat":41.9192,"lon":-87.7944,"on_metra":true,"on_cta_rail":false,"on_crosstowner":true,"on_rle":false,"exists_today":true,"wheelchair":1},{"id":"matteson-1afa","name":"Matteson","lat":41.4986,"lon":-87.7022,"on_metra":true,"on_cta_rail":false,"on_crosstowner":false,"on_rle":false,"exists_today":true,"wheelchair":0},{"id":"mayfair-1bcc","name":"Mayfair","lat":41.9597,"lon":-87.7458,"on_metra":true,"on_cta_rail":false,"on_crosstowner":false,"on_rle":false,"exists_today":true,"wheelchair":0},{"id":"maywood-1bc1","name":"Maywood","lat":41.8883,"lon":-87.8386,"on_metra":true,"on_cta_rail":false,"on_crosstowner":true,"on_rle":false,"exists_today":true,"wheelchair":1},{"id":"mccormick-place-1b1b","name":"McCormick Place","lat":41.8514,"lon":-87.6164,"on_metra":true,"on_cta_rail":false,"on_crosstowner":true,"on_rle":false,"exists_today":true,"wheelchair":1},{"id":"mchenry-1b04","name":"McHenry","lat":42.3433,"lon":-88.2761,"on_metra":true,"on_cta_rail":false,"on_crosstowner":false,"on_rle":false,"exists_today":true,"wheelchair":1},{"id":"medinah-1b19","name":"Medinah","lat":41.9781,"lon":-88.0508,"on_metra":true,"on_cta_rail":false,"on_crosstowner":false,"on_rle":false,"exists_today":true,"wheelchair":1},{"id":"melrose-park-1b85","name":"Melrose Park","lat":41.8903,"lon":-87.8556,"on_metra":true,"on_cta_rail":false,"on_crosstowner":true,"on_rle":false,"exists_today":true,"wheelchair":1},{"id":"merchandise-mart-brown-purple-1b7d","name":"Merchandise Mart (Brown/Purple)","lat":41.889,"lon":-87.6339,"on_metra":false,"on_cta_rail":true,"on_crosstowner":false,"on_rle":false,"exists_today":true,"wheelchair":1},{"id":"michigan-116th-1b06","name":"Michigan (116th)","lat":41.683,"lon":-87.6208,"on_metra":false,"on_cta_rail":false,"on_crosstowner":false,"on_rle":true,"exists_today":false},{"id":"midlothian-1b14","name":"Midlothian","lat":41.6264,"lon":-87.7117,"on_metra":true,"on_cta_rail":false,"on_crosstowner":false,"on_rle":false,"exists_today":true,"wheelchair":1},{"id":"midway-1bda","name":"Midway","lat":41.7866,"lon":-87.7379,"on_metra":false,"on_cta_rail":true,"on_crosstowner":false,"on_rle":false,"exists_today":true,"wheelchair":1},{"id":"millennium-station-1adf","name":"Millennium Station","lat":41.8842,"lon":-87.6231,"on_metra":true,"on_cta_rail":false,"on_crosstowner":false,"on_rle":false,"exists_today":true,"wheelchair":1},{"id":"mokena-1bc7","name":"Mokena","lat":41.5308,"lon":-87.8867,"on_metra":true,"on_cta_rail":false,"on_crosstowner":false,"on_rle":false,"exists_today":true,"wheelchair":1},{"id":"monroe-blue-1b74","name":"Monroe (Blue)","lat":41.8807,"lon":-87.6294,"on_metra":false,"on_cta_rail":true,"on_crosstowner":false,"on_rle":false,"exists_today":true,"wheelchair":0},{"id":"mont-clare-1b16","name":"Mont Clare","lat":41.9217,"lon":-87.8017,"on_metra":true,"on_cta_rail":false,"on_crosstowner":false,"on_rle":false,"exists_today":true,"wheelchair":1},{"id":"montrose-blue-1b8c","name":"Montrose (Blue)","lat":41.9609,"lon":-87.7429,"on_metra":false,"on_cta_rail":true,"on_crosstowner":true,"on_rle":false,"exists_today":true,"wheelchair":0},{"id":"montrose-brown-1b45","name":"Montrose (Brown)","lat":41.9618,"lon":-87.675,"on_metra":false,"on_cta_rail":true,"on_crosstowner":false,"on_rle":false,"exists_today":true,"wheelchair":1},{"id":"morgan-green-pink-1b1c","name":"Morgan (Green/Pink)","lat":41.8856,"lon":-87.6521,"on_metra":false,"on_cta_rail":true,"on_crosstowner":false,"on_rle":false,"exists_today":true,"wheelchair":1},{"id":"morse-1b95","name":"Morse","lat":42.0084,"lon":-87.6659,"on_metra":false,"on_cta_rail":true,"on_crosstowner":false,"on_rle":false,"exists_today":true,"wheelchair":0},{"id":"morton-grove-1b3f","name":"Morton Grove","lat":42.035,"lon":-87.7853,"on_metra":true,"on_cta_rail":false,"on_crosstowner":false,"on_rle":false,"exists_today":true,"wheelchair":1},{"id":"mt-prospect-1b0c","name":"Mt. Prospect","lat":42.0631,"lon":-87.9361,"on_metra":true,"on_cta_rail":false,"on_crosstowner":true,"on_rle":false,"exists_today":true,"wheelchair":1},{"id":"mundelein-1bd0","name":"Mundelein","lat":42.2669,"lon":-87.9981,"on_metra":true,"on_cta_rail":false,"on_crosstowner":false,"on_rle":false,"exists_today":true,"wheelchair":1},{"id":"museum-campus-11th-st-1b1b","name":"Museum Campus/11th St.","lat":41.8686,"lon":-87.6214,"on_metra":true,"on_cta_rail":false,"on_crosstowner":false,"on_rle":false,"exists_today":true,"wheelchair":1},{"id":"naperville-1b6b","name":"Naperville","lat":41.7797,"lon":-88.1456,"on_metra":true,"on_cta_rail":false,"on_crosstowner":false,"on_rle":false,"exists_today":true,"wheelchair":1},{"id":"national-st-1ba5","name":"National St","lat":42.0264,"lon":-88.2789,"on_metra":true,"on_cta_rail":false,"on_crosstowner":false,"on_rle":false,"exists_today":true,"wheelchair":1},{"id":"new-lenox-1b5b","name":"New Lenox","lat":41.5144,"lon":-87.9653,"on_metra":true,"on_cta_rail":false,"on_crosstowner":false,"on_rle":false,"exists_today":true,"wheelchair":1},{"id":"north-chicago-1bb8","name":"North Chicago","lat":42.3286,"lon":-87.8369,"on_metra":true,"on_cta_rail":false,"on_crosstowner":false,"on_rle":false,"exists_today":true,"wheelchair":1},{"id":"north-clybourn-1b51","name":"North/Clybourn","lat":41.9107,"lon":-87.6492,"on_metra":false,"on_cta_rail":true,"on_crosstowner":false,"on_rle":false,"exists_today":true,"wheelchair":0},{"id":"north-ridgeway-1b74","name":"North/Ridgeway","lat":41.909,"lon":-87.7196,"on_metra":false,"on_cta_rail":false,"on_crosstowner":true,"on_rle":false,"exists_today":false},{"id":"northbrook-1baa","name":"Northbrook","lat":42.1269,"lon":-87.8278,"on_metra":true,"on_cta_rail":false,"on_crosstowner":false,"on_rle":false,"exists_today":true,"wheelchair":1},{"id":"norwood-park-1c33","name":"Norwood Park","lat":41.9917,"lon":-87.7989,"on_metra":true,"on_cta_rail":false,"on_crosstowner":true,"on_rle":false,"exists_today":true,"wheelchair":1},{"id":"noyes-1b45","name":"Noyes","lat":42.0583,"lon":-87.6833,"on_metra":false,"on_cta_rail":true,"on_crosstowner":false,"on_rle":false,"exists_today":true,"wheelchair":0},{"id":"o-hare-1b3d","name":"O'Hare","lat":41.9777,"lon":-87.9042,"on_metra":false,"on_cta_rail":true,"on_crosstowner":false,"on_rle":false,"exists_today":true,"wheelchair":1},{"id":"o-hare-transfer-1b71","name":"O'Hare Transfer","lat":41.995,"lon":-87.8806,"on_metra":true,"on_cta_rail":false,"on_crosstowner":true,"on_rle":false,"exists_today":true,"wheelchair":1},{"id":"oak-forest-1b43","name":"Oak Forest","lat":41.6044,"lon":-87.7383,"on_metra":true,"on_cta_rail":false,"on_crosstowner":false,"on_rle":false,"exists_today":true,"wheelchair":1},{"id":"oak-lawn-patriot-1ba8","name":"Oak Lawn Patriot","lat":41.7194,"lon":-87.7486,"on_metra":true,"on_cta_rail":false,"on_crosstowner":false,"on_rle":false,"exists_today":true,"wheelchair":1},{"id":"oak-park-1afc","name":"Oak Park","lat":41.8869,"lon":-87.8011,"on_metra":true,"on_cta_rail":false,"on_crosstowner":true,"on_rle":false,"exists_today":true,"wheelchair":1},{"id":"oak-park-blue-1b68","name":"Oak Park (Blue)","lat":41.8721,"lon":-87.7916,"on_metra":false,"on_cta_rail":true,"on_crosstowner":false,"on_rle":false,"exists_today":true,"wheelchair":0},{"id":"oak-park-green-1bc2","name":"Oak Park (Green)","lat":41.887,"lon":-87.7938,"on_metra":false,"on_cta_rail":true,"on_crosstowner":false,"on_rle":false,"exists_today":true,"wheelchair":0},{"id":"oakton-skokie-1b24","name":"Oakton-Skokie","lat":42.0262,"lon":-87.7472,"on_metra":false,"on_cta_rail":true,"on_crosstowner":false,"on_rle":false,"exists_today":true,"wheelchair":1},{"id":"oakwood-blvd-1ad9","name":"Oakwood Blvd","lat":41.8247,"lon":-87.6023,"on_metra":false,"on_cta_rail":false,"on_crosstowner":true,"on_rle":false,"exists_today":false},{"id":"olympia-fields-1ad6","name":"Olympia Fields","lat":41.5214,"lon":-87.69,"on_metra":true,"on_cta_rail":false,"on_crosstowner":false,"on_rle":false,"exists_today":true,"wheelchair":0},{"id":"orland-park-143rd-1b70","name":"Orland Park 143rd","lat":41.6306,"lon":-87.8592,"on_metra":true,"on_cta_rail":false,"on_crosstowner":false,"on_rle":false,"exists_today":true,"wheelchair":1},{"id":"orland-park-153rd-1b5b","name":"Orland Park 153rd","lat":41.6094,"lon":-87.8733,"on_metra":true,"on_cta_rail":false,"on_crosstowner":false,"on_rle":false,"exists_today":true,"wheelchair":1},{"id":"orland-park-179th-1b30","name":"Orland Park 179th","lat":41.5639,"lon":-87.9025,"on_metra":true,"on_cta_rail":false,"on_crosstowner":false,"on_rle":false,"exists_today":true,"wheelchair":1},{"id":"palatine-1ad9","name":"Palatine","lat":42.1131,"lon":-88.0483,"on_metra":true,"on_cta_rail":false,"on_crosstowner":true,"on_rle":false,"exists_today":true,"wheelchair":1},{"id":"palos-heights-1ba1","name":"Palos Heights","lat":41.6819,"lon":-87.8069,"on_metra":true,"on_cta_rail":false,"on_crosstowner":false,"on_rle":false,"exists_today":true,"wheelchair":1},{"id":"palos-park-1b23","name":"Palos Park","lat":41.6689,"lon":-87.8203,"on_metra":true,"on_cta_rail":false,"on_crosstowner":false,"on_rle":false,"exists_today":true,"wheelchair":1},{"id":"park-ridge-1af7","name":"Park Ridge","lat":42.0103,"lon":-87.8317,"on_metra":true,"on_cta_rail":false,"on_crosstowner":true,"on_rle":false,"exists_today":true,"wheelchair":1},{"id":"paulina-1b7e","name":"Paulina","lat":41.9436,"lon":-87.6709,"on_metra":false,"on_cta_rail":true,"on_crosstowner":false,"on_rle":false,"exists_today":true,"wheelchair":1},{"id":"peterson-ridge-1b23","name":"Peterson/Ridge","lat":41.9911,"lon":-87.675,"on_metra":true,"on_cta_rail":false,"on_crosstowner":true,"on_rle":false,"exists_today":true,"wheelchair":1},{"id":"pingree-road-1b34","name":"Pingree Road","lat":42.2342,"lon":-88.2981,"on_metra":true,"on_cta_rail":false,"on_crosstowner":false,"on_rle":false,"exists_today":true,"wheelchair":1},{"id":"polk-1bb6","name":"Polk","lat":41.8716,"lon":-87.6695,"on_metra":false,"on_cta_rail":true,"on_crosstowner":false,"on_rle":false,"exists_today":true,"wheelchair":1},{"id":"prairie-crossing-1aae","name":"Prairie Crossing","lat":42.3208,"lon":-88.0153,"on_metra":true,"on_cta_rail":false,"on_crosstowner":false,"on_rle":false,"exists_today":true,"wheelchair":1},{"id":"prairie-crossing-1ab6","name":"Prairie Crossing.","lat":42.3181,"lon":-88.0172,"on_metra":true,"on_cta_rail":false,"on_crosstowner":false,"on_rle":false,"exists_today":true,"wheelchair":1},{"id":"prairie-st-1b2a","name":"Prairie St.","lat":41.6625,"lon":-87.675,"on_metra":true,"on_cta_rail":false,"on_crosstowner":true,"on_rle":false,"exists_today":true,"wheelchair":0},{"id":"prairie-view-1bba","name":"Prairie View","lat":42.1981,"lon":-87.9558,"on_metra":true,"on_cta_rail":false,"on_crosstowner":false,"on_rle":false,"exists_today":true,"wheelchair":1},{"id":"prospect-hts-1b10","name":"Prospect Hts","lat":42.0922,"lon":-87.9081,"on_metra":true,"on_cta_rail":false,"on_crosstowner":false,"on_rle":false,"exists_today":true,"wheelchair":1},{"id":"pulaski-blue-1b89","name":"Pulaski (Blue)","lat":41.8738,"lon":-87.7257,"on_metra":false,"on_cta_rail":true,"on_crosstowner":false,"on_rle":false,"exists_today":true,"wheelchair":0},{"id":"pulaski-green-1b4e","name":"Pulaski (Green)","lat":41.8854,"lon":-87.7254,"on_metra":false,"on_cta_rail":true,"on_crosstowner":false,"on_rle":false,"exists_today":true,"wheelchair":1},{"id":"pulaski-orange-1b84","name":"Pulaski (Orange)","lat":41.7998,"lon":-87.7245,"on_metra":false,"on_cta_rail":true,"on_crosstowner":false,"on_rle":false,"exists_today":true,"wheelchair":1},{"id":"pulaski-pink-1b29","name":"Pulaski (Pink)","lat":41.8537,"lon":-87.7243,"on_metra":false,"on_cta_rail":true,"on_crosstowner":false,"on_rle":false,"exists_today":true,"wheelchair":1},{"id":"quincy-1b83","name":"Quincy","lat":41.8787,"lon":-87.6337,"on_metra":false,"on_cta_rail":true,"on_crosstowner":false,"on_rle":false,"exists_today":true,"wheelchair":1},{"id":"racine-1b5e","name":"Racine","lat":41.6742,"lon":-87.6519,"on_metra":true,"on_cta_rail":false,"on_crosstowner":true,"on_rle":false,"exists_today":true,"wheelchair":0},{"id":"racine-1bd5","name":"Racine","lat":41.8759,"lon":-87.6595,"on_metra":false,"on_cta_rail":true,"on_crosstowner":false,"on_rle":false,"exists_today":true,"wheelchair":1},{"id":"ravenswood-1b7d","name":"Ravenswood","lat":41.9683,"lon":-87.6744,"on_metra":true,"on_cta_rail":false,"on_crosstowner":true,"on_rle":false,"exists_today":true,"wheelchair":1},{"id":"ravinia-1b75","name":"Ravinia","lat":42.165,"lon":-87.7828,"on_metra":true,"on_cta_rail":false,"on_crosstowner":true,"on_rle":false,"exists_today":true,"wheelchair":1},{"id":"ravinia-park-1bc7","name":"Ravinia Park","lat":42.1581,"lon":-87.7769,"on_metra":true,"on_cta_rail":false,"on_crosstowner":true,"on_rle":false,"exists_today":true,"wheelchair":1},{"id":"richton-park-1b6c","name":"Richton Park","lat":41.4856,"lon":-87.7094,"on_metra":true,"on_cta_rail":false,"on_crosstowner":false,"on_rle":false,"exists_today":true,"wheelchair":1},{"id":"ridgeland-1bb2","name":"Ridgeland","lat":41.8872,"lon":-87.7837,"on_metra":false,"on_cta_rail":true,"on_crosstowner":false,"on_rle":false,"exists_today":true,"wheelchair":0},{"id":"river-forest-1b44","name":"River Forest","lat":41.8869,"lon":-87.825,"on_metra":true,"on_cta_rail":false,"on_crosstowner":true,"on_rle":false,"exists_today":true,"wheelchair":0},{"id":"river-grove-1b06","name":"River Grove","lat":41.9311,"lon":-87.8361,"on_metra":true,"on_cta_rail":false,"on_crosstowner":true,"on_rle":false,"exists_today":true,"wheelchair":1},{"id":"riverdale-1b12","name":"Riverdale","lat":41.6467,"lon":-87.6233,"on_metra":true,"on_cta_rail":false,"on_crosstowner":true,"on_rle":false,"exists_today":true,"wheelchair":0},{"id":"riverside-1ab0","name":"Riverside","lat":41.8272,"lon":-87.82,"on_metra":true,"on_cta_rail":false,"on_crosstowner":true,"on_rle":false,"exists_today":true,"wheelchair":1},{"id":"robbins-1b76","name":"Robbins","lat":41.6408,"lon":-87.6944,"on_metra":true,"on_cta_rail":false,"on_crosstowner":false,"on_rle":false,"exists_today":true,"wheelchair":1},{"id":"rockwell-1b4f","name":"Rockwell","lat":41.9661,"lon":-87.6941,"on_metra":false,"on_cta_rail":true,"on_crosstowner":false,"on_rle":false,"exists_today":true,"wheelchair":1},{"id":"rogers-park-1b79","name":"Rogers Park","lat":42.0094,"lon":-87.6756,"on_metra":true,"on_cta_rail":false,"on_crosstowner":true,"on_rle":false,"exists_today":true,"wheelchair":1},{"id":"romeoville-1b33","name":"Romeoville","lat":41.6372,"lon":-88.0494,"on_metra":true,"on_cta_rail":false,"on_crosstowner":false,"on_rle":false,"exists_today":true,"wheelchair":1},{"id":"roosevelt-1b21","name":"Roosevelt","lat":41.8674,"lon":-87.627,"on_metra":false,"on_cta_rail":true,"on_crosstowner":true,"on_rle":false,"exists_today":true,"wheelchair":1},{"id":"roselle-1b20","name":"Roselle","lat":41.9814,"lon":-88.0672,"on_metra":true,"on_cta_rail":false,"on_crosstowner":false,"on_rle":false,"exists_today":true,"wheelchair":1},{"id":"rosemont-1bc3","name":"Rosemont","lat":41.9761,"lon":-87.8739,"on_metra":true,"on_cta_rail":false,"on_crosstowner":true,"on_rle":false,"exists_today":true,"wheelchair":1},{"id":"rosemont-1bc0","name":"Rosemont","lat":41.9835,"lon":-87.8594,"on_metra":false,"on_cta_rail":true,"on_crosstowner":false,"on_rle":false,"exists_today":true,"wheelchair":1},{"id":"round-lake-1b0a","name":"Round Lake","lat":42.3544,"lon":-88.0942,"on_metra":true,"on_cta_rail":false,"on_crosstowner":false,"on_rle":false,"exists_today":true,"wheelchair":1},{"id":"round-lake-beach-1b28","name":"Round Lake Beach","lat":42.385,"lon":-88.0656,"on_metra":true,"on_cta_rail":false,"on_crosstowner":false,"on_rle":false,"exists_today":true,"wheelchair":1},{"id":"route-59-1b68","name":"Route 59","lat":41.7778,"lon":-88.2086,"on_metra":true,"on_cta_rail":false,"on_crosstowner":false,"on_rle":false,"exists_today":true,"wheelchair":1},{"id":"schaumburg-1b08","name":"Schaumburg","lat":41.9892,"lon":-88.1181,"on_metra":true,"on_cta_rail":false,"on_crosstowner":false,"on_rle":false,"exists_today":true,"wheelchair":1},{"id":"schiller-park-1b7a","name":"Schiller Park","lat":41.9628,"lon":-87.8706,"on_metra":true,"on_cta_rail":false,"on_crosstowner":false,"on_rle":false,"exists_today":true,"wheelchair":1},{"id":"schiller-park-irving-park-rd-1bc4","name":"Schiller Park - Irving Park Rd","lat":41.9542,"lon":-87.8659,"on_metra":false,"on_cta_rail":false,"on_crosstowner":true,"on_rle":false,"exists_today":false},{"id":"sedgwick-brown-purple-1b3e","name":"Sedgwick (Brown/Purple)","lat":41.9104,"lon":-87.6393,"on_metra":false,"on_cta_rail":true,"on_crosstowner":false,"on_rle":false,"exists_today":true,"wheelchair":1},{"id":"sheridan-1b98","name":"Sheridan","lat":41.9539,"lon":-87.6547,"on_metra":false,"on_cta_rail":true,"on_crosstowner":false,"on_rle":false,"exists_today":true,"wheelchair":0},{"id":"south-boulevard-1b82","name":"South Boulevard","lat":42.0276,"lon":-87.6783,"on_metra":false,"on_cta_rail":true,"on_crosstowner":false,"on_rle":false,"exists_today":true,"wheelchair":0},{"id":"south-chicago-93rd-1ba7","name":"South Chicago (93rd)","lat":41.7267,"lon":-87.5478,"on_metra":true,"on_cta_rail":false,"on_crosstowner":true,"on_rle":false,"exists_today":true,"wheelchair":1},{"id":"south-shore-1b97","name":"South Shore","lat":41.7653,"lon":-87.5658,"on_metra":true,"on_cta_rail":false,"on_crosstowner":true,"on_rle":false,"exists_today":true,"wheelchair":1},{"id":"southport-1b74","name":"Southport","lat":41.9437,"lon":-87.6636,"on_metra":false,"on_cta_rail":true,"on_crosstowner":false,"on_rle":false,"exists_today":true,"wheelchair":1},{"id":"state-st-1b42","name":"State St.","lat":41.6744,"lon":-87.6219,"on_metra":true,"on_cta_rail":false,"on_crosstowner":true,"on_rle":false,"exists_today":true,"wheelchair":0},{"id":"stewart-ridge-1b30","name":"Stewart Ridge","lat":41.6744,"lon":-87.6317,"on_metra":true,"on_cta_rail":false,"on_crosstowner":true,"on_rle":false,"exists_today":true,"wheelchair":0},{"id":"stone-ave-1b87","name":"Stone Ave.","lat":41.8142,"lon":-87.8783,"on_metra":true,"on_cta_rail":false,"on_crosstowner":true,"on_rle":false,"exists_today":true,"wheelchair":0},{"id":"stony-island-1bca","name":"Stony Island","lat":41.7661,"lon":-87.5869,"on_metra":true,"on_cta_rail":false,"on_crosstowner":true,"on_rle":false,"exists_today":true,"wheelchair":1},{"id":"summit-1b90","name":"Summit","lat":41.795,"lon":-87.8097,"on_metra":true,"on_cta_rail":false,"on_crosstowner":false,"on_rle":false,"exists_today":true,"wheelchair":1},{"id":"taylor-clinton-1b7c","name":"Taylor/Clinton","lat":41.8698,"lon":-87.6408,"on_metra":false,"on_cta_rail":false,"on_crosstowner":true,"on_rle":false,"exists_today":false},{"id":"thorndale-1b4d","name":"Thorndale","lat":41.9901,"lon":-87.6591,"on_metra":false,"on_cta_rail":true,"on_crosstowner":false,"on_rle":false,"exists_today":true,"wheelchair":0},{"id":"tinley-park-1bc0","name":"Tinley Park","lat":41.5758,"lon":-87.7828,"on_metra":true,"on_cta_rail":false,"on_crosstowner":false,"on_rle":false,"exists_today":true,"wheelchair":1},{"id":"tinley-80th-1b5f","name":"Tinley-80th","lat":41.5644,"lon":-87.8094,"on_metra":true,"on_cta_rail":false,"on_crosstowner":false,"on_rle":false,"exists_today":true,"wheelchair":1},{"id":"uic-halsted-1bcb","name":"UIC-Halsted","lat":41.8755,"lon":-87.6497,"on_metra":false,"on_cta_rail":true,"on_crosstowner":false,"on_rle":false,"exists_today":true,"wheelchair":1},{"id":"university-park-1b19","name":"University Park","lat":41.4594,"lon":-87.7233,"on_metra":true,"on_cta_rail":false,"on_crosstowner":false,"on_rle":false,"exists_today":true,"wheelchair":1},{"id":"van-buren-st-1b17","name":"Van Buren St.","lat":41.8769,"lon":-87.6231,"on_metra":true,"on_cta_rail":false,"on_crosstowner":false,"on_rle":false,"exists_today":true,"wheelchair":1},{"id":"vernon-hills-1b66","name":"Vernon Hills","lat":42.2156,"lon":-87.9644,"on_metra":true,"on_cta_rail":false,"on_crosstowner":false,"on_rle":false,"exists_today":true,"wheelchair":1},{"id":"villa-park-1be7","name":"Villa Park","lat":41.8964,"lon":-87.9775,"on_metra":true,"on_cta_rail":false,"on_crosstowner":false,"on_rle":false,"exists_today":true,"wheelchair":1},{"id":"washington-1b63","name":"Washington","lat":41.8832,"lon":-87.6294,"on_metra":false,"on_cta_rail":true,"on_crosstowner":false,"on_rle":false,"exists_today":true,"wheelchair":0},{"id":"washington-st-grayslake-1ae6","name":"Washington St (Grayslake)","lat":42.3592,"lon":-88.0506,"on_metra":true,"on_cta_rail":false,"on_crosstowner":false,"on_rle":false,"exists_today":true,"wheelchair":1},{"id":"washington-wabash-1b16","name":"Washington/Wabash","lat":41.8832,"lon":-87.6262,"on_metra":false,"on_cta_rail":true,"on_crosstowner":false,"on_rle":false,"exists_today":true,"wheelchair":1},{"id":"washington-wells-1b74","name":"Washington/Wells","lat":41.8827,"lon":-87.6338,"on_metra":false,"on_cta_rail":true,"on_crosstowner":false,"on_rle":false,"exists_today":true,"wheelchair":1},{"id":"waukegan-1b4c","name":"Waukegan","lat":42.3606,"lon":-87.8283,"on_metra":true,"on_cta_rail":false,"on_crosstowner":false,"on_rle":false,"exists_today":true,"wheelchair":1},{"id":"wellington-brown-purple-1b12","name":"Wellington (Brown/Purple)","lat":41.936,"lon":-87.6533,"on_metra":false,"on_cta_rail":true,"on_crosstowner":false,"on_rle":false,"exists_today":true,"wheelchair":1},{"id":"west-chicago-1bbd","name":"West Chicago","lat":41.8811,"lon":-88.1989,"on_metra":true,"on_cta_rail":false,"on_crosstowner":false,"on_rle":false,"exists_today":true,"wheelchair":1},{"id":"west-hinsdale-1baa","name":"West Hinsdale","lat":41.7989,"lon":-87.9453,"on_metra":true,"on_cta_rail":false,"on_crosstowner":true,"on_rle":false,"exists_today":true,"wheelchair":1},{"id":"west-pullman-1aef","name":"West Pullman","lat":41.6742,"lon":-87.6422,"on_metra":true,"on_cta_rail":false,"on_crosstowner":true,"on_rle":false,"exists_today":true,"wheelchair":0},{"id":"western-blue-forest-park-branch-1bc4","name":"Western (Blue - Forest Park Branch)","lat":41.8755,"lon":-87.6884,"on_metra":false,"on_cta_rail":true,"on_crosstowner":false,"on_rle":false,"exists_today":true,"wheelchair":0},{"id":"western-blue-o-hare-branch-1b8c","name":"Western (Blue - O'Hare Branch)","lat":41.9162,"lon":-87.6874,"on_metra":false,"on_cta_rail":true,"on_crosstowner":false,"on_rle":false,"exists_today":true,"wheelchair":1},{"id":"western-brown-1bc4","name":"Western (Brown)","lat":41.9662,"lon":-87.6885,"on_metra":false,"on_cta_rail":true,"on_crosstowner":false,"on_rle":false,"exists_today":true,"wheelchair":1},{"id":"western-orange-1b1f","name":"Western (Orange)","lat":41.8045,"lon":-87.684,"on_metra":false,"on_cta_rail":true,"on_crosstowner":false,"on_rle":false,"exists_today":true,"wheelchair":1},{"id":"western-pink-1b42","name":"Western (Pink)","lat":41.8542,"lon":-87.6851,"on_metra":false,"on_cta_rail":true,"on_crosstowner":false,"on_rle":false,"exists_today":true,"wheelchair":1},{"id":"western-ave-1b9c","name":"Western Ave","lat":41.8892,"lon":-87.6881,"on_metra":true,"on_cta_rail":false,"on_crosstowner":true,"on_rle":false,"exists_today":true,"wheelchair":1},{"id":"western-avenue-1b9e","name":"Western Avenue","lat":41.8578,"lon":-87.6853,"on_metra":true,"on_cta_rail":false,"on_crosstowner":true,"on_rle":false,"exists_today":true,"wheelchair":0},{"id":"western-springs-1aed","name":"Western Springs","lat":41.8089,"lon":-87.9011,"on_metra":true,"on_cta_rail":false,"on_crosstowner":true,"on_rle":false,"exists_today":true,"wheelchair":1},{"id":"western-logan-1c00","name":"Western/Logan","lat":41.9287,"lon":-87.6878,"on_metra":false,"on_cta_rail":false,"on_crosstowner":true,"on_rle":false,"exists_today":false},{"id":"westmont-1bcc","name":"Westmont","lat":41.7956,"lon":-87.9764,"on_metra":true,"on_cta_rail":false,"on_crosstowner":true,"on_rle":false,"exists_today":true,"wheelchair":1},{"id":"wheaton-1b01","name":"Wheaton","lat":41.8644,"lon":-88.1119,"on_metra":true,"on_cta_rail":false,"on_crosstowner":false,"on_rle":false,"exists_today":true,"wheelchair":1},{"id":"wheeling-1b39","name":"Wheeling","lat":42.1364,"lon":-87.9272,"on_metra":true,"on_cta_rail":false,"on_crosstowner":false,"on_rle":false,"exists_today":true,"wheelchair":1},{"id":"willow-springs-1b8e","name":"Willow Springs","lat":41.7333,"lon":-87.8783,"on_metra":true,"on_cta_rail":false,"on_crosstowner":false,"on_rle":false,"exists_today":true,"wheelchair":1},{"id":"wilmette-1b29","name":"Wilmette","lat":42.0772,"lon":-87.7092,"on_metra":true,"on_cta_rail":false,"on_crosstowner":true,"on_rle":false,"exists_today":true,"wheelchair":1},{"id":"wilson-1bda","name":"Wilson","lat":41.9655,"lon":-87.6579,"on_metra":false,"on_cta_rail":true,"on_crosstowner":false,"on_rle":false,"exists_today":true,"wheelchair":1},{"id":"windsor-park-1ba7","name":"Windsor Park","lat":41.7586,"lon":-87.5594,"on_metra":true,"on_cta_rail":false,"on_crosstowner":true,"on_rle":false,"exists_today":true,"wheelchair":1},{"id":"winfield-1b55","name":"Winfield","lat":41.87,"lon":-88.1569,"on_metra":true,"on_cta_rail":false,"on_crosstowner":false,"on_rle":false,"exists_today":true,"wheelchair":1},{"id":"winnetka-1b26","name":"Winnetka","lat":42.1053,"lon":-87.7328,"on_metra":true,"on_cta_rail":false,"on_crosstowner":true,"on_rle":false,"exists_today":true,"wheelchair":1},{"id":"winthrop-harbor-1b28","name":"Winthrop Harbor","lat":42.4828,"lon":-87.8161,"on_metra":true,"on_cta_rail":false,"on_crosstowner":false,"on_rle":false,"exists_today":true,"wheelchair":1},{"id":"wood-dale-1b8d","name":"Wood Dale","lat":41.9625,"lon":-87.9753,"on_metra":true,"on_cta_rail":false,"on_crosstowner":false,"on_rle":false,"exists_today":true,"wheelchair":1},{"id":"woodstock-1b70","name":"Woodstock","lat":42.3169,"lon":-88.4475,"on_metra":true,"on_cta_rail":false,"on_crosstowner":false,"on_rle":false,"exists_today":true,"wheelchair":1},{"id":"worth-1bd5","name":"Worth","lat":41.6914,"lon":-87.7958,"on_metra":true,"on_cta_rail":false,"on_crosstowner":false,"on_rle":false,"exists_today":true,"wheelchair":1},{"id":"wrightwood-1b51","name":"Wrightwood","lat":41.7489,"lon":-87.7036,"on_metra":true,"on_cta_rail":false,"on_crosstowner":false,"on_rle":false,"exists_today":true,"wheelchair":1},{"id":"zion-1b32","name":"Zion","lat":42.4492,"lon":-87.8181,"on_metra":true,"on_cta_rail":false,"on_crosstowner":false,"on_rle":false,"exists_today":true,"wheelchair":1}]
